Workbook

Sheet Dashboard
B1: Data Center Cooling Water Management — M&E Dashboard
B2: 50 MW IT design case · US customary units · yellow = input, green = live formula
B5: Scenario & source controls
B6: Water source | C6: Municipal Potable | E6: Dropdown — pulls Source Library column
B7: Active scenario (Mass Balance view) | C7: Corrugated Fill + High CoC | E7: Dropdown — drives the Process Flow Mass Balance sheet
B8: IT load | C8: 50 | D8: MW
B9: Design wet-bulb temperature | C9: 76 | D9: °F
B10: Average IT utilization | C10: 0.8 | D10: -
B11: RO / IX demineralization on (1/0) | C11: 0 | D11: - | E11: Skippable demineralization step
B13: Scenario levers
B14: Lever | C14: Current Baseline | D14: Corrugated Fill + High CoC | E14: Unit
B15: Target cycles of concentration (2–10) | C15: 4 | D15: 10 | E15: cycles | F15: Clipped by LEED/LSI/drift limits
B16: Blowdown recovery RO on (1/0) | C16: 0 | D16: 1 | E16: -
B18: Key performance indicators
B19: KPI | C19: Current Baseline | D19: Optimized | E19: Δ (Opt − Base) | F19: Unit
B20: Cooling load | C20: ='Cooling Tower & Corrugated Fill'!$C$46 | D20: ='Cooling Tower & Corrugated Fill'!$D$46 | E20: =D20-C20 | F20: MW
B21: Cooling load | C21: ='Cooling Tower & Corrugated Fill'!$C$47 | D21: ='Cooling Tower & Corrugated Fill'!$D$47 | E21: =D21-C21 | F21: tons
B22: Tower heat-rejection load | C22: ='Cooling Tower & Corrugated Fill'!$C$57 | D22: ='Cooling Tower & Corrugated Fill'!$D$57 | E22: =D22-C22 | F22: tons
B23: Chiller COP | C23: ='Cooling Tower & Corrugated Fill'!$C$54 | D23: ='Cooling Tower & Corrugated Fill'!$D$54 | E23: =D23-C23 | F23: -
B24: Tower approach | C24: ='Cooling Tower & Corrugated Fill'!$C$50 | D24: ='Cooling Tower & Corrugated Fill'!$D$50 | E24: =D24-C24 | F24: °F
B25: Cycles of concentration (operating) | C25: ='Cooling Tower & Corrugated Fill'!$C$75 | D25: ='Cooling Tower & Corrugated Fill'!$D$75 | E25: =D25-C25 | F25: cycles
B26: Raw water intake | C26: ='Cooling Tower & Corrugated Fill'!$C$86 | D26: ='Cooling Tower & Corrugated Fill'!$D$86 | E26: =D26-C26 | F26: gpd
B27: Raw water intake | C27: ='Cooling Tower & Corrugated Fill'!$C$87 | D27: ='Cooling Tower & Corrugated Fill'!$D$87 | E27: =D27-C27 | F27: m³/d
B28: Evaporation loss | C28: ='Cooling Tower & Corrugated Fill'!$C$60 | D28: ='Cooling Tower & Corrugated Fill'!$D$60 | E28: =D28-C28 | F28: gpd
B29: Drift loss | C29: ='Cooling Tower & Corrugated Fill'!$C$61 | D29: ='Cooling Tower & Corrugated Fill'!$D$61 | E29: =D29-C29 | F29: gpd
B30: Blowdown (bleed-off) | C30: ='Cooling Tower & Corrugated Fill'!$C$80 | D30: ='Cooling Tower & Corrugated Fill'!$D$80 | E30: =D30-C30 | F30: gpd
B31: Total discharge to sewer | C31: ='Cooling Tower & Corrugated Fill'!$C$89 | D31: ='Cooling Tower & Corrugated Fill'!$D$89 | E31: =D31-C31 | F31: gpd
B32: WUE (water usage effectiveness) | C32: ='Cooling Tower & Corrugated Fill'!$C$90 | D32: ='Cooling Tower & Corrugated Fill'!$D$90 | E32: =D32-C32 | F32: L/kWh IT
B33: Cooling + water plant power | C33: ='Pumping & Fan Hydraulics'!$C$47 | D33: ='Pumping & Fan Hydraulics'!$D$47 | E33: =D33-C33 | F33: kW
B34: Cooling share of PUE | C34: ='Pumping & Fan Hydraulics'!$C$48 | D34: ='Pumping & Fan Hydraulics'!$D$48 | E34: =D34-C34 | F34: -
B35: PUE (incl. other overhead) | C35: ='Pumping & Fan Hydraulics'!$C$49 | D35: ='Pumping & Fan Hydraulics'!$D$49 | E35: =D35-C35 | F35: -
B36: Water-system energy intensity | C36: ='Pumping & Fan Hydraulics'!$C$50 | D36: ='Pumping & Fan Hydraulics'!$D$50 | E36: =D36-C36 | F36: kWh/m³
B37: Annual operating cost (incl. carbon) | C37: ='Financial & LCC Analysis'!$C$51 | D37: ='Financial & LCC Analysis'!$D$51 | E37: =D37-C37 | F37: $/yr
B38: CO₂e emissions | C38: ='Financial & LCC Analysis'!$C$41 | D38: ='Financial & LCC Analysis'!$D$41 | E38: =D38-C38 | F38: t/yr
B39: LEED v4 WE cooling-tower points | C39: ='Cooling Tower & Corrugated Fill'!$C$125 | D39: ='Cooling Tower & Corrugated Fill'!$D$125 | E39: =D39-C39 | F39: pts
B40: Legionella annual inhalation risk | C40: ='Disinfection & Microbial Risk'!$C$68 | D40: ='Disinfection & Microbial Risk'!$D$68 | E40: =D40-C40 | F40: per yr
B42: Compliance & engineering checks
B43: Check | C43: Current Baseline | D43: Optimized | F43: Basis
B44: CoC limiting constraint | C44: ="Limited by "&'Cooling Tower & Corrugated Fill'!$C$74 | D44: ="Limited by "&'Cooling Tower & Corrugated Fill'!$D$74 | F44: LEED / LSI / drift / target
B45: CoC feasible with this source | C45: =IF('Cooling Tower & Corrugated Fill'!$C$73>='Cooling Tower & Corrugated Fill'!$C$15,"✅ Feasible","❌ Enable RO/IX") | D45: =IF('Cooling Tower & Corrugated Fill'!$D$73>='Cooling Tower & Corrugated Fill'!$C$15,"✅ Feasible","❌ Enable RO/IX") | F45: ≥ min CoC
B46: Recirc silica | C46: =IF('Cooling Tower & Corrugated Fill'!$F$97>'Cooling Tower & Corrugated Fill'!$C$18,"❌ Blowdown alert","✅ "&TEXT('Cooling Tower & Corrugated Fill'!$F$97,"0")&" mg/L") | D46: =IF('Cooling Tower & Corrugated Fill'!$K$97>'Cooling Tower & Corrugated Fill'!$C$18,"❌ Blowdown alert","✅ "&TEXT('Cooling Tower & Corrugated Fill'!$K$97,"0")&" mg/L") | F46: >150 mg/L alert
B47: Recirc LSI (hot water) | C47: =IF('Cooling Tower & Corrugated Fill'!$C$117>'Cooling Tower & Corrugated Fill'!$C$16,"❌ ","✅ ")&TEXT('Cooling Tower & Corrugated Fill'!$C$117,"0.00") | D47: =IF('Cooling Tower & Corrugated Fill'!$D$117>'Cooling Tower & Corrugated Fill'!$C$16,"❌ ","✅ ")&TEXT('Cooling Tower & Corrugated Fill'!$D$117,"0.00") | F47: ≤ inhibitor ceiling
B48: LEED condenser limits | C48: =IF('Cooling Tower & Corrugated Fill'!$C$122=1,"✅ All within","❌ Exceeded") | D48: =IF('Cooling Tower & Corrugated Fill'!$D$122=1,"✅ All within","❌ Exceeded") | F48: LEED v4 Table 1
B49: Legionella Py ≤ target | C49: =IF('Disinfection & Microbial Risk'!$C$68<='Disinfection & Microbial Risk'!$C$41,"✅ ","❌ ")&TEXT('Disinfection & Microbial Risk'!$C$68,"0.0E+00") | D49: =IF('Disinfection & Microbial Risk'!$D$68<='Disinfection & Microbial Risk'!$C$41,"✅ ","❌ ")&TEXT('Disinfection & Microbial Risk'!$D$68,"0.0E+00") | F49: 1e-4 /yr
B50: Ingestion QMRA (all pathogens) | C50: =IF('Disinfection & Microbial Risk'!$C$52=1,"✅ Py ≤ target","❌ LRV < LRT") | D50: =IF('Disinfection & Microbial Risk'!$D$52=1,"✅ Py ≤ target","❌ LRV < LRT") | F50: Beta-Poisson / exp.
B51: Pumps in HI 9.6.3 POR | C51: =IF('Pumping & Fan Hydraulics'!$C$51=1,"✅ In POR","❌ Outside POR") | D51: =IF('Pumping & Fan Hydraulics'!$D$51=1,"✅ In POR","❌ Outside POR") | F51: 0.7–1.2 × Q_BEP
B52: System water balance closes | C52: =IF(ABS('Cooling Tower & Corrugated Fill'!$C$86-'Cooling Tower & Corrugated Fill'!$C$60-'Cooling Tower & Corrugated Fill'!$C$61-'Cooling Tower & Corrugated Fill'!$C$89)<1,"✅ Closed","❌ Error") | D52: =IF(ABS('Cooling Tower & Corrugated Fill'!$D$86-'Cooling Tower & Corrugated Fill'!$D$60-'Cooling Tower & Corrugated Fill'!$D$61-'Cooling Tower & Corrugated Fill'!$D$89)<1,"✅ Closed","❌ Error") | F52: Intake = E + D + sewer
B54: Upgrade investment (Baseline → Optimized)
B55: CapEx (fill + eliminators + BD-RO + install) | C55: ='Financial & LCC Analysis'!$C$59 | D55: $
B56: Year-1 net operating savings | C56: ='Financial & LCC Analysis'!$C$52 | D56: $/yr
B57: NPV | C57: ='Financial & LCC Analysis'!$C$75 | D57: $
B58: IRR | C58: ='Financial & LCC Analysis'!$C$77 | D58: -
B59: Discounted break-even (BEP) | C59: ='Financial & LCC Analysis'!$C$78 | D59: years
B60: Simple payback (SPBT) | C60: ='Financial & LCC Analysis'!$C$79 | D60: years
B62: Water losses breakdown
B63: Stream | C63: Current Baseline | D63: Optimized | F63: Unit
B64: Evaporation | C64: ='Cooling Tower & Corrugated Fill'!$C$60 | D64: ='Cooling Tower & Corrugated Fill'!$D$60 | F64: gpd
B65: Drift | C65: ='Cooling Tower & Corrugated Fill'!$C$61 | D65: ='Cooling Tower & Corrugated Fill'!$D$61 | F65: gpd
B66: Blowdown / brine to sewer | C66: ='Cooling Tower & Corrugated Fill'!$C$83 | D66: ='Cooling Tower & Corrugated Fill'!$D$83 | F66: gpd
B67: Treatment rejects | C67: ='Cooling Tower & Corrugated Fill'!$C$88 | D67: ='Cooling Tower & Corrugated Fill'!$D$88 | F67: gpd
B69: Annual cost breakdown
B70: Cost item | C70: Current Baseline | D70: Optimized | F70: Unit
B71: Water purchase | C71: ='Financial & LCC Analysis'!$C$45 | D71: ='Financial & LCC Analysis'!$D$45 | F71: $/yr
B72: Sewer | C72: ='Financial & LCC Analysis'!$C$46 | D72: ='Financial & LCC Analysis'!$D$46 | F72: $/yr
B73: Electricity | C73: ='Financial & LCC Analysis'!$C$47 | D73: ='Financial & LCC Analysis'!$D$47 | F73: $/yr
B74: Chemicals | C74: ='Financial & LCC Analysis'!$C$48 | D74: ='Financial & LCC Analysis'!$D$48 | F74: $/yr
B75: Sludge disposal | C75: ='Financial & LCC Analysis'!$C$49 | D75: ='Financial & LCC Analysis'!$D$49 | F75: $/yr
B76: Carbon (SCC) | C76: ='Financial & LCC Analysis'!$C$50 | D76: ='Financial & LCC Analysis'!$D$50 | F76: $/yr

Sheet Process Flow Mass Balance
B1: Process Flow Mass Balance — node by node
B2: Q_out = Q_in − Q_reject − Q_evap ; C_out,j = [Q_in·C_in,j·(1 − R_j) + Dosing_j] / Q_out | D2: ="Active scenario: "&'Dashboard'!$C$7
B5: 1. Node configuration (toggle steps on/off)
B6: Process step | C6: On (1/0) | D6: Recovery Q_out/Q_in | E6: Energy kWh/kgal | F6: LRV virus | G6: LRV protozoa | H6: LRV bacteria | I6: pH out (blank = pass) | J6: Effective recovery | K6: Relative inflow Q_in/Q_intake | L6: Energy used kWh/kgal
B7: Raw Water Intake | C7: 1 | D7: 1 | E7: 1.5 | F7: 0 | G7: 0 | H7: 0 | J7: =IF(C7=1,D7,1) | K7: 1 | L7: =IF(C7=1,E7,0)
B8: Coagulation / Flocculation / Sedimentation | C8: 1 | D8: 0.98 | E8: 0.1 | F8: 1 | G8: 0.5 | H8: 1 | J8: =IF(C8=1,D8,1) | K8: =K7*J7 | L8: =IF(C8=1,E8,0)
B9: Multi-Media Filtration | C9: 1 | D9: 0.97 | E9: 0.1 | F9: 1 | G9: 2 | H9: 1 | J9: =IF(C9=1,D9,1) | K9: =K8*J8 | L9: =IF(C9=1,E9,0)
B10: Ultrafiltration | C10: 1 | D10: 0.95 | E10: 0.4 | F10: 4 | G10: 4 | H10: 4 | J10: =IF(C10=1,D10,1) | K10: =K9*J9 | L10: =IF(C10=1,E10,0)
B11: RO / IX Demineralization | C11: ='Dashboard'!$C$11 | D11: 0.8 | F11: 1.5 | G11: 1.5 | H11: 1.5 | I11: 6.5 | J11: =IF(C11=1,D11,1) | K11: =K10*J10 | L11: =IF(C11=1,IF(ISNUMBER(E11),E11,(0.3+0.1*'Process Flow Mass Balance'!$G$54/1000)*1000*0.00378541),0)
B12: Chlorine Contact (CT) | C12: 1 | D12: 1 | E12: 0.05 | F12: 0 | G12: 0 | H12: 0 | J12: =IF(C12=1,D12,1) | K12: =K11*J11 | L12: =IF(C12=1,E12,0)
B14: Overall train recovery Π(effective recovery) | C14: =PRODUCT(J7:J12) | D14: -
B15: Treatment energy per gallon of intake | C15: =SUMPRODUCT('Process Flow Mass Balance'!$L$7:$L$12,'Process Flow Mass Balance'!$K$7:$K$12)/1000 | D15: kWh/gal | E15: RO blank energy → 0.3 + 0.1·TDS(g/L) kWh/m³ (screening)
B17: 2. Coagulation / sedimentation — Stokes' law settling
B18: Floc particle diameter | C18: 150 | D18: µm
B19: Particle density ρp | C19: 1065 | D19: kg/m³
B20: Water density ρw | C20: 1000 | D20: kg/m³
B21: Dynamic viscosity μ (15 °C) | C21: 0.00113 | D21: Pa·s
B22: Clarifier overflow rate | C22: 1.5 | D22: m/h
B23: Design TSS removal | C23: 0.9 | D23: -
B24: Settling velocity v_s = g(ρp − ρw)d²/(18μ) | C24: =9.81*('Process Flow Mass Balance'!$C$19-'Process Flow Mass Balance'!$C$20)*('Process Flow Mass Balance'!$C$18*0.000001)^2/(18*'Process Flow Mass Balance'!$C$21) | D24: m/s
B25: Settling velocity | C25: ='Process Flow Mass Balance'!$C$24*3600 | D25: m/h
B26: Achieved TSS removal = R_design × MIN(1, v_s/SOR) | C26: ='Process Flow Mass Balance'!$C$23*MIN(1,'Process Flow Mass Balance'!$C$25/'Process Flow Mass Balance'!$C$22) | D26: -
B27: Alum dose | C27: 10 | D27: mg/L
B29: 3. Removal fraction R_j (mass to waste) — RO row = 1 − Y·(1 − rejection)
B30: Process step | C30: EC | D30: TDS | E30: SiO₂ | F30: Na⁺ | G30: Ca²⁺ | H30: Mg²⁺ | I30: Cl⁻ | J30: PO₄³⁻ | K30: SO₄²⁻ | L30: Alk (CaCO₃) | M30: Free Cl₂ | N30: TSS | O30: BOD₅ | P30: COD
B31: RO membrane rejection (input) | C31: 0.99 | D31: 0.99 | E31: 0.98 | F31: 0.985 | G31: 0.995 | H31: 0.995 | I31: 0.985 | J31: 0.995 | K31: 0.995 | L31: 0.97 | M31: 1 | N31: 1 | O31: 0.9 | P31: 0.9
B32: Raw Water Intake | C32: 0 | D32: 0 | E32: 0 | F32: 0 | G32: 0 | H32: 0 | I32: 0 | J32: 0 | K32: 0 | L32: 0 | M32: 0 | N32: 0 | O32: 0 | P32: 0
B33: Coagulation / Flocculation / Sedimentation | C33: 0 | D33: 0 | E33: 0 | F33: 0 | G33: 0 | H33: 0 | I33: 0 | J33: 0.8 | K33: 0 | L33: 0 | M33: 0 | N33: ='Process Flow Mass Balance'!$C$26 | O33: 0.3 | P33: 0.3
B34: Multi-Media Filtration | C34: 0 | D34: 0 | E34: 0 | F34: 0 | G34: 0 | H34: 0 | I34: 0 | J34: 0 | K34: 0 | L34: 0 | M34: 0 | N34: 0.8 | O34: 0.1 | P34: 0.1
B35: Ultrafiltration | C35: 0 | D35: 0 | E35: 0 | F35: 0 | G35: 0 | H35: 0 | I35: 0 | J35: 0 | K35: 0 | L35: 0 | M35: 0 | N35: 0.999 | O35: 0.2 | P35: 0.15
B36: RO / IX Demineralization | C36: =1-'Process Flow Mass Balance'!$D$11*(1-'Process Flow Mass Balance'!$C$31) | D36: =1-'Process Flow Mass Balance'!$D$11*(1-'Process Flow Mass Balance'!$D$31) | E36: =1-'Process Flow Mass Balance'!$D$11*(1-'Process Flow Mass Balance'!$E$31) | F36: =1-'Process Flow Mass Balance'!$D$11*(1-'Process Flow Mass Balance'!$F$31) | G36: =1-'Process Flow Mass Balance'!$D$11*(1-'Process Flow Mass Balance'!$G$31) | H36: =1-'Process Flow Mass Balance'!$D$11*(1-'Process Flow Mass Balance'!$H$31) | I36: =1-'Process Flow Mass Balance'!$D$11*(1-'Process Flow Mass Balance'!$I$31) | J36: =1-'Process Flow Mass Balance'!$D$11*(1-'Process Flow Mass Balance'!$J$31) | K36: =1-'Process Flow Mass Balance'!$D$11*(1-'Process Flow Mass Balance'!$K$31) | L36: =1-'Process Flow Mass Balance'!$D$11*(1-'Process Flow Mass Balance'!$L$31) | M36: =1-'Process Flow Mass Balance'!$D$11*(1-'Process Flow Mass Balance'!$M$31) | N36: =1-'Process Flow Mass Balance'!$D$11*(1-'Process Flow Mass Balance'!$N$31) | O36: =1-'Process Flow Mass Balance'!$D$11*(1-'Process Flow Mass Balance'!$O$31) | P36: =1-'Process Flow Mass Balance'!$D$11*(1-'Process Flow Mass Balance'!$P$31)
B37: Chlorine Contact (CT) | C37: 0 | D37: 0 | E37: 0 | F37: 0 | G37: 0 | H37: 0 | I37: 0 | J37: 0 | K37: 0 | L37: 0 | M37: 0.5 | N37: 0 | O37: 0 | P37: 0
B39: 4. Chemical dosing (mg/L of node inflow; negative = consumed)
B40: Process step | C40: EC | D40: TDS | E40: SiO₂ | F40: Na⁺ | G40: Ca²⁺ | H40: Mg²⁺ | I40: Cl⁻ | J40: PO₄³⁻ | K40: SO₄²⁻ | L40: Alk (CaCO₃) | M40: Free Cl₂ | N40: TSS | O40: BOD₅ | P40: COD
B41: Raw Water Intake | C41: 0 | D41: 0 | E41: 0 | F41: 0 | G41: 0 | H41: 0 | I41: 0 | J41: 0 | K41: 0 | L41: 0 | M41: 0 | N41: 0 | O41: 0 | P41: 0
B42: Coagulation / Flocculation / Sedimentation | C42: 6 | D42: 4 | E42: 0 | F42: 0 | G42: 0 | H42: 0 | I42: 0 | J42: 0 | K42: 4.85 | L42: -5 | M42: 0 | N42: 0 | O42: 0 | P42: 0
B43: Multi-Media Filtration | C43: 0 | D43: 0 | E43: 0 | F43: 0 | G43: 0 | H43: 0 | I43: 0 | J43: 0 | K43: 0 | L43: 0 | M43: 0 | N43: 0 | O43: 0 | P43: 0
B44: Ultrafiltration | C44: 0 | D44: 0 | E44: 0 | F44: 0 | G44: 0 | H44: 0 | I44: 0 | J44: 0 | K44: 0 | L44: 0 | M44: 0 | N44: 0 | O44: 0 | P44: 0
B45: RO / IX Demineralization | C45: 0 | D45: 0 | E45: 0 | F45: 0 | G45: 0 | H45: 0 | I45: 0 | J45: 0 | K45: 0 | L45: 0 | M45: 0 | N45: 0 | O45: 0 | P45: 0
B46: Chlorine Contact (CT) | C46: 4 | D46: 2.5 | E46: 0 | F46: 1 | G46: 0 | H46: 0 | I46: 1.5 | J46: 0 | K46: 0 | L46: 0 | M46: 1.5 | N46: 0 | O46: 0 | P46: 0
B48: 5. Flow & quality matrix (active scenario) — C_out,j = [Q_in·C_in,j·(1−R_j) + Dosing_j]/Q_out with Q per unit intake
B49: Process step | C49: On | D49: Inflow Q_in (gpd) | E49: In pH | F49: In EC | G49: In TDS | H49: In SiO₂ | I49: In Na⁺ | J49: In Ca²⁺ | K49: In Mg²⁺ | L49: In Cl⁻ | M49: In PO₄³⁻ | N49: In SO₄²⁻ | O49: In Alk (CaCO₃) | P49: In Free Cl₂ | Q49: In TSS | R49: In BOD₅ | S49: In COD | T49: Reject / losses (gpd) | U49: Evaporation (gpd) | V49: Outflow Q_out (gpd) | W49: Out pH | X49: Out EC | Y49: Out TDS | Z49: Out SiO₂ | AA49: Out Na⁺ | AB49: Out Ca²⁺ | AC49: Out Mg²⁺ | AD49: Out Cl⁻ | AE49: Out PO₄³⁻ | AF49: Out SO₄²⁻ | AG49: Out Alk (CaCO₃) | AH49: Out Free Cl₂ | AI49: Out TSS | AJ49: Out BOD₅ | AK49: Out COD | AL49: Flow balance check | AM49: TSS removed (kg/gal intake)
B50: Raw Water Intake | C50: ='Process Flow Mass Balance'!$C$7 | D50: =IF('Dashboard'!$C$7='Dashboard'!$C$14,'Cooling Tower & Corrugated Fill'!$C$84,'Cooling Tower & Corrugated Fill'!$D$84)/'Process Flow Mass Balance'!$C$14 | E50: ='Source Library'!$J$7 | F50: ='Source Library'!$J$8 | G50: ='Source Library'!$J$9 | H50: ='Source Library'!$J$10 | I50: ='Source Library'!$J$11 | J50: ='Source Library'!$J$12 | K50: ='Source Library'!$J$13 | L50: ='Source Library'!$J$14 | M50: ='Source Library'!$J$15 | N50: ='Source Library'!$J$16 | O50: ='Source Library'!$J$17 | P50: ='Source Library'!$J$18 | Q50: ='Source Library'!$J$19 | R50: ='Source Library'!$J$20 | S50: ='Source Library'!$J$21 | T50: =D50-V50 | U50: 0 | V50: =D50*'Process Flow Mass Balance'!$J$7 | W50: =IF(AND(C50=1,ISNUMBER('Process Flow Mass Balance'!$I$7)),'Process Flow Mass Balance'!$I$7,E50) | X50: =IF(C50=1,MAX(0,('Process Flow Mass Balance'!$K$7*F50*(1-'Process Flow Mass Balance'!$C$32)+'Process Flow Mass Balance'!$C$41*'Process Flow Mass Balance'!$K$7)/('Process Flow Mass Balance'!$K$7*'Process Flow Mass Balance'!$J$7)),F50) | Y50: =IF(C50=1,MAX(0,('Process Flow Mass Balance'!$K$7*G50*(1-'Process Flow Mass Balance'!$D$32)+'Process Flow Mass Balance'!$D$41*'Process Flow Mass Balance'!$K$7)/('Process Flow Mass Balance'!$K$7*'Process Flow Mass Balance'!$J$7)),G50) | Z50: =IF(C50=1,MAX(0,('Process Flow Mass Balance'!$K$7*H50*(1-'Process Flow Mass Balance'!$E$32)+'Process Flow Mass Balance'!$E$41*'Process Flow Mass Balance'!$K$7)/('Process Flow Mass Balance'!$K$7*'Process Flow Mass Balance'!$J$7)),H50) | AA50: =IF(C50=1,MAX(0,('Process Flow Mass Balance'!$K$7*I50*(1-'Process Flow Mass Balance'!$F$32)+'Process Flow Mass Balance'!$F$41*'Process Flow Mass Balance'!$K$7)/('Process Flow Mass Balance'!$K$7*'Process Flow Mass Balance'!$J$7)),I50) | AB50: =IF(C50=1,MAX(0,('Process Flow Mass Balance'!$K$7*J50*(1-'Process Flow Mass Balance'!$G$32)+'Process Flow Mass Balance'!$G$41*'Process Flow Mass Balance'!$K$7)/('Process Flow Mass Balance'!$K$7*'Process Flow Mass Balance'!$J$7)),J50) | AC50: =IF(C50=1,MAX(0,('Process Flow Mass Balance'!$K$7*K50*(1-'Process Flow Mass Balance'!$H$32)+'Process Flow Mass Balance'!$H$41*'Process Flow Mass Balance'!$K$7)/('Process Flow Mass Balance'!$K$7*'Process Flow Mass Balance'!$J$7)),K50) | AD50: =IF(C50=1,MAX(0,('Process Flow Mass Balance'!$K$7*L50*(1-'Process Flow Mass Balance'!$I$32)+'Process Flow Mass Balance'!$I$41*'Process Flow Mass Balance'!$K$7)/('Process Flow Mass Balance'!$K$7*'Process Flow Mass Balance'!$J$7)),L50) | AE50: =IF(C50=1,MAX(0,('Process Flow Mass Balance'!$K$7*M50*(1-'Process Flow Mass Balance'!$J$32)+'Process Flow Mass Balance'!$J$41*'Process Flow Mass Balance'!$K$7)/('Process Flow Mass Balance'!$K$7*'Process Flow Mass Balance'!$J$7)),M50) | AF50: =IF(C50=1,MAX(0,('Process Flow Mass Balance'!$K$7*N50*(1-'Process Flow Mass Balance'!$K$32)+'Process Flow Mass Balance'!$K$41*'Process Flow Mass Balance'!$K$7)/('Process Flow Mass Balance'!$K$7*'Process Flow Mass Balance'!$J$7)),N50) | AG50: =IF(C50=1,MAX(0,('Process Flow Mass Balance'!$K$7*O50*(1-'Process Flow Mass Balance'!$L$32)+'Process Flow Mass Balance'!$L$41*'Process Flow Mass Balance'!$K$7)/('Process Flow Mass Balance'!$K$7*'Process Flow Mass Balance'!$J$7)),O50) | AH50: =IF(C50=1,MAX(0,('Process Flow Mass Balance'!$K$7*P50*(1-'Process Flow Mass Balance'!$M$32)+'Process Flow Mass Balance'!$M$41*'Process Flow Mass Balance'!$K$7)/('Process Flow Mass Balance'!$K$7*'Process Flow Mass Balance'!$J$7)),P50) | AI50: =IF(C50=1,MAX(0,('Process Flow Mass Balance'!$K$7*Q50*(1-'Process Flow Mass Balance'!$N$32)+'Process Flow Mass Balance'!$N$41*'Process Flow Mass Balance'!$K$7)/('Process Flow Mass Balance'!$K$7*'Process Flow Mass Balance'!$J$7)),Q50) | AJ50: =IF(C50=1,MAX(0,('Process Flow Mass Balance'!$K$7*R50*(1-'Process Flow Mass Balance'!$O$32)+'Process Flow Mass Balance'!$O$41*'Process Flow Mass Balance'!$K$7)/('Process Flow Mass Balance'!$K$7*'Process Flow Mass Balance'!$J$7)),R50) | AK50: =IF(C50=1,MAX(0,('Process Flow Mass Balance'!$K$7*S50*(1-'Process Flow Mass Balance'!$P$32)+'Process Flow Mass Balance'!$P$41*'Process Flow Mass Balance'!$K$7)/('Process Flow Mass Balance'!$K$7*'Process Flow Mass Balance'!$J$7)),S50) | AL50: =IF(ABS(D50-T50-U50-V50)<0.001,"✅","❌") | AM50: =IF(C50=1,'Process Flow Mass Balance'!$K$7*Q50*'Process Flow Mass Balance'!$N$32,0)*3.78541/1000000
B51: Coagulation / Flocculation / Sedimentation | C51: ='Process Flow Mass Balance'!$C$8 | D51: ='Process Flow Mass Balance'!$V$50 | E51: ='Process Flow Mass Balance'!$W$50 | F51: ='Process Flow Mass Balance'!$X$50 | G51: ='Process Flow Mass Balance'!$Y$50 | H51: ='Process Flow Mass Balance'!$Z$50 | I51: ='Process Flow Mass Balance'!$AA$50 | J51: ='Process Flow Mass Balance'!$AB$50 | K51: ='Process Flow Mass Balance'!$AC$50 | L51: ='Process Flow Mass Balance'!$AD$50 | M51: ='Process Flow Mass Balance'!$AE$50 | N51: ='Process Flow Mass Balance'!$AF$50 | O51: ='Process Flow Mass Balance'!$AG$50 | P51: ='Process Flow Mass Balance'!$AH$50 | Q51: ='Process Flow Mass Balance'!$AI$50 | R51: ='Process Flow Mass Balance'!$AJ$50 | S51: ='Process Flow Mass Balance'!$AK$50 | T51: =D51-V51 | U51: 0 | V51: =D51*'Process Flow Mass Balance'!$J$8 | W51: =IF(AND(C51=1,ISNUMBER('Process Flow Mass Balance'!$I$8)),'Process Flow Mass Balance'!$I$8,E51) | X51: =IF(C51=1,MAX(0,('Process Flow Mass Balance'!$K$8*F51*(1-'Process Flow Mass Balance'!$C$33)+'Process Flow Mass Balance'!$C$42*'Process Flow Mass Balance'!$K$8)/('Process Flow Mass Balance'!$K$8*'Process Flow Mass Balance'!$J$8)),F51) | Y51: =IF(C51=1,MAX(0,('Process Flow Mass Balance'!$K$8*G51*(1-'Process Flow Mass Balance'!$D$33)+'Process Flow Mass Balance'!$D$42*'Process Flow Mass Balance'!$K$8)/('Process Flow Mass Balance'!$K$8*'Process Flow Mass Balance'!$J$8)),G51) | Z51: =IF(C51=1,MAX(0,('Process Flow Mass Balance'!$K$8*H51*(1-'Process Flow Mass Balance'!$E$33)+'Process Flow Mass Balance'!$E$42*'Process Flow Mass Balance'!$K$8)/('Process Flow Mass Balance'!$K$8*'Process Flow Mass Balance'!$J$8)),H51) | AA51: =IF(C51=1,MAX(0,('Process Flow Mass Balance'!$K$8*I51*(1-'Process Flow Mass Balance'!$F$33)+'Process Flow Mass Balance'!$F$42*'Process Flow Mass Balance'!$K$8)/('Process Flow Mass Balance'!$K$8*'Process Flow Mass Balance'!$J$8)),I51) | AB51: =IF(C51=1,MAX(0,('Process Flow Mass Balance'!$K$8*J51*(1-'Process Flow Mass Balance'!$G$33)+'Process Flow Mass Balance'!$G$42*'Process Flow Mass Balance'!$K$8)/('Process Flow Mass Balance'!$K$8*'Process Flow Mass Balance'!$J$8)),J51) | AC51: =IF(C51=1,MAX(0,('Process Flow Mass Balance'!$K$8*K51*(1-'Process Flow Mass Balance'!$H$33)+'Process Flow Mass Balance'!$H$42*'Process Flow Mass Balance'!$K$8)/('Process Flow Mass Balance'!$K$8*'Process Flow Mass Balance'!$J$8)),K51) | AD51: =IF(C51=1,MAX(0,('Process Flow Mass Balance'!$K$8*L51*(1-'Process Flow Mass Balance'!$I$33)+'Process Flow Mass Balance'!$I$42*'Process Flow Mass Balance'!$K$8)/('Process Flow Mass Balance'!$K$8*'Process Flow Mass Balance'!$J$8)),L51) | AE51: =IF(C51=1,MAX(0,('Process Flow Mass Balance'!$K$8*M51*(1-'Process Flow Mass Balance'!$J$33)+'Process Flow Mass Balance'!$J$42*'Process Flow Mass Balance'!$K$8)/('Process Flow Mass Balance'!$K$8*'Process Flow Mass Balance'!$J$8)),M51) | AF51: =IF(C51=1,MAX(0,('Process Flow Mass Balance'!$K$8*N51*(1-'Process Flow Mass Balance'!$K$33)+'Process Flow Mass Balance'!$K$42*'Process Flow Mass Balance'!$K$8)/('Process Flow Mass Balance'!$K$8*'Process Flow Mass Balance'!$J$8)),N51) | AG51: =IF(C51=1,MAX(0,('Process Flow Mass Balance'!$K$8*O51*(1-'Process Flow Mass Balance'!$L$33)+'Process Flow Mass Balance'!$L$42*'Process Flow Mass Balance'!$K$8)/('Process Flow Mass Balance'!$K$8*'Process Flow Mass Balance'!$J$8)),O51) | AH51: =IF(C51=1,MAX(0,('Process Flow Mass Balance'!$K$8*P51*(1-'Process Flow Mass Balance'!$M$33)+'Process Flow Mass Balance'!$M$42*'Process Flow Mass Balance'!$K$8)/('Process Flow Mass Balance'!$K$8*'Process Flow Mass Balance'!$J$8)),P51) | AI51: =IF(C51=1,MAX(0,('Process Flow Mass Balance'!$K$8*Q51*(1-'Process Flow Mass Balance'!$N$33)+'Process Flow Mass Balance'!$N$42*'Process Flow Mass Balance'!$K$8)/('Process Flow Mass Balance'!$K$8*'Process Flow Mass Balance'!$J$8)),Q51) | AJ51: =IF(C51=1,MAX(0,('Process Flow Mass Balance'!$K$8*R51*(1-'Process Flow Mass Balance'!$O$33)+'Process Flow Mass Balance'!$O$42*'Process Flow Mass Balance'!$K$8)/('Process Flow Mass Balance'!$K$8*'Process Flow Mass Balance'!$J$8)),R51) | AK51: =IF(C51=1,MAX(0,('Process Flow Mass Balance'!$K$8*S51*(1-'Process Flow Mass Balance'!$P$33)+'Process Flow Mass Balance'!$P$42*'Process Flow Mass Balance'!$K$8)/('Process Flow Mass Balance'!$K$8*'Process Flow Mass Balance'!$J$8)),S51) | AL51: =IF(ABS(D51-T51-U51-V51)<0.001,"✅","❌") | AM51: =IF(C51=1,'Process Flow Mass Balance'!$K$8*Q51*'Process Flow Mass Balance'!$N$33,0)*3.78541/1000000
B52: Multi-Media Filtration | C52: ='Process Flow Mass Balance'!$C$9 | D52: ='Process Flow Mass Balance'!$V$51 | E52: ='Process Flow Mass Balance'!$W$51 | F52: ='Process Flow Mass Balance'!$X$51 | G52: ='Process Flow Mass Balance'!$Y$51 | H52: ='Process Flow Mass Balance'!$Z$51 | I52: ='Process Flow Mass Balance'!$AA$51 | J52: ='Process Flow Mass Balance'!$AB$51 | K52: ='Process Flow Mass Balance'!$AC$51 | L52: ='Process Flow Mass Balance'!$AD$51 | M52: ='Process Flow Mass Balance'!$AE$51 | N52: ='Process Flow Mass Balance'!$AF$51 | O52: ='Process Flow Mass Balance'!$AG$51 | P52: ='Process Flow Mass Balance'!$AH$51 | Q52: ='Process Flow Mass Balance'!$AI$51 | R52: ='Process Flow Mass Balance'!$AJ$51 | S52: ='Process Flow Mass Balance'!$AK$51 | T52: =D52-V52 | U52: 0 | V52: =D52*'Process Flow Mass Balance'!$J$9 | W52: =IF(AND(C52=1,ISNUMBER('Process Flow Mass Balance'!$I$9)),'Process Flow Mass Balance'!$I$9,E52) | X52: =IF(C52=1,MAX(0,('Process Flow Mass Balance'!$K$9*F52*(1-'Process Flow Mass Balance'!$C$34)+'Process Flow Mass Balance'!$C$43*'Process Flow Mass Balance'!$K$9)/('Process Flow Mass Balance'!$K$9*'Process Flow Mass Balance'!$J$9)),F52) | Y52: =IF(C52=1,MAX(0,('Process Flow Mass Balance'!$K$9*G52*(1-'Process Flow Mass Balance'!$D$34)+'Process Flow Mass Balance'!$D$43*'Process Flow Mass Balance'!$K$9)/('Process Flow Mass Balance'!$K$9*'Process Flow Mass Balance'!$J$9)),G52) | Z52: =IF(C52=1,MAX(0,('Process Flow Mass Balance'!$K$9*H52*(1-'Process Flow Mass Balance'!$E$34)+'Process Flow Mass Balance'!$E$43*'Process Flow Mass Balance'!$K$9)/('Process Flow Mass Balance'!$K$9*'Process Flow Mass Balance'!$J$9)),H52) | AA52: =IF(C52=1,MAX(0,('Process Flow Mass Balance'!$K$9*I52*(1-'Process Flow Mass Balance'!$F$34)+'Process Flow Mass Balance'!$F$43*'Process Flow Mass Balance'!$K$9)/('Process Flow Mass Balance'!$K$9*'Process Flow Mass Balance'!$J$9)),I52) | AB52: =IF(C52=1,MAX(0,('Process Flow Mass Balance'!$K$9*J52*(1-'Process Flow Mass Balance'!$G$34)+'Process Flow Mass Balance'!$G$43*'Process Flow Mass Balance'!$K$9)/('Process Flow Mass Balance'!$K$9*'Process Flow Mass Balance'!$J$9)),J52) | AC52: =IF(C52=1,MAX(0,('Process Flow Mass Balance'!$K$9*K52*(1-'Process Flow Mass Balance'!$H$34)+'Process Flow Mass Balance'!$H$43*'Process Flow Mass Balance'!$K$9)/('Process Flow Mass Balance'!$K$9*'Process Flow Mass Balance'!$J$9)),K52) | AD52: =IF(C52=1,MAX(0,('Process Flow Mass Balance'!$K$9*L52*(1-'Process Flow Mass Balance'!$I$34)+'Process Flow Mass Balance'!$I$43*'Process Flow Mass Balance'!$K$9)/('Process Flow Mass Balance'!$K$9*'Process Flow Mass Balance'!$J$9)),L52) | AE52: =IF(C52=1,MAX(0,('Process Flow Mass Balance'!$K$9*M52*(1-'Process Flow Mass Balance'!$J$34)+'Process Flow Mass Balance'!$J$43*'Process Flow Mass Balance'!$K$9)/('Process Flow Mass Balance'!$K$9*'Process Flow Mass Balance'!$J$9)),M52) | AF52: =IF(C52=1,MAX(0,('Process Flow Mass Balance'!$K$9*N52*(1-'Process Flow Mass Balance'!$K$34)+'Process Flow Mass Balance'!$K$43*'Process Flow Mass Balance'!$K$9)/('Process Flow Mass Balance'!$K$9*'Process Flow Mass Balance'!$J$9)),N52) | AG52: =IF(C52=1,MAX(0,('Process Flow Mass Balance'!$K$9*O52*(1-'Process Flow Mass Balance'!$L$34)+'Process Flow Mass Balance'!$L$43*'Process Flow Mass Balance'!$K$9)/('Process Flow Mass Balance'!$K$9*'Process Flow Mass Balance'!$J$9)),O52) | AH52: =IF(C52=1,MAX(0,('Process Flow Mass Balance'!$K$9*P52*(1-'Process Flow Mass Balance'!$M$34)+'Process Flow Mass Balance'!$M$43*'Process Flow Mass Balance'!$K$9)/('Process Flow Mass Balance'!$K$9*'Process Flow Mass Balance'!$J$9)),P52) | AI52: =IF(C52=1,MAX(0,('Process Flow Mass Balance'!$K$9*Q52*(1-'Process Flow Mass Balance'!$N$34)+'Process Flow Mass Balance'!$N$43*'Process Flow Mass Balance'!$K$9)/('Process Flow Mass Balance'!$K$9*'Process Flow Mass Balance'!$J$9)),Q52) | AJ52: =IF(C52=1,MAX(0,('Process Flow Mass Balance'!$K$9*R52*(1-'Process Flow Mass Balance'!$O$34)+'Process Flow Mass Balance'!$O$43*'Process Flow Mass Balance'!$K$9)/('Process Flow Mass Balance'!$K$9*'Process Flow Mass Balance'!$J$9)),R52) | AK52: =IF(C52=1,MAX(0,('Process Flow Mass Balance'!$K$9*S52*(1-'Process Flow Mass Balance'!$P$34)+'Process Flow Mass Balance'!$P$43*'Process Flow Mass Balance'!$K$9)/('Process Flow Mass Balance'!$K$9*'Process Flow Mass Balance'!$J$9)),S52) | AL52: =IF(ABS(D52-T52-U52-V52)<0.001,"✅","❌") | AM52: =IF(C52=1,'Process Flow Mass Balance'!$K$9*Q52*'Process Flow Mass Balance'!$N$34,0)*3.78541/1000000
B53: Ultrafiltration | C53: ='Process Flow Mass Balance'!$C$10 | D53: ='Process Flow Mass Balance'!$V$52 | E53: ='Process Flow Mass Balance'!$W$52 | F53: ='Process Flow Mass Balance'!$X$52 | G53: ='Process Flow Mass Balance'!$Y$52 | H53: ='Process Flow Mass Balance'!$Z$52 | I53: ='Process Flow Mass Balance'!$AA$52 | J53: ='Process Flow Mass Balance'!$AB$52 | K53: ='Process Flow Mass Balance'!$AC$52 | L53: ='Process Flow Mass Balance'!$AD$52 | M53: ='Process Flow Mass Balance'!$AE$52 | N53: ='Process Flow Mass Balance'!$AF$52 | O53: ='Process Flow Mass Balance'!$AG$52 | P53: ='Process Flow Mass Balance'!$AH$52 | Q53: ='Process Flow Mass Balance'!$AI$52 | R53: ='Process Flow Mass Balance'!$AJ$52 | S53: ='Process Flow Mass Balance'!$AK$52 | T53: =D53-V53 | U53: 0 | V53: =D53*'Process Flow Mass Balance'!$J$10 | W53: =IF(AND(C53=1,ISNUMBER('Process Flow Mass Balance'!$I$10)),'Process Flow Mass Balance'!$I$10,E53) | X53: =IF(C53=1,MAX(0,('Process Flow Mass Balance'!$K$10*F53*(1-'Process Flow Mass Balance'!$C$35)+'Process Flow Mass Balance'!$C$44*'Process Flow Mass Balance'!$K$10)/('Process Flow Mass Balance'!$K$10*'Process Flow Mass Balance'!$J$10)),F53) | Y53: =IF(C53=1,MAX(0,('Process Flow Mass Balance'!$K$10*G53*(1-'Process Flow Mass Balance'!$D$35)+'Process Flow Mass Balance'!$D$44*'Process Flow Mass Balance'!$K$10)/('Process Flow Mass Balance'!$K$10*'Process Flow Mass Balance'!$J$10)),G53) | Z53: =IF(C53=1,MAX(0,('Process Flow Mass Balance'!$K$10*H53*(1-'Process Flow Mass Balance'!$E$35)+'Process Flow Mass Balance'!$E$44*'Process Flow Mass Balance'!$K$10)/('Process Flow Mass Balance'!$K$10*'Process Flow Mass Balance'!$J$10)),H53) | AA53: =IF(C53=1,MAX(0,('Process Flow Mass Balance'!$K$10*I53*(1-'Process Flow Mass Balance'!$F$35)+'Process Flow Mass Balance'!$F$44*'Process Flow Mass Balance'!$K$10)/('Process Flow Mass Balance'!$K$10*'Process Flow Mass Balance'!$J$10)),I53) | AB53: =IF(C53=1,MAX(0,('Process Flow Mass Balance'!$K$10*J53*(1-'Process Flow Mass Balance'!$G$35)+'Process Flow Mass Balance'!$G$44*'Process Flow Mass Balance'!$K$10)/('Process Flow Mass Balance'!$K$10*'Process Flow Mass Balance'!$J$10)),J53) | AC53: =IF(C53=1,MAX(0,('Process Flow Mass Balance'!$K$10*K53*(1-'Process Flow Mass Balance'!$H$35)+'Process Flow Mass Balance'!$H$44*'Process Flow Mass Balance'!$K$10)/('Process Flow Mass Balance'!$K$10*'Process Flow Mass Balance'!$J$10)),K53) | AD53: =IF(C53=1,MAX(0,('Process Flow Mass Balance'!$K$10*L53*(1-'Process Flow Mass Balance'!$I$35)+'Process Flow Mass Balance'!$I$44*'Process Flow Mass Balance'!$K$10)/('Process Flow Mass Balance'!$K$10*'Process Flow Mass Balance'!$J$10)),L53) | AE53: =IF(C53=1,MAX(0,('Process Flow Mass Balance'!$K$10*M53*(1-'Process Flow Mass Balance'!$J$35)+'Process Flow Mass Balance'!$J$44*'Process Flow Mass Balance'!$K$10)/('Process Flow Mass Balance'!$K$10*'Process Flow Mass Balance'!$J$10)),M53) | AF53: =IF(C53=1,MAX(0,('Process Flow Mass Balance'!$K$10*N53*(1-'Process Flow Mass Balance'!$K$35)+'Process Flow Mass Balance'!$K$44*'Process Flow Mass Balance'!$K$10)/('Process Flow Mass Balance'!$K$10*'Process Flow Mass Balance'!$J$10)),N53) | AG53: =IF(C53=1,MAX(0,('Process Flow Mass Balance'!$K$10*O53*(1-'Process Flow Mass Balance'!$L$35)+'Process Flow Mass Balance'!$L$44*'Process Flow Mass Balance'!$K$10)/('Process Flow Mass Balance'!$K$10*'Process Flow Mass Balance'!$J$10)),O53) | AH53: =IF(C53=1,MAX(0,('Process Flow Mass Balance'!$K$10*P53*(1-'Process Flow Mass Balance'!$M$35)+'Process Flow Mass Balance'!$M$44*'Process Flow Mass Balance'!$K$10)/('Process Flow Mass Balance'!$K$10*'Process Flow Mass Balance'!$J$10)),P53) | AI53: =IF(C53=1,MAX(0,('Process Flow Mass Balance'!$K$10*Q53*(1-'Process Flow Mass Balance'!$N$35)+'Process Flow Mass Balance'!$N$44*'Process Flow Mass Balance'!$K$10)/('Process Flow Mass Balance'!$K$10*'Process Flow Mass Balance'!$J$10)),Q53) | AJ53: =IF(C53=1,MAX(0,('Process Flow Mass Balance'!$K$10*R53*(1-'Process Flow Mass Balance'!$O$35)+'Process Flow Mass Balance'!$O$44*'Process Flow Mass Balance'!$K$10)/('Process Flow Mass Balance'!$K$10*'Process Flow Mass Balance'!$J$10)),R53) | AK53: =IF(C53=1,MAX(0,('Process Flow Mass Balance'!$K$10*S53*(1-'Process Flow Mass Balance'!$P$35)+'Process Flow Mass Balance'!$P$44*'Process Flow Mass Balance'!$K$10)/('Process Flow Mass Balance'!$K$10*'Process Flow Mass Balance'!$J$10)),S53) | AL53: =IF(ABS(D53-T53-U53-V53)<0.001,"✅","❌") | AM53: =IF(C53=1,'Process Flow Mass Balance'!$K$10*Q53*'Process Flow Mass Balance'!$N$35,0)*3.78541/1000000
B54: RO / IX Demineralization | C54: ='Process Flow Mass Balance'!$C$11 | D54: ='Process Flow Mass Balance'!$V$53 | E54: ='Process Flow Mass Balance'!$W$53 | F54: ='Process Flow Mass Balance'!$X$53 | G54: ='Process Flow Mass Balance'!$Y$53 | H54: ='Process Flow Mass Balance'!$Z$53 | I54: ='Process Flow Mass Balance'!$AA$53 | J54: ='Process Flow Mass Balance'!$AB$53 | K54: ='Process Flow Mass Balance'!$AC$53 | L54: ='Process Flow Mass Balance'!$AD$53 | M54: ='Process Flow Mass Balance'!$AE$53 | N54: ='Process Flow Mass Balance'!$AF$53 | O54: ='Process Flow Mass Balance'!$AG$53 | P54: ='Process Flow Mass Balance'!$AH$53 | Q54: ='Process Flow Mass Balance'!$AI$53 | R54: ='Process Flow Mass Balance'!$AJ$53 | S54: ='Process Flow Mass Balance'!$AK$53 | T54: =D54-V54 | U54: 0 | V54: =D54*'Process Flow Mass Balance'!$J$11 | W54: =IF(AND(C54=1,ISNUMBER('Process Flow Mass Balance'!$I$11)),'Process Flow Mass Balance'!$I$11,E54) | X54: =IF(C54=1,MAX(0,('Process Flow Mass Balance'!$K$11*F54*(1-'Process Flow Mass Balance'!$C$36)+'Process Flow Mass Balance'!$C$45*'Process Flow Mass Balance'!$K$11)/('Process Flow Mass Balance'!$K$11*'Process Flow Mass Balance'!$J$11)),F54) | Y54: =IF(C54=1,MAX(0,('Process Flow Mass Balance'!$K$11*G54*(1-'Process Flow Mass Balance'!$D$36)+'Process Flow Mass Balance'!$D$45*'Process Flow Mass Balance'!$K$11)/('Process Flow Mass Balance'!$K$11*'Process Flow Mass Balance'!$J$11)),G54) | Z54: =IF(C54=1,MAX(0,('Process Flow Mass Balance'!$K$11*H54*(1-'Process Flow Mass Balance'!$E$36)+'Process Flow Mass Balance'!$E$45*'Process Flow Mass Balance'!$K$11)/('Process Flow Mass Balance'!$K$11*'Process Flow Mass Balance'!$J$11)),H54) | AA54: =IF(C54=1,MAX(0,('Process Flow Mass Balance'!$K$11*I54*(1-'Process Flow Mass Balance'!$F$36)+'Process Flow Mass Balance'!$F$45*'Process Flow Mass Balance'!$K$11)/('Process Flow Mass Balance'!$K$11*'Process Flow Mass Balance'!$J$11)),I54) | AB54: =IF(C54=1,MAX(0,('Process Flow Mass Balance'!$K$11*J54*(1-'Process Flow Mass Balance'!$G$36)+'Process Flow Mass Balance'!$G$45*'Process Flow Mass Balance'!$K$11)/('Process Flow Mass Balance'!$K$11*'Process Flow Mass Balance'!$J$11)),J54) | AC54: =IF(C54=1,MAX(0,('Process Flow Mass Balance'!$K$11*K54*(1-'Process Flow Mass Balance'!$H$36)+'Process Flow Mass Balance'!$H$45*'Process Flow Mass Balance'!$K$11)/('Process Flow Mass Balance'!$K$11*'Process Flow Mass Balance'!$J$11)),K54) | AD54: =IF(C54=1,MAX(0,('Process Flow Mass Balance'!$K$11*L54*(1-'Process Flow Mass Balance'!$I$36)+'Process Flow Mass Balance'!$I$45*'Process Flow Mass Balance'!$K$11)/('Process Flow Mass Balance'!$K$11*'Process Flow Mass Balance'!$J$11)),L54) | AE54: =IF(C54=1,MAX(0,('Process Flow Mass Balance'!$K$11*M54*(1-'Process Flow Mass Balance'!$J$36)+'Process Flow Mass Balance'!$J$45*'Process Flow Mass Balance'!$K$11)/('Process Flow Mass Balance'!$K$11*'Process Flow Mass Balance'!$J$11)),M54) | AF54: =IF(C54=1,MAX(0,('Process Flow Mass Balance'!$K$11*N54*(1-'Process Flow Mass Balance'!$K$36)+'Process Flow Mass Balance'!$K$45*'Process Flow Mass Balance'!$K$11)/('Process Flow Mass Balance'!$K$11*'Process Flow Mass Balance'!$J$11)),N54) | AG54: =IF(C54=1,MAX(0,('Process Flow Mass Balance'!$K$11*O54*(1-'Process Flow Mass Balance'!$L$36)+'Process Flow Mass Balance'!$L$45*'Process Flow Mass Balance'!$K$11)/('Process Flow Mass Balance'!$K$11*'Process Flow Mass Balance'!$J$11)),O54) | AH54: =IF(C54=1,MAX(0,('Process Flow Mass Balance'!$K$11*P54*(1-'Process Flow Mass Balance'!$M$36)+'Process Flow Mass Balance'!$M$45*'Process Flow Mass Balance'!$K$11)/('Process Flow Mass Balance'!$K$11*'Process Flow Mass Balance'!$J$11)),P54) | AI54: =IF(C54=1,MAX(0,('Process Flow Mass Balance'!$K$11*Q54*(1-'Process Flow Mass Balance'!$N$36)+'Process Flow Mass Balance'!$N$45*'Process Flow Mass Balance'!$K$11)/('Process Flow Mass Balance'!$K$11*'Process Flow Mass Balance'!$J$11)),Q54) | AJ54: =IF(C54=1,MAX(0,('Process Flow Mass Balance'!$K$11*R54*(1-'Process Flow Mass Balance'!$O$36)+'Process Flow Mass Balance'!$O$45*'Process Flow Mass Balance'!$K$11)/('Process Flow Mass Balance'!$K$11*'Process Flow Mass Balance'!$J$11)),R54) | AK54: =IF(C54=1,MAX(0,('Process Flow Mass Balance'!$K$11*S54*(1-'Process Flow Mass Balance'!$P$36)+'Process Flow Mass Balance'!$P$45*'Process Flow Mass Balance'!$K$11)/('Process Flow Mass Balance'!$K$11*'Process Flow Mass Balance'!$J$11)),S54) | AL54: =IF(ABS(D54-T54-U54-V54)<0.001,"✅","❌") | AM54: =IF(C54=1,'Process Flow Mass Balance'!$K$11*Q54*'Process Flow Mass Balance'!$N$36,0)*3.78541/1000000
B55: Chlorine Contact (CT) | C55: ='Process Flow Mass Balance'!$C$12 | D55: ='Process Flow Mass Balance'!$V$54 | E55: ='Process Flow Mass Balance'!$W$54 | F55: ='Process Flow Mass Balance'!$X$54 | G55: ='Process Flow Mass Balance'!$Y$54 | H55: ='Process Flow Mass Balance'!$Z$54 | I55: ='Process Flow Mass Balance'!$AA$54 | J55: ='Process Flow Mass Balance'!$AB$54 | K55: ='Process Flow Mass Balance'!$AC$54 | L55: ='Process Flow Mass Balance'!$AD$54 | M55: ='Process Flow Mass Balance'!$AE$54 | N55: ='Process Flow Mass Balance'!$AF$54 | O55: ='Process Flow Mass Balance'!$AG$54 | P55: ='Process Flow Mass Balance'!$AH$54 | Q55: ='Process Flow Mass Balance'!$AI$54 | R55: ='Process Flow Mass Balance'!$AJ$54 | S55: ='Process Flow Mass Balance'!$AK$54 | T55: =D55-V55 | U55: 0 | V55: =D55*'Process Flow Mass Balance'!$J$12 | W55: =IF(AND(C55=1,ISNUMBER('Process Flow Mass Balance'!$I$12)),'Process Flow Mass Balance'!$I$12,E55) | X55: =IF(C55=1,MAX(0,('Process Flow Mass Balance'!$K$12*F55*(1-'Process Flow Mass Balance'!$C$37)+'Process Flow Mass Balance'!$C$46*'Process Flow Mass Balance'!$K$12)/('Process Flow Mass Balance'!$K$12*'Process Flow Mass Balance'!$J$12)),F55) | Y55: =IF(C55=1,MAX(0,('Process Flow Mass Balance'!$K$12*G55*(1-'Process Flow Mass Balance'!$D$37)+'Process Flow Mass Balance'!$D$46*'Process Flow Mass Balance'!$K$12)/('Process Flow Mass Balance'!$K$12*'Process Flow Mass Balance'!$J$12)),G55) | Z55: =IF(C55=1,MAX(0,('Process Flow Mass Balance'!$K$12*H55*(1-'Process Flow Mass Balance'!$E$37)+'Process Flow Mass Balance'!$E$46*'Process Flow Mass Balance'!$K$12)/('Process Flow Mass Balance'!$K$12*'Process Flow Mass Balance'!$J$12)),H55) | AA55: =IF(C55=1,MAX(0,('Process Flow Mass Balance'!$K$12*I55*(1-'Process Flow Mass Balance'!$F$37)+'Process Flow Mass Balance'!$F$46*'Process Flow Mass Balance'!$K$12)/('Process Flow Mass Balance'!$K$12*'Process Flow Mass Balance'!$J$12)),I55) | AB55: =IF(C55=1,MAX(0,('Process Flow Mass Balance'!$K$12*J55*(1-'Process Flow Mass Balance'!$G$37)+'Process Flow Mass Balance'!$G$46*'Process Flow Mass Balance'!$K$12)/('Process Flow Mass Balance'!$K$12*'Process Flow Mass Balance'!$J$12)),J55) | AC55: =IF(C55=1,MAX(0,('Process Flow Mass Balance'!$K$12*K55*(1-'Process Flow Mass Balance'!$H$37)+'Process Flow Mass Balance'!$H$46*'Process Flow Mass Balance'!$K$12)/('Process Flow Mass Balance'!$K$12*'Process Flow Mass Balance'!$J$12)),K55) | AD55: =IF(C55=1,MAX(0,('Process Flow Mass Balance'!$K$12*L55*(1-'Process Flow Mass Balance'!$I$37)+'Process Flow Mass Balance'!$I$46*'Process Flow Mass Balance'!$K$12)/('Process Flow Mass Balance'!$K$12*'Process Flow Mass Balance'!$J$12)),L55) | AE55: =IF(C55=1,MAX(0,('Process Flow Mass Balance'!$K$12*M55*(1-'Process Flow Mass Balance'!$J$37)+'Process Flow Mass Balance'!$J$46*'Process Flow Mass Balance'!$K$12)/('Process Flow Mass Balance'!$K$12*'Process Flow Mass Balance'!$J$12)),M55) | AF55: =IF(C55=1,MAX(0,('Process Flow Mass Balance'!$K$12*N55*(1-'Process Flow Mass Balance'!$K$37)+'Process Flow Mass Balance'!$K$46*'Process Flow Mass Balance'!$K$12)/('Process Flow Mass Balance'!$K$12*'Process Flow Mass Balance'!$J$12)),N55) | AG55: =IF(C55=1,MAX(0,('Process Flow Mass Balance'!$K$12*O55*(1-'Process Flow Mass Balance'!$L$37)+'Process Flow Mass Balance'!$L$46*'Process Flow Mass Balance'!$K$12)/('Process Flow Mass Balance'!$K$12*'Process Flow Mass Balance'!$J$12)),O55) | AH55: =IF(C55=1,MAX(0,('Process Flow Mass Balance'!$K$12*P55*(1-'Process Flow Mass Balance'!$M$37)+'Process Flow Mass Balance'!$M$46*'Process Flow Mass Balance'!$K$12)/('Process Flow Mass Balance'!$K$12*'Process Flow Mass Balance'!$J$12)),P55) | AI55: =IF(C55=1,MAX(0,('Process Flow Mass Balance'!$K$12*Q55*(1-'Process Flow Mass Balance'!$N$37)+'Process Flow Mass Balance'!$N$46*'Process Flow Mass Balance'!$K$12)/('Process Flow Mass Balance'!$K$12*'Process Flow Mass Balance'!$J$12)),Q55) | AJ55: =IF(C55=1,MAX(0,('Process Flow Mass Balance'!$K$12*R55*(1-'Process Flow Mass Balance'!$O$37)+'Process Flow Mass Balance'!$O$46*'Process Flow Mass Balance'!$K$12)/('Process Flow Mass Balance'!$K$12*'Process Flow Mass Balance'!$J$12)),R55) | AK55: =IF(C55=1,MAX(0,('Process Flow Mass Balance'!$K$12*S55*(1-'Process Flow Mass Balance'!$P$37)+'Process Flow Mass Balance'!$P$46*'Process Flow Mass Balance'!$K$12)/('Process Flow Mass Balance'!$K$12*'Process Flow Mass Balance'!$J$12)),S55) | AL55: =IF(ABS(D55-T55-U55-V55)<0.001,"✅","❌") | AM55: =IF(C55=1,'Process Flow Mass Balance'!$K$12*Q55*'Process Flow Mass Balance'!$N$37,0)*3.78541/1000000
B56: Cooling Tower (recirculation → blowdown) | C56: 1 | D56: =IF('Dashboard'!$C$7='Dashboard'!$C$14,'Cooling Tower & Corrugated Fill'!$C$85,'Cooling Tower & Corrugated Fill'!$D$85) | E56: =IF('Dashboard'!$C$7='Dashboard'!$C$14,'Cooling Tower & Corrugated Fill'!$I$94,'Cooling Tower & Corrugated Fill'!$N$94) | F56: =IF('Dashboard'!$C$7='Dashboard'!$C$14,'Cooling Tower & Corrugated Fill'!$I$95,'Cooling Tower & Corrugated Fill'!$N$95) | G56: =IF('Dashboard'!$C$7='Dashboard'!$C$14,'Cooling Tower & Corrugated Fill'!$I$96,'Cooling Tower & Corrugated Fill'!$N$96) | H56: =IF('Dashboard'!$C$7='Dashboard'!$C$14,'Cooling Tower & Corrugated Fill'!$I$97,'Cooling Tower & Corrugated Fill'!$N$97) | I56: =IF('Dashboard'!$C$7='Dashboard'!$C$14,'Cooling Tower & Corrugated Fill'!$I$98,'Cooling Tower & Corrugated Fill'!$N$98) | J56: =IF('Dashboard'!$C$7='Dashboard'!$C$14,'Cooling Tower & Corrugated Fill'!$I$99,'Cooling Tower & Corrugated Fill'!$N$99) | K56: =IF('Dashboard'!$C$7='Dashboard'!$C$14,'Cooling Tower & Corrugated Fill'!$I$100,'Cooling Tower & Corrugated Fill'!$N$100) | L56: =IF('Dashboard'!$C$7='Dashboard'!$C$14,'Cooling Tower & Corrugated Fill'!$I$101,'Cooling Tower & Corrugated Fill'!$N$101) | M56: =IF('Dashboard'!$C$7='Dashboard'!$C$14,'Cooling Tower & Corrugated Fill'!$I$102,'Cooling Tower & Corrugated Fill'!$N$102) | N56: =IF('Dashboard'!$C$7='Dashboard'!$C$14,'Cooling Tower & Corrugated Fill'!$I$103,'Cooling Tower & Corrugated Fill'!$N$103) | O56: =IF('Dashboard'!$C$7='Dashboard'!$C$14,'Cooling Tower & Corrugated Fill'!$I$104,'Cooling Tower & Corrugated Fill'!$N$104) | P56: =IF('Dashboard'!$C$7='Dashboard'!$C$14,'Cooling Tower & Corrugated Fill'!$I$105,'Cooling Tower & Corrugated Fill'!$N$105) | Q56: =IF('Dashboard'!$C$7='Dashboard'!$C$14,'Cooling Tower & Corrugated Fill'!$I$106,'Cooling Tower & Corrugated Fill'!$N$106) | R56: =IF('Dashboard'!$C$7='Dashboard'!$C$14,'Cooling Tower & Corrugated Fill'!$I$107,'Cooling Tower & Corrugated Fill'!$N$107) | S56: =IF('Dashboard'!$C$7='Dashboard'!$C$14,'Cooling Tower & Corrugated Fill'!$I$108,'Cooling Tower & Corrugated Fill'!$N$108) | T56: =IF('Dashboard'!$C$7='Dashboard'!$C$14,'Cooling Tower & Corrugated Fill'!$C$61,'Cooling Tower & Corrugated Fill'!$D$61) | U56: =IF('Dashboard'!$C$7='Dashboard'!$C$14,'Cooling Tower & Corrugated Fill'!$C$60,'Cooling Tower & Corrugated Fill'!$D$60) | V56: =IF('Dashboard'!$C$7='Dashboard'!$C$14,'Cooling Tower & Corrugated Fill'!$C$80,'Cooling Tower & Corrugated Fill'!$D$80) | W56: =IF('Dashboard'!$C$7='Dashboard'!$C$14,'Cooling Tower & Corrugated Fill'!$F$94,'Cooling Tower & Corrugated Fill'!$K$94) | X56: =IF('Dashboard'!$C$7='Dashboard'!$C$14,'Cooling Tower & Corrugated Fill'!$F$95,'Cooling Tower & Corrugated Fill'!$K$95) | Y56: =IF('Dashboard'!$C$7='Dashboard'!$C$14,'Cooling Tower & Corrugated Fill'!$F$96,'Cooling Tower & Corrugated Fill'!$K$96) | Z56: =IF('Dashboard'!$C$7='Dashboard'!$C$14,'Cooling Tower & Corrugated Fill'!$F$97,'Cooling Tower & Corrugated Fill'!$K$97) | AA56: =IF('Dashboard'!$C$7='Dashboard'!$C$14,'Cooling Tower & Corrugated Fill'!$F$98,'Cooling Tower & Corrugated Fill'!$K$98) | AB56: =IF('Dashboard'!$C$7='Dashboard'!$C$14,'Cooling Tower & Corrugated Fill'!$F$99,'Cooling Tower & Corrugated Fill'!$K$99) | AC56: =IF('Dashboard'!$C$7='Dashboard'!$C$14,'Cooling Tower & Corrugated Fill'!$F$100,'Cooling Tower & Corrugated Fill'!$K$100) | AD56: =IF('Dashboard'!$C$7='Dashboard'!$C$14,'Cooling Tower & Corrugated Fill'!$F$101,'Cooling Tower & Corrugated Fill'!$K$101) | AE56: =IF('Dashboard'!$C$7='Dashboard'!$C$14,'Cooling Tower & Corrugated Fill'!$F$102,'Cooling Tower & Corrugated Fill'!$K$102) | AF56: =IF('Dashboard'!$C$7='Dashboard'!$C$14,'Cooling Tower & Corrugated Fill'!$F$103,'Cooling Tower & Corrugated Fill'!$K$103) | AG56: =IF('Dashboard'!$C$7='Dashboard'!$C$14,'Cooling Tower & Corrugated Fill'!$F$104,'Cooling Tower & Corrugated Fill'!$K$104) | AH56: =IF('Dashboard'!$C$7='Dashboard'!$C$14,'Cooling Tower & Corrugated Fill'!$F$105,'Cooling Tower & Corrugated Fill'!$K$105) | AI56: =IF('Dashboard'!$C$7='Dashboard'!$C$14,'Cooling Tower & Corrugated Fill'!$F$106,'Cooling Tower & Corrugated Fill'!$K$106) | AJ56: =IF('Dashboard'!$C$7='Dashboard'!$C$14,'Cooling Tower & Corrugated Fill'!$F$107,'Cooling Tower & Corrugated Fill'!$K$107) | AK56: =IF('Dashboard'!$C$7='Dashboard'!$C$14,'Cooling Tower & Corrugated Fill'!$F$108,'Cooling Tower & Corrugated Fill'!$K$108) | AL56: =IF(ABS(D56-T56-U56-V56)<0.01,"✅","❌")
B57: Blowdown Recovery RO (permeate → makeup) | C57: =IF('Dashboard'!$C$7='Dashboard'!$C$14,'Dashboard'!$C$16,'Dashboard'!$D$16) | D57: =IF(C57=1,IF('Dashboard'!$C$7='Dashboard'!$C$14,'Cooling Tower & Corrugated Fill'!$C$80,'Cooling Tower & Corrugated Fill'!$D$80),0) | E57: =IF('Dashboard'!$C$7='Dashboard'!$C$14,'Cooling Tower & Corrugated Fill'!$F$94,'Cooling Tower & Corrugated Fill'!$K$94) | F57: =IF('Dashboard'!$C$7='Dashboard'!$C$14,'Cooling Tower & Corrugated Fill'!$F$95,'Cooling Tower & Corrugated Fill'!$K$95) | G57: =IF('Dashboard'!$C$7='Dashboard'!$C$14,'Cooling Tower & Corrugated Fill'!$F$96,'Cooling Tower & Corrugated Fill'!$K$96) | H57: =IF('Dashboard'!$C$7='Dashboard'!$C$14,'Cooling Tower & Corrugated Fill'!$F$97,'Cooling Tower & Corrugated Fill'!$K$97) | I57: =IF('Dashboard'!$C$7='Dashboard'!$C$14,'Cooling Tower & Corrugated Fill'!$F$98,'Cooling Tower & Corrugated Fill'!$K$98) | J57: =IF('Dashboard'!$C$7='Dashboard'!$C$14,'Cooling Tower & Corrugated Fill'!$F$99,'Cooling Tower & Corrugated Fill'!$K$99) | K57: =IF('Dashboard'!$C$7='Dashboard'!$C$14,'Cooling Tower & Corrugated Fill'!$F$100,'Cooling Tower & Corrugated Fill'!$K$100) | L57: =IF('Dashboard'!$C$7='Dashboard'!$C$14,'Cooling Tower & Corrugated Fill'!$F$101,'Cooling Tower & Corrugated Fill'!$K$101) | M57: =IF('Dashboard'!$C$7='Dashboard'!$C$14,'Cooling Tower & Corrugated Fill'!$F$102,'Cooling Tower & Corrugated Fill'!$K$102) | N57: =IF('Dashboard'!$C$7='Dashboard'!$C$14,'Cooling Tower & Corrugated Fill'!$F$103,'Cooling Tower & Corrugated Fill'!$K$103) | O57: =IF('Dashboard'!$C$7='Dashboard'!$C$14,'Cooling Tower & Corrugated Fill'!$F$104,'Cooling Tower & Corrugated Fill'!$K$104) | P57: =IF('Dashboard'!$C$7='Dashboard'!$C$14,'Cooling Tower & Corrugated Fill'!$F$105,'Cooling Tower & Corrugated Fill'!$K$105) | Q57: =IF('Dashboard'!$C$7='Dashboard'!$C$14,'Cooling Tower & Corrugated Fill'!$F$106,'Cooling Tower & Corrugated Fill'!$K$106) | R57: =IF('Dashboard'!$C$7='Dashboard'!$C$14,'Cooling Tower & Corrugated Fill'!$F$107,'Cooling Tower & Corrugated Fill'!$K$107) | S57: =IF('Dashboard'!$C$7='Dashboard'!$C$14,'Cooling Tower & Corrugated Fill'!$F$108,'Cooling Tower & Corrugated Fill'!$K$108) | T57: =D57-V57 | U57: 0 | V57: =IF(C57=1,IF('Dashboard'!$C$7='Dashboard'!$C$14,'Cooling Tower & Corrugated Fill'!$C$82,'Cooling Tower & Corrugated Fill'!$D$82),0) | W57: =IF(C57=1,IF('Dashboard'!$C$7='Dashboard'!$C$14,'Cooling Tower & Corrugated Fill'!$G$94,'Cooling Tower & Corrugated Fill'!$L$94),0) | X57: =IF(C57=1,IF('Dashboard'!$C$7='Dashboard'!$C$14,'Cooling Tower & Corrugated Fill'!$G$95,'Cooling Tower & Corrugated Fill'!$L$95),0) | Y57: =IF(C57=1,IF('Dashboard'!$C$7='Dashboard'!$C$14,'Cooling Tower & Corrugated Fill'!$G$96,'Cooling Tower & Corrugated Fill'!$L$96),0) | Z57: =IF(C57=1,IF('Dashboard'!$C$7='Dashboard'!$C$14,'Cooling Tower & Corrugated Fill'!$G$97,'Cooling Tower & Corrugated Fill'!$L$97),0) | AA57: =IF(C57=1,IF('Dashboard'!$C$7='Dashboard'!$C$14,'Cooling Tower & Corrugated Fill'!$G$98,'Cooling Tower & Corrugated Fill'!$L$98),0) | AB57: =IF(C57=1,IF('Dashboard'!$C$7='Dashboard'!$C$14,'Cooling Tower & Corrugated Fill'!$G$99,'Cooling Tower & Corrugated Fill'!$L$99),0) | AC57: =IF(C57=1,IF('Dashboard'!$C$7='Dashboard'!$C$14,'Cooling Tower & Corrugated Fill'!$G$100,'Cooling Tower & Corrugated Fill'!$L$100),0) | AD57: =IF(C57=1,IF('Dashboard'!$C$7='Dashboard'!$C$14,'Cooling Tower & Corrugated Fill'!$G$101,'Cooling Tower & Corrugated Fill'!$L$101),0) | AE57: =IF(C57=1,IF('Dashboard'!$C$7='Dashboard'!$C$14,'Cooling Tower & Corrugated Fill'!$G$102,'Cooling Tower & Corrugated Fill'!$L$102),0) | AF57: =IF(C57=1,IF('Dashboard'!$C$7='Dashboard'!$C$14,'Cooling Tower & Corrugated Fill'!$G$103,'Cooling Tower & Corrugated Fill'!$L$103),0) | AG57: =IF(C57=1,IF('Dashboard'!$C$7='Dashboard'!$C$14,'Cooling Tower & Corrugated Fill'!$G$104,'Cooling Tower & Corrugated Fill'!$L$104),0) | AH57: =IF(C57=1,IF('Dashboard'!$C$7='Dashboard'!$C$14,'Cooling Tower & Corrugated Fill'!$G$105,'Cooling Tower & Corrugated Fill'!$L$105),0) | AI57: =IF(C57=1,IF('Dashboard'!$C$7='Dashboard'!$C$14,'Cooling Tower & Corrugated Fill'!$G$106,'Cooling Tower & Corrugated Fill'!$L$106),0) | AJ57: =IF(C57=1,IF('Dashboard'!$C$7='Dashboard'!$C$14,'Cooling Tower & Corrugated Fill'!$G$107,'Cooling Tower & Corrugated Fill'!$L$107),0) | AK57: =IF(C57=1,IF('Dashboard'!$C$7='Dashboard'!$C$14,'Cooling Tower & Corrugated Fill'!$G$108,'Cooling Tower & Corrugated Fill'!$L$108),0) | AL57: =IF(ABS(D57-T57-U57-V57)<0.01,"✅","❌")
B59: System check: Intake − Evaporation − Drift − Sewer discharges | C59: =IF('Dashboard'!$C$7='Dashboard'!$C$14,'Cooling Tower & Corrugated Fill'!$C$86,'Cooling Tower & Corrugated Fill'!$D$86)-IF('Dashboard'!$C$7='Dashboard'!$C$14,'Cooling Tower & Corrugated Fill'!$C$60,'Cooling Tower & Corrugated Fill'!$D$60)-IF('Dashboard'!$C$7='Dashboard'!$C$14,'Cooling Tower & Corrugated Fill'!$C$61,'Cooling Tower & Corrugated Fill'!$D$61)-IF('Dashboard'!$C$7='Dashboard'!$C$14,'Cooling Tower & Corrugated Fill'!$C$89,'Cooling Tower & Corrugated Fill'!$D$89) | D59: gpd | E59: Must be 0 — whole-plant water balance

Sheet Cooling Tower & Corrugated Fill
B1: Cooling Tower Heat Balance & Corrugated Fill Simulation
B2: Q = ṁ·cp·ΔT · Tower Load = Q(1 + 1/COP) · E = TL/(970×8.34) · B = (E − (N−1)D)/(N·k − 1 + Y)
B5: 1. Shared design inputs
B6: Other heat to chilled water (fraction of IT) | C6: 0.05 | D6: -
B7: Chilled-water ΔT | C7: 12 | D7: °F
B8: Chiller COP at reference CWST | C8: 5.5 | D8: -
B9: Reference condenser-water supply temp | C9: 85 | D9: °F
B10: COP sensitivity per °F colder CWST | C10: 0.02 | D10: 1/°F | E10: Screening ~2 %/°F
B11: Non-cooling PUE overhead | C11: 0.08 | D11: -
B12: Tower range (hot − cold) | C12: 10 | D12: °F
B13: Water/air mass ratio L/G | C13: 1.2 | D13: -
B14: Barometric pressure | C14: 101.325 | D14: kPa
B15: Minimum CoC | C15: 1.2 | D15: cycles
B16: Max recirculating LSI (inhibitor program) | C16: 2.5 | D16: -
B17: Recirculating free-chlorine residual | C17: 0.5 | D17: mg/L
B18: Silica blowdown alert | C18: 150 | D18: mg/L
B19: Blowdown-recovery RO recovery Y | C19: 0.7 | D19: -
B20: LEED max Ca (as CaCO3) | C20: 1000 | D20: ppm | E20: LEED v4 WE Cooling Tower Water Use, Table 1
B21: LEED max alkalinity | C21: 1000 | D21: ppm | E21: LEED v4 WE Cooling Tower Water Use, Table 1
B22: LEED max SiO₂ | C22: 100 | D22: ppm | E22: LEED v4 WE Cooling Tower Water Use, Table 1
B23: LEED max chloride | C23: 250 | D23: ppm | E23: LEED v4 WE Cooling Tower Water Use, Table 1
B24: LEED max conductivity | C24: 2000 | D24: µS/cm | E24: LEED v4 WE Cooling Tower Water Use, Table 1
B25: Fill model c0 (KaV/L at reference) | C25: 1.2 | D25: - | E25: Screening calibration
B26: Reference SSA | C26: 150 | D26: m²/m³
B27: Reference fill height | C27: 1.2 | D27: m
B28: KaV/L exponent on L/G (n) | C28: 0.6 | D28: -
B29: Flute-angle thermal exponent | C29: 0.15 | D29: -
B31: 2. Scenario inputs — fill, drift eliminator, chemistry
B32: Parameter | C32: Current Baseline | D32: Corrugated Fill + High CoC | E32: Unit | F32: Note
B33: Fill / eliminator description | C33: Legacy offset film fill + blade eliminator | D33: Cross-fluted corrugated fill + cellular HE eliminator
B34: Specific surface area (SSA) | C34: 150 | D34: 226 | E34: m²/m³
B35: Flute angle | C35: 30 | D35: 60 | E35: °
B36: Sheet thickness | C36: 0.25 | D36: 0.38 | E36: mm
B37: Fill height | C37: 1 | D37: 1.2 | E37: m
B38: Drift fraction of recirculation | C38: 0.002 | D38: 1e-05 | E38: - | F38: 0.20 % → 0.001 % with HE eliminator
B39: Drift eliminator pressure drop | C39: 10 | D39: 20 | E39: Pa
B40: Recirculating pH | C40: 8.3 | D40: 8.4 | E40: -
B41: Target CoC (from Dashboard) | C41: ='Dashboard'!$C$15 | D41: ='Dashboard'!$D$15 | E41: cycles
B42: Blowdown recovery on (from Dashboard) | C42: ='Dashboard'!$C$16 | D42: ='Dashboard'!$D$16 | E42: -
B44: 3. Heat balance
B45: Cooling load Q = IT × 3412 × (1 + other) | C45: ='Dashboard'!$C$8*1000*3412*(1+'Cooling Tower & Corrugated Fill'!$C$6) | D45: ='Dashboard'!$C$8*1000*3412*(1+'Cooling Tower & Corrugated Fill'!$C$6) | E45: BTU/hr
B46: Cooling load | C46: ='Cooling Tower & Corrugated Fill'!$C$45/3412/1000 | D46: ='Cooling Tower & Corrugated Fill'!$D$45/3412/1000 | E46: MW
B47: Cooling load | C47: ='Cooling Tower & Corrugated Fill'!$C$45/12000 | D47: ='Cooling Tower & Corrugated Fill'!$D$45/12000 | E47: tons
B48: Fill KaV/L available = c0(SSA/SSAref)(H/Href)(θ/30)^a(L/G)^−n | C48: ='Cooling Tower & Corrugated Fill'!$C$25*('Cooling Tower & Corrugated Fill'!$C$34/'Cooling Tower & Corrugated Fill'!$C$26)*('Cooling Tower & Corrugated Fill'!$C$37/'Cooling Tower & Corrugated Fill'!$C$27)*('Cooling Tower & Corrugated Fill'!$C$35/30)^'Cooling Tower & Corrugated Fill'!$C$29*'Cooling Tower & Corrugated Fill'!$C$13^(-'Cooling Tower & Corrugated Fill'!$C$28) | D48: ='Cooling Tower & Corrugated Fill'!$C$25*('Cooling Tower & Corrugated Fill'!$D$34/'Cooling Tower & Corrugated Fill'!$C$26)*('Cooling Tower & Corrugated Fill'!$D$37/'Cooling Tower & Corrugated Fill'!$C$27)*('Cooling Tower & Corrugated Fill'!$D$35/30)^'Cooling Tower & Corrugated Fill'!$C$29*'Cooling Tower & Corrugated Fill'!$C$13^(-'Cooling Tower & Corrugated Fill'!$C$28) | E48: -
B49: Cold-water temperature (Merkel solver, interpolated) | C49: =IFERROR(INDEX('Merkel Solver'!$C$7:$C$406,MATCH('Cooling Tower & Corrugated Fill'!$C$48,'Merkel Solver'!$H$7:$H$406,-1))+(INDEX('Merkel Solver'!$C$7:$C$406,MATCH('Cooling Tower & Corrugated Fill'!$C$48,'Merkel Solver'!$H$7:$H$406,-1)+1)-INDEX('Merkel Solver'!$C$7:$C$406,MATCH('Cooling Tower & Corrugated Fill'!$C$48,'Merkel Solver'!$H$7:$H$406,-1)))*(INDEX('Merkel Solver'!$H$7:$H$406,MATCH('Cooling Tower & Corrugated Fill'!$C$48,'Merkel Solver'!$H$7:$H$406,-1))-'Cooling Tower & Corrugated Fill'!$C$48)/(INDEX('Merkel Solver'!$H$7:$H$406,MATCH('Cooling Tower & Corrugated Fill'!$C$48,'Merkel Solver'!$H$7:$H$406,-1))-INDEX('Merkel Solver'!$H$7:$H$406,MATCH('Cooling Tower & Corrugated Fill'!$C$48,'Merkel Solver'!$H$7:$H$406,-1)+1)),'Dashboard'!$C$9+0.1) | D49: =IFERROR(INDEX('Merkel Solver'!$C$7:$C$406,MATCH('Cooling Tower & Corrugated Fill'!$D$48,'Merkel Solver'!$H$7:$H$406,-1))+(INDEX('Merkel Solver'!$C$7:$C$406,MATCH('Cooling Tower & Corrugated Fill'!$D$48,'Merkel Solver'!$H$7:$H$406,-1)+1)-INDEX('Merkel Solver'!$C$7:$C$406,MATCH('Cooling Tower & Corrugated Fill'!$D$48,'Merkel Solver'!$H$7:$H$406,-1)))*(INDEX('Merkel Solver'!$H$7:$H$406,MATCH('Cooling Tower & Corrugated Fill'!$D$48,'Merkel Solver'!$H$7:$H$406,-1))-'Cooling Tower & Corrugated Fill'!$D$48)/(INDEX('Merkel Solver'!$H$7:$H$406,MATCH('Cooling Tower & Corrugated Fill'!$D$48,'Merkel Solver'!$H$7:$H$406,-1))-INDEX('Merkel Solver'!$H$7:$H$406,MATCH('Cooling Tower & Corrugated Fill'!$D$48,'Merkel Solver'!$H$7:$H$406,-1)+1)),'Dashboard'!$C$9+0.1) | E49: °F | F49: Required KaV/L = available (Chebyshev)
B50: Approach (cold water − wet bulb) | C50: ='Cooling Tower & Corrugated Fill'!$C$49-'Dashboard'!$C$9 | D50: ='Cooling Tower & Corrugated Fill'!$D$49-'Dashboard'!$C$9 | E50: °F
B51: Hot-water temperature | C51: ='Cooling Tower & Corrugated Fill'!$C$49+'Cooling Tower & Corrugated Fill'!$C$12 | D51: ='Cooling Tower & Corrugated Fill'!$D$49+'Cooling Tower & Corrugated Fill'!$C$12 | E51: °F
B52: Hot-water temperature | C52: =('Cooling Tower & Corrugated Fill'!$C$51-32)/1.8 | D52: =('Cooling Tower & Corrugated Fill'!$D$51-32)/1.8 | E52: °C
B53: Cold-water temperature | C53: =('Cooling Tower & Corrugated Fill'!$C$49-32)/1.8 | D53: =('Cooling Tower & Corrugated Fill'!$D$49-32)/1.8 | E53: °C
B54: Chiller COP = COPref·(1 + s·(CWSTref − CWST)) | C54: ='Cooling Tower & Corrugated Fill'!$C$8*(1+'Cooling Tower & Corrugated Fill'!$C$10*('Cooling Tower & Corrugated Fill'!$C$9-'Cooling Tower & Corrugated Fill'!$C$49)) | D54: ='Cooling Tower & Corrugated Fill'!$C$8*(1+'Cooling Tower & Corrugated Fill'!$C$10*('Cooling Tower & Corrugated Fill'!$C$9-'Cooling Tower & Corrugated Fill'!$D$49)) | E54: -
B55: Chiller power | C55: ='Cooling Tower & Corrugated Fill'!$C$45/3412/'Cooling Tower & Corrugated Fill'!$C$54 | D55: ='Cooling Tower & Corrugated Fill'!$D$45/3412/'Cooling Tower & Corrugated Fill'!$D$54 | E55: kW
B56: Tower Load = Q·(1 + 1/COP) | C56: ='Cooling Tower & Corrugated Fill'!$C$45*(1+1/'Cooling Tower & Corrugated Fill'!$C$54) | D56: ='Cooling Tower & Corrugated Fill'!$D$45*(1+1/'Cooling Tower & Corrugated Fill'!$D$54) | E56: BTU/hr
B57: Tower Load | C57: ='Cooling Tower & Corrugated Fill'!$C$56/12000 | D57: ='Cooling Tower & Corrugated Fill'!$D$56/12000 | E57: tons
B58: Recirculation Q = TL/(8.34·60·Range) | C58: ='Cooling Tower & Corrugated Fill'!$C$56/(8.34*60*'Cooling Tower & Corrugated Fill'!$C$12) | D58: ='Cooling Tower & Corrugated Fill'!$D$56/(8.34*60*'Cooling Tower & Corrugated Fill'!$C$12) | E58: gpm
B59: Evaporation E = TL/(970 × 8.34) | C59: ='Cooling Tower & Corrugated Fill'!$C$56/(970*8.34) | D59: ='Cooling Tower & Corrugated Fill'!$D$56/(970*8.34) | E59: gph
B60: Evaporation | C60: ='Cooling Tower & Corrugated Fill'!$C$59*24 | D60: ='Cooling Tower & Corrugated Fill'!$D$59*24 | E60: gpd
B61: Drift D = f_drift × Q_recirc | C61: ='Cooling Tower & Corrugated Fill'!$C$58*'Cooling Tower & Corrugated Fill'!$C$38*1440 | D61: ='Cooling Tower & Corrugated Fill'!$D$58*'Cooling Tower & Corrugated Fill'!$D$38*1440 | E61: gpd
B63: 4. Cycles of concentration — limits on treated makeup
B64: Constraint | C64: Current Baseline | D64: Corrugated Fill + High CoC | E64: Unit | F64: Basis
B65: Target | C65: ='Cooling Tower & Corrugated Fill'!$C$41 | D65: ='Cooling Tower & Corrugated Fill'!$D$41 | E65: cycles
B66: LEED Ca (as CaCO3) | C66: ='Cooling Tower & Corrugated Fill'!$C$20/MAX('Cooling Tower & Corrugated Fill'!$C$99*2.497,0.001) | D66: ='Cooling Tower & Corrugated Fill'!$C$20/MAX('Cooling Tower & Corrugated Fill'!$C$99*2.497,0.001) | E66: cycles
B67: LEED alkalinity | C67: ='Cooling Tower & Corrugated Fill'!$C$21/MAX('Cooling Tower & Corrugated Fill'!$C$104,0.001) | D67: ='Cooling Tower & Corrugated Fill'!$C$21/MAX('Cooling Tower & Corrugated Fill'!$C$104,0.001) | E67: cycles
B68: LEED SiO₂ | C68: ='Cooling Tower & Corrugated Fill'!$C$22/MAX('Cooling Tower & Corrugated Fill'!$C$97,0.001) | D68: ='Cooling Tower & Corrugated Fill'!$C$22/MAX('Cooling Tower & Corrugated Fill'!$C$97,0.001) | E68: cycles
B69: LEED chloride | C69: ='Cooling Tower & Corrugated Fill'!$C$23/MAX('Cooling Tower & Corrugated Fill'!$C$101,0.001) | D69: ='Cooling Tower & Corrugated Fill'!$C$23/MAX('Cooling Tower & Corrugated Fill'!$C$101,0.001) | E69: cycles
B70: LEED conductivity | C70: ='Cooling Tower & Corrugated Fill'!$C$24/MAX('Cooling Tower & Corrugated Fill'!$C$95,0.001) | D70: ='Cooling Tower & Corrugated Fill'!$C$24/MAX('Cooling Tower & Corrugated Fill'!$C$95,0.001) | E70: cycles
B71: LSI ceiling: 10^((LSImax − pHr + pHs₁)/1.9) | C71: =10^(('Cooling Tower & Corrugated Fill'!$C$16-'Cooling Tower & Corrugated Fill'!$C$40+((9.3+(LOG(MAX('Cooling Tower & Corrugated Fill'!$C$96,0.001))-1)/10+(-13.12*LOG('Cooling Tower & Corrugated Fill'!$C$52+273)+34.55))-((LOG(MAX('Cooling Tower & Corrugated Fill'!$C$99*2.497,0.001))-0.4)+LOG(MAX('Cooling Tower & Corrugated Fill'!$C$104,0.001)))))/1.9) | D71: =10^(('Cooling Tower & Corrugated Fill'!$C$16-'Cooling Tower & Corrugated Fill'!$D$40+((9.3+(LOG(MAX('Cooling Tower & Corrugated Fill'!$C$96,0.001))-1)/10+(-13.12*LOG('Cooling Tower & Corrugated Fill'!$D$52+273)+34.55))-((LOG(MAX('Cooling Tower & Corrugated Fill'!$C$99*2.497,0.001))-0.4)+LOG(MAX('Cooling Tower & Corrugated Fill'!$C$104,0.001)))))/1.9) | E71: cycles
B72: Drift (bleed ≥ 0): 1 + E/D | C72: =IF('Cooling Tower & Corrugated Fill'!$C$61>0,1+'Cooling Tower & Corrugated Fill'!$C$60/'Cooling Tower & Corrugated Fill'!$C$61,1000000000) | D72: =IF('Cooling Tower & Corrugated Fill'!$D$61>0,1+'Cooling Tower & Corrugated Fill'!$D$60/'Cooling Tower & Corrugated Fill'!$D$61,1000000000) | E72: cycles
B73: Most restrictive limit | C73: =MIN('Cooling Tower & Corrugated Fill'!$C$65:$C$72) | D73: =MIN('Cooling Tower & Corrugated Fill'!$D$65:$D$72) | E73: cycles
B74: Limiting constraint | C74: =INDEX('Cooling Tower & Corrugated Fill'!$B$65:$B$72,MATCH('Cooling Tower & Corrugated Fill'!$C$73,'Cooling Tower & Corrugated Fill'!$C$65:$C$72,0)) | D74: =INDEX('Cooling Tower & Corrugated Fill'!$B$65:$B$72,MATCH('Cooling Tower & Corrugated Fill'!$D$73,'Cooling Tower & Corrugated Fill'!$D$65:$D$72,0))
B75: Operating CoC = MAX(min CoC, limit) | C75: =MAX('Cooling Tower & Corrugated Fill'!$C$15,'Cooling Tower & Corrugated Fill'!$C$73) | D75: =MAX('Cooling Tower & Corrugated Fill'!$C$15,'Cooling Tower & Corrugated Fill'!$D$73) | E75: cycles
B77: 5. Tower & blowdown-recovery water balance
B78: BD-RO recovery used Y | C78: =IF('Cooling Tower & Corrugated Fill'!$C$42=1,'Cooling Tower & Corrugated Fill'!$C$19,0) | D78: =IF('Cooling Tower & Corrugated Fill'!$D$42=1,'Cooling Tower & Corrugated Fill'!$C$19,0) | E78: -
B79: TDS mass fraction to brine k | C79: ='Cooling Tower & Corrugated Fill'!$E$96 | D79: ='Cooling Tower & Corrugated Fill'!$J$96 | E79: -
B80: Blowdown B = (E − (N−1)D)/(N·k − 1 + Y) | C80: =MAX(0,('Cooling Tower & Corrugated Fill'!$C$60-('Cooling Tower & Corrugated Fill'!$C$75-1)*'Cooling Tower & Corrugated Fill'!$C$61)/('Cooling Tower & Corrugated Fill'!$C$75*'Cooling Tower & Corrugated Fill'!$E$96-1+'Cooling Tower & Corrugated Fill'!$C$78)) | D80: =MAX(0,('Cooling Tower & Corrugated Fill'!$D$60-('Cooling Tower & Corrugated Fill'!$D$75-1)*'Cooling Tower & Corrugated Fill'!$D$61)/('Cooling Tower & Corrugated Fill'!$D$75*'Cooling Tower & Corrugated Fill'!$J$96-1+'Cooling Tower & Corrugated Fill'!$D$78)) | E80: gpd
B81: Course check: B = E/(CoC − 1) | C81: ='Cooling Tower & Corrugated Fill'!$C$60/('Cooling Tower & Corrugated Fill'!$C$75-1) | D81: ='Cooling Tower & Corrugated Fill'!$D$60/('Cooling Tower & Corrugated Fill'!$D$75-1) | E81: gpd | F81: Drift lumped into B; recovery off
B82: Permeate recycled P = Y·B | C82: ='Cooling Tower & Corrugated Fill'!$C$78*'Cooling Tower & Corrugated Fill'!$C$80 | D82: ='Cooling Tower & Corrugated Fill'!$D$78*'Cooling Tower & Corrugated Fill'!$D$80 | E82: gpd
B83: Brine / blowdown to sewer | C83: ='Cooling Tower & Corrugated Fill'!$C$80-'Cooling Tower & Corrugated Fill'!$C$82 | D83: ='Cooling Tower & Corrugated Fill'!$D$80-'Cooling Tower & Corrugated Fill'!$D$82 | E83: gpd
B84: Fresh makeup M_f = E + D + brine | C84: ='Cooling Tower & Corrugated Fill'!$C$60+'Cooling Tower & Corrugated Fill'!$C$61+'Cooling Tower & Corrugated Fill'!$C$83 | D84: ='Cooling Tower & Corrugated Fill'!$D$60+'Cooling Tower & Corrugated Fill'!$D$61+'Cooling Tower & Corrugated Fill'!$D$83 | E84: gpd
B85: Tower makeup M_t = M_f + P | C85: ='Cooling Tower & Corrugated Fill'!$C$84+'Cooling Tower & Corrugated Fill'!$C$82 | D85: ='Cooling Tower & Corrugated Fill'!$D$84+'Cooling Tower & Corrugated Fill'!$D$82 | E85: gpd
B86: Raw water intake = M_f / Π recovery | C86: ='Cooling Tower & Corrugated Fill'!$C$84/'Process Flow Mass Balance'!$C$14 | D86: ='Cooling Tower & Corrugated Fill'!$D$84/'Process Flow Mass Balance'!$C$14 | E86: gpd
B87: Raw water intake | C87: ='Cooling Tower & Corrugated Fill'!$C$86*0.00378541 | D87: ='Cooling Tower & Corrugated Fill'!$D$86*0.00378541 | E87: m³/d
B88: Treatment rejects | C88: ='Cooling Tower & Corrugated Fill'!$C$86-'Cooling Tower & Corrugated Fill'!$C$84 | D88: ='Cooling Tower & Corrugated Fill'!$D$86-'Cooling Tower & Corrugated Fill'!$D$84 | E88: gpd
B89: Total discharge to sewer | C89: ='Cooling Tower & Corrugated Fill'!$C$88+'Cooling Tower & Corrugated Fill'!$C$83 | D89: ='Cooling Tower & Corrugated Fill'!$D$88+'Cooling Tower & Corrugated Fill'!$D$83 | E89: gpd
B90: WUE = intake / IT energy | C90: ='Cooling Tower & Corrugated Fill'!$C$86*3.78541/('Dashboard'!$C$8*1000*24) | D90: ='Cooling Tower & Corrugated Fill'!$D$86*3.78541/('Dashboard'!$C$8*1000*24) | E90: L/kWh
B92: 6. Recirculating chemistry C_r,j = M_f·C_f,j / (D + B·k_j)
B93: Species | C93: Treated makeup C_f | D93: BD-RO rejection | E93: k (Base) | F93: C_recirc (Base) | G93: C_permeate (Base) | H93: C_brine (Base) | I93: C_blend (Base) | J93: k (Opt) | K93: C_recirc (Opt) | L93: C_permeate (Opt) | M93: C_brine (Opt) | N93: C_blend (Opt)
B94: pH | C94: ='Process Flow Mass Balance'!$W$55 | F94: ='Cooling Tower & Corrugated Fill'!$C$40 | G94: ='Cooling Tower & Corrugated Fill'!$C$40 | H94: ='Cooling Tower & Corrugated Fill'!$C$40 | I94: =C94 | K94: ='Cooling Tower & Corrugated Fill'!$D$40 | L94: ='Cooling Tower & Corrugated Fill'!$D$40 | M94: ='Cooling Tower & Corrugated Fill'!$D$40 | N94: =C94
B95: EC | C95: ='Process Flow Mass Balance'!$X$55 | D95: 0.98 | E95: =IF('Cooling Tower & Corrugated Fill'!$C$42=1,1-'Cooling Tower & Corrugated Fill'!$C$19*(1-D95),1) | F95: ='Cooling Tower & Corrugated Fill'!$C$84*C95/MAX('Cooling Tower & Corrugated Fill'!$C$61+'Cooling Tower & Corrugated Fill'!$C$80*E95,0.000000000001) | G95: =IF('Cooling Tower & Corrugated Fill'!$C$42=1,F95*(1-E95)/'Cooling Tower & Corrugated Fill'!$C$19,0) | H95: =IF('Cooling Tower & Corrugated Fill'!$C$42=1,F95*E95/(1-'Cooling Tower & Corrugated Fill'!$C$19),F95) | I95: =('Cooling Tower & Corrugated Fill'!$C$84*C95+'Cooling Tower & Corrugated Fill'!$C$82*G95)/'Cooling Tower & Corrugated Fill'!$C$85 | J95: =IF('Cooling Tower & Corrugated Fill'!$D$42=1,1-'Cooling Tower & Corrugated Fill'!$C$19*(1-D95),1) | K95: ='Cooling Tower & Corrugated Fill'!$D$84*C95/MAX('Cooling Tower & Corrugated Fill'!$D$61+'Cooling Tower & Corrugated Fill'!$D$80*J95,0.000000000001) | L95: =IF('Cooling Tower & Corrugated Fill'!$D$42=1,K95*(1-J95)/'Cooling Tower & Corrugated Fill'!$C$19,0) | M95: =IF('Cooling Tower & Corrugated Fill'!$D$42=1,K95*J95/(1-'Cooling Tower & Corrugated Fill'!$C$19),K95) | N95: =('Cooling Tower & Corrugated Fill'!$D$84*C95+'Cooling Tower & Corrugated Fill'!$D$82*L95)/'Cooling Tower & Corrugated Fill'!$D$85
B96: TDS | C96: ='Process Flow Mass Balance'!$Y$55 | D96: 0.98 | E96: =IF('Cooling Tower & Corrugated Fill'!$C$42=1,1-'Cooling Tower & Corrugated Fill'!$C$19*(1-D96),1) | F96: ='Cooling Tower & Corrugated Fill'!$C$84*C96/MAX('Cooling Tower & Corrugated Fill'!$C$61+'Cooling Tower & Corrugated Fill'!$C$80*E96,0.000000000001) | G96: =IF('Cooling Tower & Corrugated Fill'!$C$42=1,F96*(1-E96)/'Cooling Tower & Corrugated Fill'!$C$19,0) | H96: =IF('Cooling Tower & Corrugated Fill'!$C$42=1,F96*E96/(1-'Cooling Tower & Corrugated Fill'!$C$19),F96) | I96: =('Cooling Tower & Corrugated Fill'!$C$84*C96+'Cooling Tower & Corrugated Fill'!$C$82*G96)/'Cooling Tower & Corrugated Fill'!$C$85 | J96: =IF('Cooling Tower & Corrugated Fill'!$D$42=1,1-'Cooling Tower & Corrugated Fill'!$C$19*(1-D96),1) | K96: ='Cooling Tower & Corrugated Fill'!$D$84*C96/MAX('Cooling Tower & Corrugated Fill'!$D$61+'Cooling Tower & Corrugated Fill'!$D$80*J96,0.000000000001) | L96: =IF('Cooling Tower & Corrugated Fill'!$D$42=1,K96*(1-J96)/'Cooling Tower & Corrugated Fill'!$C$19,0) | M96: =IF('Cooling Tower & Corrugated Fill'!$D$42=1,K96*J96/(1-'Cooling Tower & Corrugated Fill'!$C$19),K96) | N96: =('Cooling Tower & Corrugated Fill'!$D$84*C96+'Cooling Tower & Corrugated Fill'!$D$82*L96)/'Cooling Tower & Corrugated Fill'!$D$85
B97: SiO₂ | C97: ='Process Flow Mass Balance'!$Z$55 | D97: 0.97 | E97: =IF('Cooling Tower & Corrugated Fill'!$C$42=1,1-'Cooling Tower & Corrugated Fill'!$C$19*(1-D97),1) | F97: ='Cooling Tower & Corrugated Fill'!$C$84*C97/MAX('Cooling Tower & Corrugated Fill'!$C$61+'Cooling Tower & Corrugated Fill'!$C$80*E97,0.000000000001) | G97: =IF('Cooling Tower & Corrugated Fill'!$C$42=1,F97*(1-E97)/'Cooling Tower & Corrugated Fill'!$C$19,0) | H97: =IF('Cooling Tower & Corrugated Fill'!$C$42=1,F97*E97/(1-'Cooling Tower & Corrugated Fill'!$C$19),F97) | I97: =('Cooling Tower & Corrugated Fill'!$C$84*C97+'Cooling Tower & Corrugated Fill'!$C$82*G97)/'Cooling Tower & Corrugated Fill'!$C$85 | J97: =IF('Cooling Tower & Corrugated Fill'!$D$42=1,1-'Cooling Tower & Corrugated Fill'!$C$19*(1-D97),1) | K97: ='Cooling Tower & Corrugated Fill'!$D$84*C97/MAX('Cooling Tower & Corrugated Fill'!$D$61+'Cooling Tower & Corrugated Fill'!$D$80*J97,0.000000000001) | L97: =IF('Cooling Tower & Corrugated Fill'!$D$42=1,K97*(1-J97)/'Cooling Tower & Corrugated Fill'!$C$19,0) | M97: =IF('Cooling Tower & Corrugated Fill'!$D$42=1,K97*J97/(1-'Cooling Tower & Corrugated Fill'!$C$19),K97) | N97: =('Cooling Tower & Corrugated Fill'!$D$84*C97+'Cooling Tower & Corrugated Fill'!$D$82*L97)/'Cooling Tower & Corrugated Fill'!$D$85
B98: Na⁺ | C98: ='Process Flow Mass Balance'!$AA$55 | D98: 0.97 | E98: =IF('Cooling Tower & Corrugated Fill'!$C$42=1,1-'Cooling Tower & Corrugated Fill'!$C$19*(1-D98),1) | F98: ='Cooling Tower & Corrugated Fill'!$C$84*C98/MAX('Cooling Tower & Corrugated Fill'!$C$61+'Cooling Tower & Corrugated Fill'!$C$80*E98,0.000000000001) | G98: =IF('Cooling Tower & Corrugated Fill'!$C$42=1,F98*(1-E98)/'Cooling Tower & Corrugated Fill'!$C$19,0) | H98: =IF('Cooling Tower & Corrugated Fill'!$C$42=1,F98*E98/(1-'Cooling Tower & Corrugated Fill'!$C$19),F98) | I98: =('Cooling Tower & Corrugated Fill'!$C$84*C98+'Cooling Tower & Corrugated Fill'!$C$82*G98)/'Cooling Tower & Corrugated Fill'!$C$85 | J98: =IF('Cooling Tower & Corrugated Fill'!$D$42=1,1-'Cooling Tower & Corrugated Fill'!$C$19*(1-D98),1) | K98: ='Cooling Tower & Corrugated Fill'!$D$84*C98/MAX('Cooling Tower & Corrugated Fill'!$D$61+'Cooling Tower & Corrugated Fill'!$D$80*J98,0.000000000001) | L98: =IF('Cooling Tower & Corrugated Fill'!$D$42=1,K98*(1-J98)/'Cooling Tower & Corrugated Fill'!$C$19,0) | M98: =IF('Cooling Tower & Corrugated Fill'!$D$42=1,K98*J98/(1-'Cooling Tower & Corrugated Fill'!$C$19),K98) | N98: =('Cooling Tower & Corrugated Fill'!$D$84*C98+'Cooling Tower & Corrugated Fill'!$D$82*L98)/'Cooling Tower & Corrugated Fill'!$D$85
B99: Ca²⁺ | C99: ='Process Flow Mass Balance'!$AB$55 | D99: 0.99 | E99: =IF('Cooling Tower & Corrugated Fill'!$C$42=1,1-'Cooling Tower & Corrugated Fill'!$C$19*(1-D99),1) | F99: ='Cooling Tower & Corrugated Fill'!$C$84*C99/MAX('Cooling Tower & Corrugated Fill'!$C$61+'Cooling Tower & Corrugated Fill'!$C$80*E99,0.000000000001) | G99: =IF('Cooling Tower & Corrugated Fill'!$C$42=1,F99*(1-E99)/'Cooling Tower & Corrugated Fill'!$C$19,0) | H99: =IF('Cooling Tower & Corrugated Fill'!$C$42=1,F99*E99/(1-'Cooling Tower & Corrugated Fill'!$C$19),F99) | I99: =('Cooling Tower & Corrugated Fill'!$C$84*C99+'Cooling Tower & Corrugated Fill'!$C$82*G99)/'Cooling Tower & Corrugated Fill'!$C$85 | J99: =IF('Cooling Tower & Corrugated Fill'!$D$42=1,1-'Cooling Tower & Corrugated Fill'!$C$19*(1-D99),1) | K99: ='Cooling Tower & Corrugated Fill'!$D$84*C99/MAX('Cooling Tower & Corrugated Fill'!$D$61+'Cooling Tower & Corrugated Fill'!$D$80*J99,0.000000000001) | L99: =IF('Cooling Tower & Corrugated Fill'!$D$42=1,K99*(1-J99)/'Cooling Tower & Corrugated Fill'!$C$19,0) | M99: =IF('Cooling Tower & Corrugated Fill'!$D$42=1,K99*J99/(1-'Cooling Tower & Corrugated Fill'!$C$19),K99) | N99: =('Cooling Tower & Corrugated Fill'!$D$84*C99+'Cooling Tower & Corrugated Fill'!$D$82*L99)/'Cooling Tower & Corrugated Fill'!$D$85
B100: Mg²⁺ | C100: ='Process Flow Mass Balance'!$AC$55 | D100: 0.99 | E100: =IF('Cooling Tower & Corrugated Fill'!$C$42=1,1-'Cooling Tower & Corrugated Fill'!$C$19*(1-D100),1) | F100: ='Cooling Tower & Corrugated Fill'!$C$84*C100/MAX('Cooling Tower & Corrugated Fill'!$C$61+'Cooling Tower & Corrugated Fill'!$C$80*E100,0.000000000001) | G100: =IF('Cooling Tower & Corrugated Fill'!$C$42=1,F100*(1-E100)/'Cooling Tower & Corrugated Fill'!$C$19,0) | H100: =IF('Cooling Tower & Corrugated Fill'!$C$42=1,F100*E100/(1-'Cooling Tower & Corrugated Fill'!$C$19),F100) | I100: =('Cooling Tower & Corrugated Fill'!$C$84*C100+'Cooling Tower & Corrugated Fill'!$C$82*G100)/'Cooling Tower & Corrugated Fill'!$C$85 | J100: =IF('Cooling Tower & Corrugated Fill'!$D$42=1,1-'Cooling Tower & Corrugated Fill'!$C$19*(1-D100),1) | K100: ='Cooling Tower & Corrugated Fill'!$D$84*C100/MAX('Cooling Tower & Corrugated Fill'!$D$61+'Cooling Tower & Corrugated Fill'!$D$80*J100,0.000000000001) | L100: =IF('Cooling Tower & Corrugated Fill'!$D$42=1,K100*(1-J100)/'Cooling Tower & Corrugated Fill'!$C$19,0) | M100: =IF('Cooling Tower & Corrugated Fill'!$D$42=1,K100*J100/(1-'Cooling Tower & Corrugated Fill'!$C$19),K100) | N100: =('Cooling Tower & Corrugated Fill'!$D$84*C100+'Cooling Tower & Corrugated Fill'!$D$82*L100)/'Cooling Tower & Corrugated Fill'!$D$85
B101: Cl⁻ | C101: ='Process Flow Mass Balance'!$AD$55 | D101: 0.97 | E101: =IF('Cooling Tower & Corrugated Fill'!$C$42=1,1-'Cooling Tower & Corrugated Fill'!$C$19*(1-D101),1) | F101: ='Cooling Tower & Corrugated Fill'!$C$84*C101/MAX('Cooling Tower & Corrugated Fill'!$C$61+'Cooling Tower & Corrugated Fill'!$C$80*E101,0.000000000001) | G101: =IF('Cooling Tower & Corrugated Fill'!$C$42=1,F101*(1-E101)/'Cooling Tower & Corrugated Fill'!$C$19,0) | H101: =IF('Cooling Tower & Corrugated Fill'!$C$42=1,F101*E101/(1-'Cooling Tower & Corrugated Fill'!$C$19),F101) | I101: =('Cooling Tower & Corrugated Fill'!$C$84*C101+'Cooling Tower & Corrugated Fill'!$C$82*G101)/'Cooling Tower & Corrugated Fill'!$C$85 | J101: =IF('Cooling Tower & Corrugated Fill'!$D$42=1,1-'Cooling Tower & Corrugated Fill'!$C$19*(1-D101),1) | K101: ='Cooling Tower & Corrugated Fill'!$D$84*C101/MAX('Cooling Tower & Corrugated Fill'!$D$61+'Cooling Tower & Corrugated Fill'!$D$80*J101,0.000000000001) | L101: =IF('Cooling Tower & Corrugated Fill'!$D$42=1,K101*(1-J101)/'Cooling Tower & Corrugated Fill'!$C$19,0) | M101: =IF('Cooling Tower & Corrugated Fill'!$D$42=1,K101*J101/(1-'Cooling Tower & Corrugated Fill'!$C$19),K101) | N101: =('Cooling Tower & Corrugated Fill'!$D$84*C101+'Cooling Tower & Corrugated Fill'!$D$82*L101)/'Cooling Tower & Corrugated Fill'!$D$85
B102: PO₄³⁻ | C102: ='Process Flow Mass Balance'!$AE$55 | D102: 0.99 | E102: =IF('Cooling Tower & Corrugated Fill'!$C$42=1,1-'Cooling Tower & Corrugated Fill'!$C$19*(1-D102),1) | F102: ='Cooling Tower & Corrugated Fill'!$C$84*C102/MAX('Cooling Tower & Corrugated Fill'!$C$61+'Cooling Tower & Corrugated Fill'!$C$80*E102,0.000000000001) | G102: =IF('Cooling Tower & Corrugated Fill'!$C$42=1,F102*(1-E102)/'Cooling Tower & Corrugated Fill'!$C$19,0) | H102: =IF('Cooling Tower & Corrugated Fill'!$C$42=1,F102*E102/(1-'Cooling Tower & Corrugated Fill'!$C$19),F102) | I102: =('Cooling Tower & Corrugated Fill'!$C$84*C102+'Cooling Tower & Corrugated Fill'!$C$82*G102)/'Cooling Tower & Corrugated Fill'!$C$85 | J102: =IF('Cooling Tower & Corrugated Fill'!$D$42=1,1-'Cooling Tower & Corrugated Fill'!$C$19*(1-D102),1) | K102: ='Cooling Tower & Corrugated Fill'!$D$84*C102/MAX('Cooling Tower & Corrugated Fill'!$D$61+'Cooling Tower & Corrugated Fill'!$D$80*J102,0.000000000001) | L102: =IF('Cooling Tower & Corrugated Fill'!$D$42=1,K102*(1-J102)/'Cooling Tower & Corrugated Fill'!$C$19,0) | M102: =IF('Cooling Tower & Corrugated Fill'!$D$42=1,K102*J102/(1-'Cooling Tower & Corrugated Fill'!$C$19),K102) | N102: =('Cooling Tower & Corrugated Fill'!$D$84*C102+'Cooling Tower & Corrugated Fill'!$D$82*L102)/'Cooling Tower & Corrugated Fill'!$D$85
B103: SO₄²⁻ | C103: ='Process Flow Mass Balance'!$AF$55 | D103: 0.99 | E103: =IF('Cooling Tower & Corrugated Fill'!$C$42=1,1-'Cooling Tower & Corrugated Fill'!$C$19*(1-D103),1) | F103: ='Cooling Tower & Corrugated Fill'!$C$84*C103/MAX('Cooling Tower & Corrugated Fill'!$C$61+'Cooling Tower & Corrugated Fill'!$C$80*E103,0.000000000001) | G103: =IF('Cooling Tower & Corrugated Fill'!$C$42=1,F103*(1-E103)/'Cooling Tower & Corrugated Fill'!$C$19,0) | H103: =IF('Cooling Tower & Corrugated Fill'!$C$42=1,F103*E103/(1-'Cooling Tower & Corrugated Fill'!$C$19),F103) | I103: =('Cooling Tower & Corrugated Fill'!$C$84*C103+'Cooling Tower & Corrugated Fill'!$C$82*G103)/'Cooling Tower & Corrugated Fill'!$C$85 | J103: =IF('Cooling Tower & Corrugated Fill'!$D$42=1,1-'Cooling Tower & Corrugated Fill'!$C$19*(1-D103),1) | K103: ='Cooling Tower & Corrugated Fill'!$D$84*C103/MAX('Cooling Tower & Corrugated Fill'!$D$61+'Cooling Tower & Corrugated Fill'!$D$80*J103,0.000000000001) | L103: =IF('Cooling Tower & Corrugated Fill'!$D$42=1,K103*(1-J103)/'Cooling Tower & Corrugated Fill'!$C$19,0) | M103: =IF('Cooling Tower & Corrugated Fill'!$D$42=1,K103*J103/(1-'Cooling Tower & Corrugated Fill'!$C$19),K103) | N103: =('Cooling Tower & Corrugated Fill'!$D$84*C103+'Cooling Tower & Corrugated Fill'!$D$82*L103)/'Cooling Tower & Corrugated Fill'!$D$85
B104: Alk (CaCO₃) | C104: ='Process Flow Mass Balance'!$AG$55 | D104: 0.95 | E104: =IF('Cooling Tower & Corrugated Fill'!$C$42=1,1-'Cooling Tower & Corrugated Fill'!$C$19*(1-D104),1) | F104: ='Cooling Tower & Corrugated Fill'!$C$84*C104/MAX('Cooling Tower & Corrugated Fill'!$C$61+'Cooling Tower & Corrugated Fill'!$C$80*E104,0.000000000001) | G104: =IF('Cooling Tower & Corrugated Fill'!$C$42=1,F104*(1-E104)/'Cooling Tower & Corrugated Fill'!$C$19,0) | H104: =IF('Cooling Tower & Corrugated Fill'!$C$42=1,F104*E104/(1-'Cooling Tower & Corrugated Fill'!$C$19),F104) | I104: =('Cooling Tower & Corrugated Fill'!$C$84*C104+'Cooling Tower & Corrugated Fill'!$C$82*G104)/'Cooling Tower & Corrugated Fill'!$C$85 | J104: =IF('Cooling Tower & Corrugated Fill'!$D$42=1,1-'Cooling Tower & Corrugated Fill'!$C$19*(1-D104),1) | K104: ='Cooling Tower & Corrugated Fill'!$D$84*C104/MAX('Cooling Tower & Corrugated Fill'!$D$61+'Cooling Tower & Corrugated Fill'!$D$80*J104,0.000000000001) | L104: =IF('Cooling Tower & Corrugated Fill'!$D$42=1,K104*(1-J104)/'Cooling Tower & Corrugated Fill'!$C$19,0) | M104: =IF('Cooling Tower & Corrugated Fill'!$D$42=1,K104*J104/(1-'Cooling Tower & Corrugated Fill'!$C$19),K104) | N104: =('Cooling Tower & Corrugated Fill'!$D$84*C104+'Cooling Tower & Corrugated Fill'!$D$82*L104)/'Cooling Tower & Corrugated Fill'!$D$85
B105: Free Cl₂ | C105: ='Process Flow Mass Balance'!$AH$55 | D105: 1 | E105: =IF('Cooling Tower & Corrugated Fill'!$C$42=1,1-'Cooling Tower & Corrugated Fill'!$C$19*(1-D105),1) | F105: ='Cooling Tower & Corrugated Fill'!$C$17 | G105: =IF('Cooling Tower & Corrugated Fill'!$C$42=1,F105*(1-E105)/'Cooling Tower & Corrugated Fill'!$C$19,0) | H105: =IF('Cooling Tower & Corrugated Fill'!$C$42=1,F105*E105/(1-'Cooling Tower & Corrugated Fill'!$C$19),F105) | I105: =('Cooling Tower & Corrugated Fill'!$C$84*C105+'Cooling Tower & Corrugated Fill'!$C$82*G105)/'Cooling Tower & Corrugated Fill'!$C$85 | J105: =IF('Cooling Tower & Corrugated Fill'!$D$42=1,1-'Cooling Tower & Corrugated Fill'!$C$19*(1-D105),1) | K105: ='Cooling Tower & Corrugated Fill'!$C$17 | L105: =IF('Cooling Tower & Corrugated Fill'!$D$42=1,K105*(1-J105)/'Cooling Tower & Corrugated Fill'!$C$19,0) | M105: =IF('Cooling Tower & Corrugated Fill'!$D$42=1,K105*J105/(1-'Cooling Tower & Corrugated Fill'!$C$19),K105) | N105: =('Cooling Tower & Corrugated Fill'!$D$84*C105+'Cooling Tower & Corrugated Fill'!$D$82*L105)/'Cooling Tower & Corrugated Fill'!$D$85
B106: TSS | C106: ='Process Flow Mass Balance'!$AI$55 | D106: 1 | E106: =IF('Cooling Tower & Corrugated Fill'!$C$42=1,1-'Cooling Tower & Corrugated Fill'!$C$19*(1-D106),1) | F106: ='Cooling Tower & Corrugated Fill'!$C$84*C106/MAX('Cooling Tower & Corrugated Fill'!$C$61+'Cooling Tower & Corrugated Fill'!$C$80*E106,0.000000000001) | G106: =IF('Cooling Tower & Corrugated Fill'!$C$42=1,F106*(1-E106)/'Cooling Tower & Corrugated Fill'!$C$19,0) | H106: =IF('Cooling Tower & Corrugated Fill'!$C$42=1,F106*E106/(1-'Cooling Tower & Corrugated Fill'!$C$19),F106) | I106: =('Cooling Tower & Corrugated Fill'!$C$84*C106+'Cooling Tower & Corrugated Fill'!$C$82*G106)/'Cooling Tower & Corrugated Fill'!$C$85 | J106: =IF('Cooling Tower & Corrugated Fill'!$D$42=1,1-'Cooling Tower & Corrugated Fill'!$C$19*(1-D106),1) | K106: ='Cooling Tower & Corrugated Fill'!$D$84*C106/MAX('Cooling Tower & Corrugated Fill'!$D$61+'Cooling Tower & Corrugated Fill'!$D$80*J106,0.000000000001) | L106: =IF('Cooling Tower & Corrugated Fill'!$D$42=1,K106*(1-J106)/'Cooling Tower & Corrugated Fill'!$C$19,0) | M106: =IF('Cooling Tower & Corrugated Fill'!$D$42=1,K106*J106/(1-'Cooling Tower & Corrugated Fill'!$C$19),K106) | N106: =('Cooling Tower & Corrugated Fill'!$D$84*C106+'Cooling Tower & Corrugated Fill'!$D$82*L106)/'Cooling Tower & Corrugated Fill'!$D$85
B107: BOD₅ | C107: ='Process Flow Mass Balance'!$AJ$55 | D107: 0.9 | E107: =IF('Cooling Tower & Corrugated Fill'!$C$42=1,1-'Cooling Tower & Corrugated Fill'!$C$19*(1-D107),1) | F107: ='Cooling Tower & Corrugated Fill'!$C$84*C107/MAX('Cooling Tower & Corrugated Fill'!$C$61+'Cooling Tower & Corrugated Fill'!$C$80*E107,0.000000000001) | G107: =IF('Cooling Tower & Corrugated Fill'!$C$42=1,F107*(1-E107)/'Cooling Tower & Corrugated Fill'!$C$19,0) | H107: =IF('Cooling Tower & Corrugated Fill'!$C$42=1,F107*E107/(1-'Cooling Tower & Corrugated Fill'!$C$19),F107) | I107: =('Cooling Tower & Corrugated Fill'!$C$84*C107+'Cooling Tower & Corrugated Fill'!$C$82*G107)/'Cooling Tower & Corrugated Fill'!$C$85 | J107: =IF('Cooling Tower & Corrugated Fill'!$D$42=1,1-'Cooling Tower & Corrugated Fill'!$C$19*(1-D107),1) | K107: ='Cooling Tower & Corrugated Fill'!$D$84*C107/MAX('Cooling Tower & Corrugated Fill'!$D$61+'Cooling Tower & Corrugated Fill'!$D$80*J107,0.000000000001) | L107: =IF('Cooling Tower & Corrugated Fill'!$D$42=1,K107*(1-J107)/'Cooling Tower & Corrugated Fill'!$C$19,0) | M107: =IF('Cooling Tower & Corrugated Fill'!$D$42=1,K107*J107/(1-'Cooling Tower & Corrugated Fill'!$C$19),K107) | N107: =('Cooling Tower & Corrugated Fill'!$D$84*C107+'Cooling Tower & Corrugated Fill'!$D$82*L107)/'Cooling Tower & Corrugated Fill'!$D$85
...

Sheet Pumping & Fan Hydraulics
B1: Pumping & Induced-Draft Fan Hydraulics
B2: WHP = Q·TDH/3960 · BHP = WHP/η_h · kW = BHP·0.7457/(η_m·η_e) · N = ROUNDUP(Q/Q_BEP) · POR 0.7–1.2 Q_BEP
B5: 1. Fan & fill air-side inputs
B6: Tower water loading | C6: 6 | D6: gpm/ft²
B7: Exhaust air specific volume | C7: 14 | D7: ft³/lb
B8: Air density | C8: 1.15 | D8: kg/m³
B9: Other static pressure (louvers, plenum, exit) | C9: 60 | D9: Pa
B10: Fan efficiency | C10: 0.75 | D10: -
B11: Fan motor efficiency | C11: 0.94 | D11: -
B12: Fill ΔP coefficient c | C12: 0.06 | D12: - | E12: Screening calibration
B13: Fill ΔP flute-angle exponent | C13: 0.5 | D13: -
B15: 2. Induced-draft fan energy
B16: Parameter | C16: Current Baseline | D16: Corrugated Fill + High CoC | E16: Unit | F16: Formula
B17: Tower plan area | C17: ='Cooling Tower & Corrugated Fill'!$C$58/'Pumping & Fan Hydraulics'!$C$6/10.7639 | D17: ='Cooling Tower & Corrugated Fill'!$D$58/'Pumping & Fan Hydraulics'!$C$6/10.7639 | E17: m² | F17: Q_recirc / loading
B18: Air mass flow G = L/(L/G) | C18: ='Cooling Tower & Corrugated Fill'!$C$58*8.34*60/'Cooling Tower & Corrugated Fill'!$C$13 | D18: ='Cooling Tower & Corrugated Fill'!$D$58*8.34*60/'Cooling Tower & Corrugated Fill'!$C$13 | E18: lb/hr
B19: Airflow | C19: ='Pumping & Fan Hydraulics'!$C$18*'Pumping & Fan Hydraulics'!$C$7/60 | D19: ='Pumping & Fan Hydraulics'!$D$18*'Pumping & Fan Hydraulics'!$C$7/60 | E19: cfm
B20: Airflow | C20: ='Pumping & Fan Hydraulics'!$C$19*0.0283168/60 | D20: ='Pumping & Fan Hydraulics'!$D$19*0.0283168/60 | E20: m³/s
B21: Fill face velocity | C21: ='Pumping & Fan Hydraulics'!$C$20/'Pumping & Fan Hydraulics'!$C$17 | D21: ='Pumping & Fan Hydraulics'!$D$20/'Pumping & Fan Hydraulics'!$D$17 | E21: m/s
B22: Fill open area ε = 1 − SSA·t/2 | C22: =1-'Cooling Tower & Corrugated Fill'!$C$34*'Cooling Tower & Corrugated Fill'!$C$36/1000/2 | D22: =1-'Cooling Tower & Corrugated Fill'!$D$34*'Cooling Tower & Corrugated Fill'!$D$36/1000/2 | E22: -
B23: Fill ΔP = c·SSA·H·½ρv²·(θ/30)^b/ε² | C23: ='Pumping & Fan Hydraulics'!$C$12*'Cooling Tower & Corrugated Fill'!$C$34*'Cooling Tower & Corrugated Fill'!$C$37*0.5*'Pumping & Fan Hydraulics'!$C$8*'Pumping & Fan Hydraulics'!$C$21^2*('Cooling Tower & Corrugated Fill'!$C$35/30)^'Pumping & Fan Hydraulics'!$C$13/'Pumping & Fan Hydraulics'!$C$22^2 | D23: ='Pumping & Fan Hydraulics'!$C$12*'Cooling Tower & Corrugated Fill'!$D$34*'Cooling Tower & Corrugated Fill'!$D$37*0.5*'Pumping & Fan Hydraulics'!$C$8*'Pumping & Fan Hydraulics'!$D$21^2*('Cooling Tower & Corrugated Fill'!$D$35/30)^'Pumping & Fan Hydraulics'!$C$13/'Pumping & Fan Hydraulics'!$D$22^2 | E23: Pa
B24: Total static pressure | C24: ='Pumping & Fan Hydraulics'!$C$23+'Cooling Tower & Corrugated Fill'!$C$39+'Pumping & Fan Hydraulics'!$C$9 | D24: ='Pumping & Fan Hydraulics'!$D$23+'Cooling Tower & Corrugated Fill'!$D$39+'Pumping & Fan Hydraulics'!$C$9 | E24: Pa
B25: Total static pressure | C25: ='Pumping & Fan Hydraulics'!$C$24/249.089 | D25: ='Pumping & Fan Hydraulics'!$D$24/249.089 | E25: in. w.g.
B26: IDF fan power = V·ΔP/(η_f·η_m) | C26: ='Pumping & Fan Hydraulics'!$C$20*'Pumping & Fan Hydraulics'!$C$24/('Pumping & Fan Hydraulics'!$C$10*'Pumping & Fan Hydraulics'!$C$11)/1000 | D26: ='Pumping & Fan Hydraulics'!$D$20*'Pumping & Fan Hydraulics'!$D$24/('Pumping & Fan Hydraulics'!$C$10*'Pumping & Fan Hydraulics'!$C$11)/1000 | E26: kW
B28: 3. Pump stations (both scenarios)
B29: Pump station | C29: Scenario | D29: Flow Q (gpm) | E29: TDH (ft) | F29: Q_BEP (gpm) | G29: η hydraulic | H29: η mechanical | I29: η electrical | J29: N = ROUNDUP(Q/Q_BEP) | K29: Q per pump | L29: POR min | M29: POR max | N29: In POR? | O29: WHP | P29: BHP | Q29: kW
B30: Chilled-Water Pumps | C30: Baseline | D30: ='Cooling Tower & Corrugated Fill'!$C$45/(8.34*60*'Cooling Tower & Corrugated Fill'!$C$7) | E30: 120 | F30: 3000 | G30: 0.82 | H30: 0.98 | I30: 0.95 | J30: =MAX(1,ROUNDUP(D30/F30,0)) | K30: =D30/J30 | L30: =0.7*F30 | M30: =1.2*F30 | N30: =IF(AND(K30>=L30,K30<=M30),"✅ In POR","❌ Outside") | O30: =D30*E30/3960 | P30: =O30/G30 | Q30: =P30*0.7457/(H30*I30)
B31: Chilled-Water Pumps | C31: Optimized | D31: ='Cooling Tower & Corrugated Fill'!$D$45/(8.34*60*'Cooling Tower & Corrugated Fill'!$C$7) | E31: ='Pumping & Fan Hydraulics'!$E$30 | F31: ='Pumping & Fan Hydraulics'!$F$30 | G31: ='Pumping & Fan Hydraulics'!$G$30 | H31: ='Pumping & Fan Hydraulics'!$H$30 | I31: ='Pumping & Fan Hydraulics'!$I$30 | J31: =MAX(1,ROUNDUP(D31/F31,0)) | K31: =D31/J31 | L31: =0.7*F31 | M31: =1.2*F31 | N31: =IF(AND(K31>=L31,K31<=M31),"✅ In POR","❌ Outside") | O31: =D31*E31/3960 | P31: =O31/G31 | Q31: =P31*0.7457/(H31*I31)
B32: Condenser-Water Pumps | C32: Baseline | D32: ='Cooling Tower & Corrugated Fill'!$C$58 | E32: 80 | F32: 4000 | G32: 0.84 | H32: 0.98 | I32: 0.95 | J32: =MAX(1,ROUNDUP(D32/F32,0)) | K32: =D32/J32 | L32: =0.7*F32 | M32: =1.2*F32 | N32: =IF(AND(K32>=L32,K32<=M32),"✅ In POR","❌ Outside") | O32: =D32*E32/3960 | P32: =O32/G32 | Q32: =P32*0.7457/(H32*I32)
B33: Condenser-Water Pumps | C33: Optimized | D33: ='Cooling Tower & Corrugated Fill'!$D$58 | E33: ='Pumping & Fan Hydraulics'!$E$32 | F33: ='Pumping & Fan Hydraulics'!$F$32 | G33: ='Pumping & Fan Hydraulics'!$G$32 | H33: ='Pumping & Fan Hydraulics'!$H$32 | I33: ='Pumping & Fan Hydraulics'!$I$32 | J33: =MAX(1,ROUNDUP(D33/F33,0)) | K33: =D33/J33 | L33: =0.7*F33 | M33: =1.2*F33 | N33: =IF(AND(K33>=L33,K33<=M33),"✅ In POR","❌ Outside") | O33: =D33*E33/3960 | P33: =O33/G33 | Q33: =P33*0.7457/(H33*I33)
B34: Raw/Makeup Water Pumps | C34: Baseline | D34: ='Cooling Tower & Corrugated Fill'!$C$86/1440 | E34: 150 | F34: 300 | G34: 0.7 | H34: 0.98 | I34: 0.92 | J34: =MAX(1,ROUNDUP(D34/F34,0)) | K34: =D34/J34 | L34: =0.7*F34 | M34: =1.2*F34 | N34: =IF(AND(K34>=L34,K34<=M34),"✅ In POR","❌ Outside") | O34: =D34*E34/3960 | P34: =O34/G34 | Q34: =P34*0.7457/(H34*I34)
B35: Raw/Makeup Water Pumps | C35: Optimized | D35: ='Cooling Tower & Corrugated Fill'!$D$86/1440 | E35: ='Pumping & Fan Hydraulics'!$E$34 | F35: ='Pumping & Fan Hydraulics'!$F$34 | G35: ='Pumping & Fan Hydraulics'!$G$34 | H35: ='Pumping & Fan Hydraulics'!$H$34 | I35: ='Pumping & Fan Hydraulics'!$I$34 | J35: =MAX(1,ROUNDUP(D35/F35,0)) | K35: =D35/J35 | L35: =0.7*F35 | M35: =1.2*F35 | N35: =IF(AND(K35>=L35,K35<=M35),"✅ In POR","❌ Outside") | O35: =D35*E35/3960 | P35: =O35/G35 | Q35: =P35*0.7457/(H35*I35)
B38: 4. Plant power summary
B39: Component | C39: Current Baseline | D39: Corrugated Fill + High CoC | E39: Unit
B40: Chiller compressors | C40: ='Cooling Tower & Corrugated Fill'!$C$55 | D40: ='Cooling Tower & Corrugated Fill'!$D$55 | E40: kW
B41: Tower fans | C41: ='Pumping & Fan Hydraulics'!$C$26 | D41: ='Pumping & Fan Hydraulics'!$D$26 | E41: kW
B42: Chilled-water pumps | C42: ='Pumping & Fan Hydraulics'!$Q$30 | D42: ='Pumping & Fan Hydraulics'!$Q$31 | E42: kW
B43: Condenser-water pumps | C43: ='Pumping & Fan Hydraulics'!$Q$32 | D43: ='Pumping & Fan Hydraulics'!$Q$33 | E43: kW
B44: Raw/makeup water pumps | C44: ='Pumping & Fan Hydraulics'!$Q$34 | D44: ='Pumping & Fan Hydraulics'!$Q$35 | E44: kW
B45: BD-RO energy | C45: =IF('Cooling Tower & Corrugated Fill'!$C$42=1,(0.3+0.1*'Cooling Tower & Corrugated Fill'!$F$96/1000)*1000*0.00378541*'Cooling Tower & Corrugated Fill'!$C$80/1000,0) | D45: =IF('Cooling Tower & Corrugated Fill'!$D$42=1,(0.3+0.1*'Cooling Tower & Corrugated Fill'!$K$96/1000)*1000*0.00378541*'Cooling Tower & Corrugated Fill'!$D$80/1000,0) | E45: kWh/d
B46: Water treatment (train + BD-RO) | C46: =('Process Flow Mass Balance'!$C$15*'Cooling Tower & Corrugated Fill'!$C$86+'Pumping & Fan Hydraulics'!$C$45)/24 | D46: =('Process Flow Mass Balance'!$C$15*'Cooling Tower & Corrugated Fill'!$D$86+'Pumping & Fan Hydraulics'!$D$45)/24 | E46: kW
B47: Total cooling + water plant | C47: ='Pumping & Fan Hydraulics'!$C$40+'Pumping & Fan Hydraulics'!$C$41+'Pumping & Fan Hydraulics'!$C$42+'Pumping & Fan Hydraulics'!$C$43+'Pumping & Fan Hydraulics'!$C$44+'Pumping & Fan Hydraulics'!$C$46 | D47: ='Pumping & Fan Hydraulics'!$D$40+'Pumping & Fan Hydraulics'!$D$41+'Pumping & Fan Hydraulics'!$D$42+'Pumping & Fan Hydraulics'!$D$43+'Pumping & Fan Hydraulics'!$D$44+'Pumping & Fan Hydraulics'!$D$46 | E47: kW
B48: Cooling share of PUE | C48: ='Pumping & Fan Hydraulics'!$C$47/('Dashboard'!$C$8*1000) | D48: ='Pumping & Fan Hydraulics'!$D$47/('Dashboard'!$C$8*1000) | E48: -
B49: PUE | C49: =1+'Pumping & Fan Hydraulics'!$C$48+'Cooling Tower & Corrugated Fill'!$C$11 | D49: =1+'Pumping & Fan Hydraulics'!$D$48+'Cooling Tower & Corrugated Fill'!$C$11 | E49: -
B50: Water-system energy intensity | C50: =('Pumping & Fan Hydraulics'!$C$44+'Pumping & Fan Hydraulics'!$C$46)*24/('Cooling Tower & Corrugated Fill'!$C$86*0.00378541) | D50: =('Pumping & Fan Hydraulics'!$D$44+'Pumping & Fan Hydraulics'!$D$46)*24/('Cooling Tower & Corrugated Fill'!$D$86*0.00378541) | E50: kWh/m³
B51: All pumps in POR (1/0) | C51: =IF(AND(N30="✅ In POR",N32="✅ In POR",N34="✅ In POR"),1,0) | D51: =IF(AND(N31="✅ In POR",N33="✅ In POR",N35="✅ In POR"),1,0)

Sheet Disinfection & Microbial Risk
B1: Disinfection CT & Quantitative Microbial Risk Assessment
B2: CT = C·T10 · T10 = TDT·BF · LRT = LOG(C_in/C_target) · Pd = 1 − (1 + d/β)^−α · Py = 1 − (1 − Pd)^n
B5: 1. Chlorine contact inputs
B6: Contact tank operating volume | C6: 100000 | D6: gal
B7: Peak flow factor | C7: 1.5 | D7: -
B8: Baffling factor BF (0.1 unbaffled – 0.9 plug flow) | C8: 0.3 | D8: -
B9: Water temperature | C9: 20 | D9: °C
B10: Free chlorine residual (Mass Balance outlet) | C10: ='Process Flow Mass Balance'!$AH$55 | D10: mg/L
B12: 2. CT required lookup (free chlorine, SWTR Guidance Manual)
B13: Temp (°C) | C13: CT 4-log virus | E13: Temp (°C) | F13: CT 3-log Giardia (pH 7)
B14: 0.5 | C14: 12 | E14: 5 | F14: 149
B15: 5 | C15: 8 | E15: 10 | F15: 112
B16: 10 | C16: 6 | E16: 15 | F16: 75
B17: 15 | C17: 4 | E17: 20 | F17: 56
B18: 20 | C18: 3 | E18: 25 | F18: 37
B19: 25 | C19: 2
B22: 3. CT verification
B23: Parameter | C23: Current Baseline | D23: Corrugated Fill + High CoC | E23: Unit | F23: Formula
B24: Contact flow (train) | C24: ='Cooling Tower & Corrugated Fill'!$C$86*'Process Flow Mass Balance'!$K$12 | D24: ='Cooling Tower & Corrugated Fill'!$D$86*'Process Flow Mass Balance'!$K$12 | E24: gpd
B25: Peak flow Q_peak | C25: ='Disinfection & Microbial Risk'!$C$24/1440*'Disinfection & Microbial Risk'!$C$7 | D25: ='Disinfection & Microbial Risk'!$D$24/1440*'Disinfection & Microbial Risk'!$C$7 | E25: gpm
B26: Total detention time TDT = V/Q_peak | C26: ='Disinfection & Microbial Risk'!$C$6/'Disinfection & Microbial Risk'!$C$25 | D26: ='Disinfection & Microbial Risk'!$C$6/'Disinfection & Microbial Risk'!$D$25 | E26: min
B27: T10 = TDT × BF | C27: ='Disinfection & Microbial Risk'!$C$26*'Disinfection & Microbial Risk'!$C$8 | D27: ='Disinfection & Microbial Risk'!$D$26*'Disinfection & Microbial Risk'!$C$8 | E27: min
B28: CT = C × T10 | C28: ='Disinfection & Microbial Risk'!$C$10*'Disinfection & Microbial Risk'!$C$27 | D28: ='Disinfection & Microbial Risk'!$C$10*'Disinfection & Microbial Risk'!$D$27 | E28: mg·min/L
B29: CT required 4-log virus | C29: =(INDEX('Disinfection & Microbial Risk'!$C$14:$C$19,MATCH(MAX(MIN('Disinfection & Microbial Risk'!$C$9,INDEX('Disinfection & Microbial Risk'!$B$14:$B$19,6)),INDEX('Disinfection & Microbial Risk'!$B$14:$B$19,1)),'Disinfection & Microbial Risk'!$B$14:$B$19,1))+(INDEX('Disinfection & Microbial Risk'!$C$14:$C$19,MIN(MATCH(MAX(MIN('Disinfection & Microbial Risk'!$C$9,INDEX('Disinfection & Microbial Risk'!$B$14:$B$19,6)),INDEX('Disinfection & Microbial Risk'!$B$14:$B$19,1)),'Disinfection & Microbial Risk'!$B$14:$B$19,1)+1,6))-INDEX('Disinfection & Microbial Risk'!$C$14:$C$19,MATCH(MAX(MIN('Disinfection & Microbial Risk'!$C$9,INDEX('Disinfection & Microbial Risk'!$B$14:$B$19,6)),INDEX('Disinfection & Microbial Risk'!$B$14:$B$19,1)),'Disinfection & Microbial Risk'!$B$14:$B$19,1)))*(MAX(MIN('Disinfection & Microbial Risk'!$C$9,INDEX('Disinfection & Microbial Risk'!$B$14:$B$19,6)),INDEX('Disinfection & Microbial Risk'!$B$14:$B$19,1))-INDEX('Disinfection & Microbial Risk'!$B$14:$B$19,MATCH(MAX(MIN('Disinfection & Microbial Risk'!$C$9,INDEX('Disinfection & Microbial Risk'!$B$14:$B$19,6)),INDEX('Disinfection & Microbial Risk'!$B$14:$B$19,1)),'Disinfection & Microbial Risk'!$B$14:$B$19,1)))/MAX(INDEX('Disinfection & Microbial Risk'!$B$14:$B$19,MIN(MATCH(MAX(MIN('Disinfection & Microbial Risk'!$C$9,INDEX('Disinfection & Microbial Risk'!$B$14:$B$19,6)),INDEX('Disinfection & Microbial Risk'!$B$14:$B$19,1)),'Disinfection & Microbial Risk'!$B$14:$B$19,1)+1,6))-INDEX('Disinfection & Microbial Risk'!$B$14:$B$19,MATCH(MAX(MIN('Disinfection & Microbial Risk'!$C$9,INDEX('Disinfection & Microbial Risk'!$B$14:$B$19,6)),INDEX('Disinfection & Microbial Risk'!$B$14:$B$19,1)),'Disinfection & Microbial Risk'!$B$14:$B$19,1)),0.000000001)) | D29: =(INDEX('Disinfection & Microbial Risk'!$C$14:$C$19,MATCH(MAX(MIN('Disinfection & Microbial Risk'!$C$9,INDEX('Disinfection & Microbial Risk'!$B$14:$B$19,6)),INDEX('Disinfection & Microbial Risk'!$B$14:$B$19,1)),'Disinfection & Microbial Risk'!$B$14:$B$19,1))+(INDEX('Disinfection & Microbial Risk'!$C$14:$C$19,MIN(MATCH(MAX(MIN('Disinfection & Microbial Risk'!$C$9,INDEX('Disinfection & Microbial Risk'!$B$14:$B$19,6)),INDEX('Disinfection & Microbial Risk'!$B$14:$B$19,1)),'Disinfection & Microbial Risk'!$B$14:$B$19,1)+1,6))-INDEX('Disinfection & Microbial Risk'!$C$14:$C$19,MATCH(MAX(MIN('Disinfection & Microbial Risk'!$C$9,INDEX('Disinfection & Microbial Risk'!$B$14:$B$19,6)),INDEX('Disinfection & Microbial Risk'!$B$14:$B$19,1)),'Disinfection & Microbial Risk'!$B$14:$B$19,1)))*(MAX(MIN('Disinfection & Microbial Risk'!$C$9,INDEX('Disinfection & Microbial Risk'!$B$14:$B$19,6)),INDEX('Disinfection & Microbial Risk'!$B$14:$B$19,1))-INDEX('Disinfection & Microbial Risk'!$B$14:$B$19,MATCH(MAX(MIN('Disinfection & Microbial Risk'!$C$9,INDEX('Disinfection & Microbial Risk'!$B$14:$B$19,6)),INDEX('Disinfection & Microbial Risk'!$B$14:$B$19,1)),'Disinfection & Microbial Risk'!$B$14:$B$19,1)))/MAX(INDEX('Disinfection & Microbial Risk'!$B$14:$B$19,MIN(MATCH(MAX(MIN('Disinfection & Microbial Risk'!$C$9,INDEX('Disinfection & Microbial Risk'!$B$14:$B$19,6)),INDEX('Disinfection & Microbial Risk'!$B$14:$B$19,1)),'Disinfection & Microbial Risk'!$B$14:$B$19,1)+1,6))-INDEX('Disinfection & Microbial Risk'!$B$14:$B$19,MATCH(MAX(MIN('Disinfection & Microbial Risk'!$C$9,INDEX('Disinfection & Microbial Risk'!$B$14:$B$19,6)),INDEX('Disinfection & Microbial Risk'!$B$14:$B$19,1)),'Disinfection & Microbial Risk'!$B$14:$B$19,1)),0.000000001)) | E29: mg·min/L
B30: CT required 3-log Giardia | C30: =(INDEX('Disinfection & Microbial Risk'!$F$14:$F$18,MATCH(MAX(MIN('Disinfection & Microbial Risk'!$C$9,INDEX('Disinfection & Microbial Risk'!$E$14:$E$18,5)),INDEX('Disinfection & Microbial Risk'!$E$14:$E$18,1)),'Disinfection & Microbial Risk'!$E$14:$E$18,1))+(INDEX('Disinfection & Microbial Risk'!$F$14:$F$18,MIN(MATCH(MAX(MIN('Disinfection & Microbial Risk'!$C$9,INDEX('Disinfection & Microbial Risk'!$E$14:$E$18,5)),INDEX('Disinfection & Microbial Risk'!$E$14:$E$18,1)),'Disinfection & Microbial Risk'!$E$14:$E$18,1)+1,5))-INDEX('Disinfection & Microbial Risk'!$F$14:$F$18,MATCH(MAX(MIN('Disinfection & Microbial Risk'!$C$9,INDEX('Disinfection & Microbial Risk'!$E$14:$E$18,5)),INDEX('Disinfection & Microbial Risk'!$E$14:$E$18,1)),'Disinfection & Microbial Risk'!$E$14:$E$18,1)))*(MAX(MIN('Disinfection & Microbial Risk'!$C$9,INDEX('Disinfection & Microbial Risk'!$E$14:$E$18,5)),INDEX('Disinfection & Microbial Risk'!$E$14:$E$18,1))-INDEX('Disinfection & Microbial Risk'!$E$14:$E$18,MATCH(MAX(MIN('Disinfection & Microbial Risk'!$C$9,INDEX('Disinfection & Microbial Risk'!$E$14:$E$18,5)),INDEX('Disinfection & Microbial Risk'!$E$14:$E$18,1)),'Disinfection & Microbial Risk'!$E$14:$E$18,1)))/MAX(INDEX('Disinfection & Microbial Risk'!$E$14:$E$18,MIN(MATCH(MAX(MIN('Disinfection & Microbial Risk'!$C$9,INDEX('Disinfection & Microbial Risk'!$E$14:$E$18,5)),INDEX('Disinfection & Microbial Risk'!$E$14:$E$18,1)),'Disinfection & Microbial Risk'!$E$14:$E$18,1)+1,5))-INDEX('Disinfection & Microbial Risk'!$E$14:$E$18,MATCH(MAX(MIN('Disinfection & Microbial Risk'!$C$9,INDEX('Disinfection & Microbial Risk'!$E$14:$E$18,5)),INDEX('Disinfection & Microbial Risk'!$E$14:$E$18,1)),'Disinfection & Microbial Risk'!$E$14:$E$18,1)),0.000000001)) | D30: =(INDEX('Disinfection & Microbial Risk'!$F$14:$F$18,MATCH(MAX(MIN('Disinfection & Microbial Risk'!$C$9,INDEX('Disinfection & Microbial Risk'!$E$14:$E$18,5)),INDEX('Disinfection & Microbial Risk'!$E$14:$E$18,1)),'Disinfection & Microbial Risk'!$E$14:$E$18,1))+(INDEX('Disinfection & Microbial Risk'!$F$14:$F$18,MIN(MATCH(MAX(MIN('Disinfection & Microbial Risk'!$C$9,INDEX('Disinfection & Microbial Risk'!$E$14:$E$18,5)),INDEX('Disinfection & Microbial Risk'!$E$14:$E$18,1)),'Disinfection & Microbial Risk'!$E$14:$E$18,1)+1,5))-INDEX('Disinfection & Microbial Risk'!$F$14:$F$18,MATCH(MAX(MIN('Disinfection & Microbial Risk'!$C$9,INDEX('Disinfection & Microbial Risk'!$E$14:$E$18,5)),INDEX('Disinfection & Microbial Risk'!$E$14:$E$18,1)),'Disinfection & Microbial Risk'!$E$14:$E$18,1)))*(MAX(MIN('Disinfection & Microbial Risk'!$C$9,INDEX('Disinfection & Microbial Risk'!$E$14:$E$18,5)),INDEX('Disinfection & Microbial Risk'!$E$14:$E$18,1))-INDEX('Disinfection & Microbial Risk'!$E$14:$E$18,MATCH(MAX(MIN('Disinfection & Microbial Risk'!$C$9,INDEX('Disinfection & Microbial Risk'!$E$14:$E$18,5)),INDEX('Disinfection & Microbial Risk'!$E$14:$E$18,1)),'Disinfection & Microbial Risk'!$E$14:$E$18,1)))/MAX(INDEX('Disinfection & Microbial Risk'!$E$14:$E$18,MIN(MATCH(MAX(MIN('Disinfection & Microbial Risk'!$C$9,INDEX('Disinfection & Microbial Risk'!$E$14:$E$18,5)),INDEX('Disinfection & Microbial Risk'!$E$14:$E$18,1)),'Disinfection & Microbial Risk'!$E$14:$E$18,1)+1,5))-INDEX('Disinfection & Microbial Risk'!$E$14:$E$18,MATCH(MAX(MIN('Disinfection & Microbial Risk'!$C$9,INDEX('Disinfection & Microbial Risk'!$E$14:$E$18,5)),INDEX('Disinfection & Microbial Risk'!$E$14:$E$18,1)),'Disinfection & Microbial Risk'!$E$14:$E$18,1)),0.000000001)) | E30: mg·min/L
B31: Virus inactivation credit = MIN(4, 4·CT/CTreq) | C31: ='Process Flow Mass Balance'!$C$12*MIN(4,4*'Disinfection & Microbial Risk'!$C$28/'Disinfection & Microbial Risk'!$C$29) | D31: ='Process Flow Mass Balance'!$C$12*MIN(4,4*'Disinfection & Microbial Risk'!$D$28/'Disinfection & Microbial Risk'!$D$29) | E31: log
B32: Giardia inactivation credit = MIN(3, 3·CT/CTreq) | C32: ='Process Flow Mass Balance'!$C$12*MIN(3,3*'Disinfection & Microbial Risk'!$C$28/'Disinfection & Microbial Risk'!$C$30) | D32: ='Process Flow Mass Balance'!$C$12*MIN(3,3*'Disinfection & Microbial Risk'!$D$28/'Disinfection & Microbial Risk'!$D$30) | E32: log
B33: 4-log virus achieved? | C33: =IF('Disinfection & Microbial Risk'!$C$31>=4,"✅ Achieved","❌ Not achieved") | D33: =IF('Disinfection & Microbial Risk'!$D$31>=4,"✅ Achieved","❌ Not achieved")
B35: 4. Physical log-removal credits (enabled nodes, Mass Balance sheet)
B36: Virus LRV (Σ on × LRV) | C36: =SUMPRODUCT('Process Flow Mass Balance'!$C$7:$C$12,'Process Flow Mass Balance'!$F$7:$F$12) | D36: log
B37: Protozoa LRV | C37: =SUMPRODUCT('Process Flow Mass Balance'!$C$7:$C$12,'Process Flow Mass Balance'!$G$7:$G$12) | D37: log
B38: Bacteria LRV | C38: =SUMPRODUCT('Process Flow Mass Balance'!$C$7:$C$12,'Process Flow Mass Balance'!$H$7:$H$12) | D38: log
B40: 5. Ingestion QMRA (worker exposure to cooling water)
B41: Target annual risk Py | C41: 0.0001 | D41: per yr
B42: Ingested volume per event | C42: 1e-05 | D42: L | E42: WERF Table 3-1
B43: Events per year n | C43: 250 | D43: 1/yr
B44: Allowable per-event risk Pd = 1 − (1 − Py)^(1/n) | C44: =1-(1-'Disinfection & Microbial Risk'!$C$41)^(1/'Disinfection & Microbial Risk'!$C$43) | D44: -
B46: Pathogen | C46: Model | D46: α | E46: β | F46: r | G46: LRV class | H46: C source | I46: Allowable dose d | J46: C target | K46: LRT required | L46: LRV Base | M46: Py Base | N46: Check Base | O46: LRV Opt | P46: Py Opt | Q46: Check Opt
B47: Rotavirus | C47: beta_poisson | D47: 0.253 | E47: 0.422 | F47: 0 | G47: virus | H47: ='Source Library'!$J$22 | I47: =IF(C47="beta_poisson",E47*((1-'Disinfection & Microbial Risk'!$C$44)^(-1/D47)-1),-LN(1-'Disinfection & Microbial Risk'!$C$44)/F47) | J47: =I47/'Disinfection & Microbial Risk'!$C$42 | K47: =IF(H47>J47,LOG(H47/J47),0) | L47: ='Disinfection & Microbial Risk'!$C$36+'Disinfection & Microbial Risk'!$C$31 | M47: =1-(1-IF(C47="beta_poisson",1-(1+(H47/10^L47*'Disinfection & Microbial Risk'!$C$42)/E47)^(-D47),1-EXP(-F47*(H47/10^L47*'Disinfection & Microbial Risk'!$C$42))))^'Disinfection & Microbial Risk'!$C$43 | N47: =IF(M47<='Disinfection & Microbial Risk'!$C$41,"✅","❌") | O47: ='Disinfection & Microbial Risk'!$C$36+'Disinfection & Microbial Risk'!$D$31 | P47: =1-(1-IF(C47="beta_poisson",1-(1+(H47/10^O47*'Disinfection & Microbial Risk'!$C$42)/E47)^(-D47),1-EXP(-F47*(H47/10^O47*'Disinfection & Microbial Risk'!$C$42))))^'Disinfection & Microbial Risk'!$C$43 | Q47: =IF(P47<='Disinfection & Microbial Risk'!$C$41,"✅","❌")
B48: Giardia | C48: exponential | D48: 0 | E48: 0 | F48: 0.0199 | G48: protozoa | H48: ='Source Library'!$J$23 | I48: =IF(C48="beta_poisson",E48*((1-'Disinfection & Microbial Risk'!$C$44)^(-1/D48)-1),-LN(1-'Disinfection & Microbial Risk'!$C$44)/F48) | J48: =I48/'Disinfection & Microbial Risk'!$C$42 | K48: =IF(H48>J48,LOG(H48/J48),0) | L48: ='Disinfection & Microbial Risk'!$C$37+'Disinfection & Microbial Risk'!$C$32 | M48: =1-(1-IF(C48="beta_poisson",1-(1+(H48/10^L48*'Disinfection & Microbial Risk'!$C$42)/E48)^(-D48),1-EXP(-F48*(H48/10^L48*'Disinfection & Microbial Risk'!$C$42))))^'Disinfection & Microbial Risk'!$C$43 | N48: =IF(M48<='Disinfection & Microbial Risk'!$C$41,"✅","❌") | O48: ='Disinfection & Microbial Risk'!$C$37+'Disinfection & Microbial Risk'!$D$32 | P48: =1-(1-IF(C48="beta_poisson",1-(1+(H48/10^O48*'Disinfection & Microbial Risk'!$C$42)/E48)^(-D48),1-EXP(-F48*(H48/10^O48*'Disinfection & Microbial Risk'!$C$42))))^'Disinfection & Microbial Risk'!$C$43 | Q48: =IF(P48<='Disinfection & Microbial Risk'!$C$41,"✅","❌")
B49: Cryptosporidium | C49: exponential | D49: 0 | E49: 0 | F49: 0.004191 | G49: protozoa | H49: ='Source Library'!$J$24 | I49: =IF(C49="beta_poisson",E49*((1-'Disinfection & Microbial Risk'!$C$44)^(-1/D49)-1),-LN(1-'Disinfection & Microbial Risk'!$C$44)/F49) | J49: =I49/'Disinfection & Microbial Risk'!$C$42 | K49: =IF(H49>J49,LOG(H49/J49),0) | L49: ='Disinfection & Microbial Risk'!$C$37+0 | M49: =1-(1-IF(C49="beta_poisson",1-(1+(H49/10^L49*'Disinfection & Microbial Risk'!$C$42)/E49)^(-D49),1-EXP(-F49*(H49/10^L49*'Disinfection & Microbial Risk'!$C$42))))^'Disinfection & Microbial Risk'!$C$43 | N49: =IF(M49<='Disinfection & Microbial Risk'!$C$41,"✅","❌") | O49: ='Disinfection & Microbial Risk'!$C$37+0 | P49: =1-(1-IF(C49="beta_poisson",1-(1+(H49/10^O49*'Disinfection & Microbial Risk'!$C$42)/E49)^(-D49),1-EXP(-F49*(H49/10^O49*'Disinfection & Microbial Risk'!$C$42))))^'Disinfection & Microbial Risk'!$C$43 | Q49: =IF(P49<='Disinfection & Microbial Risk'!$C$41,"✅","❌")
B50: Vibrio cholerae | C50: beta_poisson | D50: 0.097 | E50: 13020 | F50: 0 | G50: bacteria | H50: ='Source Library'!$J$25 | I50: =IF(C50="beta_poisson",E50*((1-'Disinfection & Microbial Risk'!$C$44)^(-1/D50)-1),-LN(1-'Disinfection & Microbial Risk'!$C$44)/F50) | J50: =I50/'Disinfection & Microbial Risk'!$C$42 | K50: =IF(H50>J50,LOG(H50/J50),0) | L50: ='Disinfection & Microbial Risk'!$C$38+'Disinfection & Microbial Risk'!$C$31 | M50: =1-(1-IF(C50="beta_poisson",1-(1+(H50/10^L50*'Disinfection & Microbial Risk'!$C$42)/E50)^(-D50),1-EXP(-F50*(H50/10^L50*'Disinfection & Microbial Risk'!$C$42))))^'Disinfection & Microbial Risk'!$C$43 | N50: =IF(M50<='Disinfection & Microbial Risk'!$C$41,"✅","❌") | O50: ='Disinfection & Microbial Risk'!$C$38+'Disinfection & Microbial Risk'!$D$31 | P50: =1-(1-IF(C50="beta_poisson",1-(1+(H50/10^O50*'Disinfection & Microbial Risk'!$C$42)/E50)^(-D50),1-EXP(-F50*(H50/10^O50*'Disinfection & Microbial Risk'!$C$42))))^'Disinfection & Microbial Risk'!$C$43 | Q50: =IF(P50<='Disinfection & Microbial Risk'!$C$41,"✅","❌")
B52: All ingestion pathogens meet target (1/0) | C52: =IF(AND(N47="✅",N48="✅",N49="✅",N50="✅"),1,0) | D52: =IF(AND(Q47="✅",Q48="✅",Q49="✅",Q50="✅"),1,0)
B55: 6. Legionella inhalation QMRA — drift aerosol (exponential, r = 0.06)
B56: Recirculating Legionella (control level) | C56: 1000 | D56: CFU/L
B57: Receptor plume dilution | C57: 0.01 | D57: - | E57: Screening
B58: Respirable fraction of drift water | C58: 0.1 | D58: - | E58: Screening
B59: Breathing rate | C59: 1.3 | D59: m³/h
B60: Exposure duration per event | C60: 1 | D60: h
B61: Events per year | C61: 250 | D61: 1/yr
B62: Dose-response r | C62: 0.06 | D62: - | E62: Armstrong & Haas (2007)
B63: Parameter | C63: Current Baseline | D63: Corrugated Fill + High CoC | E63: Unit | F63: Formula
B64: Aerosol water at receptor | C64: ='Cooling Tower & Corrugated Fill'!$C$61/1440*3.78541/60/'Pumping & Fan Hydraulics'!$C$20*'Disinfection & Microbial Risk'!$C$57 | D64: ='Cooling Tower & Corrugated Fill'!$D$61/1440*3.78541/60/'Pumping & Fan Hydraulics'!$D$20*'Disinfection & Microbial Risk'!$C$57 | E64: L/m³
B65: Inhaled water-equivalent volume | C65: ='Disinfection & Microbial Risk'!$C$64*'Disinfection & Microbial Risk'!$C$58*'Disinfection & Microbial Risk'!$C$59*'Disinfection & Microbial Risk'!$C$60 | D65: ='Disinfection & Microbial Risk'!$D$64*'Disinfection & Microbial Risk'!$C$58*'Disinfection & Microbial Risk'!$C$59*'Disinfection & Microbial Risk'!$C$60 | E65: L/event
B66: Dose d = C × V | C66: ='Disinfection & Microbial Risk'!$C$56*'Disinfection & Microbial Risk'!$C$65 | D66: ='Disinfection & Microbial Risk'!$C$56*'Disinfection & Microbial Risk'!$D$65 | E66: CFU
B67: Pd = 1 − EXP(−r·d) | C67: =1-EXP(-'Disinfection & Microbial Risk'!$C$62*'Disinfection & Microbial Risk'!$C$66) | D67: =1-EXP(-'Disinfection & Microbial Risk'!$C$62*'Disinfection & Microbial Risk'!$D$66) | E67: -
B68: Py = 1 − (1 − Pd)^n | C68: =1-(1-'Disinfection & Microbial Risk'!$C$67)^'Disinfection & Microbial Risk'!$C$61 | D68: =1-(1-'Disinfection & Microbial Risk'!$D$67)^'Disinfection & Microbial Risk'!$C$61 | E68: per yr
B69: Allowable recirculating Legionella | C69: =-LN(1-(1-(1-'Disinfection & Microbial Risk'!$C$41)^(1/'Disinfection & Microbial Risk'!$C$61)))/'Disinfection & Microbial Risk'!$C$62/'Disinfection & Microbial Risk'!$C$65 | D69: =-LN(1-(1-(1-'Disinfection & Microbial Risk'!$C$41)^(1/'Disinfection & Microbial Risk'!$C$61)))/'Disinfection & Microbial Risk'!$C$62/'Disinfection & Microbial Risk'!$D$65 | E69: CFU/L
B70: Required additional LRT on recirc water | C70: =IF('Disinfection & Microbial Risk'!$C$56>'Disinfection & Microbial Risk'!$C$69,LOG('Disinfection & Microbial Risk'!$C$56/'Disinfection & Microbial Risk'!$C$69),0) | D70: =IF('Disinfection & Microbial Risk'!$C$56>'Disinfection & Microbial Risk'!$D$69,LOG('Disinfection & Microbial Risk'!$C$56/'Disinfection & Microbial Risk'!$D$69),0) | E70: log
B71: Legionella risk check | C71: =IF('Disinfection & Microbial Risk'!$C$68<='Disinfection & Microbial Risk'!$C$41,"✅ Py ≤ 1e-4","❌ Py > 1e-4") | D71: =IF('Disinfection & Microbial Risk'!$D$68<='Disinfection & Microbial Risk'!$C$41,"✅ Py ≤ 1e-4","❌ Py > 1e-4")

Sheet Financial & LCC Analysis
B1: Financial & Lifecycle Cost Analysis (NYC DEP FY2022 tariffs)
B2: i = r_interest + r_inflation · PV = FV/(1+i)^n · NPV = Σ CF_t/(1+i)^t − CapEx · SPBT = CapEx / savings
B5: 1. Tariffs, prices & finance inputs
B6: Water rate | C6: 4.1 | D6: $/100 ft³ | E6: NYC DEP FY22 metered water
B7: Water rate | C7: ='Financial & LCC Analysis'!$C$6/748.052*1000 | D7: $/kgal
B8: Sewer charge multiplier | C8: 1.59 | D8: × water | E8: 159 % of water charge
B9: Sewer rate | C9: ='Financial & LCC Analysis'!$C$7*'Financial & LCC Analysis'!$C$8 | D9: $/kgal
B10: Cooling-tower sewer allowance (evaporation exempt) 1/0 | C10: 1 | D10: -
B11: Electricity | C11: 0.2 | D11: $/kWh
B12: Sodium hypochlorite (as Cl₂) | C12: 0.6 | D12: $/kg
B13: Alum | C13: 0.35 | D13: $/kg
B14: Scale/corrosion inhibitor | C14: 3 | D14: $/kg
B15: Sludge disposal | C15: 150 | D15: $/dry ton
B16: Alum sludge yield | C16: 0.26 | D16: kg/kg
B17: Tower biocide dose (per makeup) | C17: 2 | D17: mg/L
B18: Inhibitor held in recirculation | C18: 10 | D18: mg/L
B19: Grid emission factor | C19: 0.88 | D19: lb CO₂/kWh
B20: Social cost of carbon | C20: 142 | D20: $/t
B21: Hours per year | C21: 8760 | D21: h
B22: Operating days equivalent = hours/24 × utilization | C22: ='Financial & LCC Analysis'!$C$21/24*'Dashboard'!$C$10 | D22: d/yr
B23: Interest rate | C23: 0.04 | D23: -
B24: Inflation rate | C24: 0.03 | D24: -
B25: Discount rate i = interest + inflation | C25: ='Financial & LCC Analysis'!$C$23+'Financial & LCC Analysis'!$C$24 | D25: -
B26: Utility cost escalation | C26: 0.0276 | D26: - | E26: NYC water rate +2.76 % (FY22)
B27: Fill cost | C27: 350 | D27: $/m³
B28: Drift eliminator cost | C28: 120 | D28: $/m²
B29: Blowdown-recovery RO cost | C29: 2 | D29: $/gpd
B30: Installation factor | C30: 1.3 | D30: ×
B32: 2. Annual quantities
B33: Quantity | C33: Current Baseline | D33: Corrugated Fill + High CoC | E33: Unit
B34: Raw water intake | C34: ='Cooling Tower & Corrugated Fill'!$C$86*'Financial & LCC Analysis'!$C$22 | D34: ='Cooling Tower & Corrugated Fill'!$D$86*'Financial & LCC Analysis'!$C$22 | E34: gal/yr
B35: Sewer discharge | C35: ='Cooling Tower & Corrugated Fill'!$C$89*'Financial & LCC Analysis'!$C$22 | D35: ='Cooling Tower & Corrugated Fill'!$D$89*'Financial & LCC Analysis'!$C$22 | E35: gal/yr
B36: Electricity | C36: ='Pumping & Fan Hydraulics'!$C$47*'Financial & LCC Analysis'!$C$21*'Dashboard'!$C$10 | D36: ='Pumping & Fan Hydraulics'!$D$47*'Financial & LCC Analysis'!$C$21*'Dashboard'!$C$10 | E36: kWh/yr
B37: Alum | C37: ='Process Flow Mass Balance'!$C$8*'Process Flow Mass Balance'!$C$27*'Cooling Tower & Corrugated Fill'!$C$86*'Process Flow Mass Balance'!$K$8*3.78541/1000000*'Financial & LCC Analysis'!$C$22 | D37: ='Process Flow Mass Balance'!$C$8*'Process Flow Mass Balance'!$C$27*'Cooling Tower & Corrugated Fill'!$D$86*'Process Flow Mass Balance'!$K$8*3.78541/1000000*'Financial & LCC Analysis'!$C$22 | E37: kg/yr
B38: NaOCl (contact + tower biocide) | C38: =('Process Flow Mass Balance'!$C$12*'Process Flow Mass Balance'!$M$46*'Cooling Tower & Corrugated Fill'!$C$86*'Process Flow Mass Balance'!$K$12+'Financial & LCC Analysis'!$C$17*'Cooling Tower & Corrugated Fill'!$C$85)*3.78541/1000000*'Financial & LCC Analysis'!$C$22 | D38: =('Process Flow Mass Balance'!$C$12*'Process Flow Mass Balance'!$M$46*'Cooling Tower & Corrugated Fill'!$D$86*'Process Flow Mass Balance'!$K$12+'Financial & LCC Analysis'!$C$17*'Cooling Tower & Corrugated Fill'!$D$85)*3.78541/1000000*'Financial & LCC Analysis'!$C$22 | E38: kg/yr
B39: Inhibitor = C × (B + D) | C39: ='Financial & LCC Analysis'!$C$18*('Cooling Tower & Corrugated Fill'!$C$80+'Cooling Tower & Corrugated Fill'!$C$61)*3.78541/1000000*'Financial & LCC Analysis'!$C$22 | D39: ='Financial & LCC Analysis'!$C$18*('Cooling Tower & Corrugated Fill'!$D$80+'Cooling Tower & Corrugated Fill'!$D$61)*3.78541/1000000*'Financial & LCC Analysis'!$C$22 | E39: kg/yr
B40: Dry sludge | C40: =(SUM('Process Flow Mass Balance'!$AM$50:$AM$55)*'Cooling Tower & Corrugated Fill'!$C$86+'Financial & LCC Analysis'!$C$37/'Financial & LCC Analysis'!$C$22*'Financial & LCC Analysis'!$C$16)/907.185*'Financial & LCC Analysis'!$C$22 | D40: =(SUM('Process Flow Mass Balance'!$AM$50:$AM$55)*'Cooling Tower & Corrugated Fill'!$D$86+'Financial & LCC Analysis'!$D$37/'Financial & LCC Analysis'!$C$22*'Financial & LCC Analysis'!$C$16)/907.185*'Financial & LCC Analysis'!$C$22 | E40: dry t/yr
B41: CO₂e | C41: ='Financial & LCC Analysis'!$C$36*'Financial & LCC Analysis'!$C$19/2204.6 | D41: ='Financial & LCC Analysis'!$D$36*'Financial & LCC Analysis'!$C$19/2204.6 | E41: t/yr
B43: 3. Annual operating cost (year 1)
B44: Cost item | C44: Current Baseline | D44: Corrugated Fill + High CoC | E44: Unit
B45: Water purchase | C45: =IF('Source Library'!$J$29=1,'Financial & LCC Analysis'!$C$34/1000*'Financial & LCC Analysis'!$C$7,0) | D45: =IF('Source Library'!$J$29=1,'Financial & LCC Analysis'!$D$34/1000*'Financial & LCC Analysis'!$C$7,0) | E45: $/yr
B46: Sewer | C46: =IF('Financial & LCC Analysis'!$C$10=1,'Financial & LCC Analysis'!$C$35,'Financial & LCC Analysis'!$C$34)/1000*'Financial & LCC Analysis'!$C$9 | D46: =IF('Financial & LCC Analysis'!$C$10=1,'Financial & LCC Analysis'!$D$35,'Financial & LCC Analysis'!$D$34)/1000*'Financial & LCC Analysis'!$C$9 | E46: $/yr
B47: Electricity | C47: ='Financial & LCC Analysis'!$C$36*'Financial & LCC Analysis'!$C$11 | D47: ='Financial & LCC Analysis'!$D$36*'Financial & LCC Analysis'!$C$11 | E47: $/yr
B48: Chemicals | C48: ='Financial & LCC Analysis'!$C$37*'Financial & LCC Analysis'!$C$13+'Financial & LCC Analysis'!$C$38*'Financial & LCC Analysis'!$C$12+'Financial & LCC Analysis'!$C$39*'Financial & LCC Analysis'!$C$14 | D48: ='Financial & LCC Analysis'!$D$37*'Financial & LCC Analysis'!$C$13+'Financial & LCC Analysis'!$D$38*'Financial & LCC Analysis'!$C$12+'Financial & LCC Analysis'!$D$39*'Financial & LCC Analysis'!$C$14 | E48: $/yr
B49: Sludge disposal | C49: ='Financial & LCC Analysis'!$C$40*'Financial & LCC Analysis'!$C$15 | D49: ='Financial & LCC Analysis'!$D$40*'Financial & LCC Analysis'!$C$15 | E49: $/yr
B50: Carbon (social cost) | C50: ='Financial & LCC Analysis'!$C$41*'Financial & LCC Analysis'!$C$20 | D50: ='Financial & LCC Analysis'!$D$41*'Financial & LCC Analysis'!$C$20 | E50: $/yr
B51: TOTAL | C51: =SUM('Financial & LCC Analysis'!$C$45,'Financial & LCC Analysis'!$C$46,'Financial & LCC Analysis'!$C$47,'Financial & LCC Analysis'!$C$48,'Financial & LCC Analysis'!$C$49,'Financial & LCC Analysis'!$C$50) | D51: =SUM('Financial & LCC Analysis'!$D$45,'Financial & LCC Analysis'!$D$46,'Financial & LCC Analysis'!$D$47,'Financial & LCC Analysis'!$D$48,'Financial & LCC Analysis'!$D$49,'Financial & LCC Analysis'!$D$50) | E51: $/yr
B52: Year-1 net operating savings (Baseline − Optimized) | C52: ='Financial & LCC Analysis'!$C$51-'Financial & LCC Analysis'!$D$51 | D52: $/yr
B54: 4. Upgrade capital cost
B55: Corrugated fill = area × height × $/m³ | C55: ='Pumping & Fan Hydraulics'!$D$17*'Cooling Tower & Corrugated Fill'!$D$37*'Financial & LCC Analysis'!$C$27 | D55: $
B56: HE drift eliminators = area × $/m² | C56: ='Pumping & Fan Hydraulics'!$D$17*'Financial & LCC Analysis'!$C$28 | D56: $
B57: Blowdown-recovery RO | C57: =IF(AND('Dashboard'!$D$16=1,'Dashboard'!$C$16=0),'Cooling Tower & Corrugated Fill'!$D$80*'Financial & LCC Analysis'!$C$29,0) | D57: $
B58: Installation | C58: =('Financial & LCC Analysis'!$C$55+'Financial & LCC Analysis'!$C$56+'Financial & LCC Analysis'!$C$57)*('Financial & LCC Analysis'!$C$30-1) | D58: $
B59: TOTAL CapEx | C59: ='Financial & LCC Analysis'!$C$55+'Financial & LCC Analysis'!$C$56+'Financial & LCC Analysis'!$C$57+'Financial & LCC Analysis'!$C$58 | D59: $
B61: 5. 10-year discounted cash flow
B62: Year t | C62: Cash flow CF_t | D62: Discount factor 1/(1+i)^t | E62: PV = CF/(1+i)^t | F62: Cumulative PV
B63: 0 | C63: =-'Financial & LCC Analysis'!$C$59 | D63: 1 | E63: =C63*D63 | F63: =E63
B64: 1 | C64: ='Financial & LCC Analysis'!$C$52*(1+'Financial & LCC Analysis'!$C$26)^(B64-1) | D64: =1/(1+'Financial & LCC Analysis'!$C$25)^B64 | E64: =C64*D64 | F64: =F63+E64
B65: 2 | C65: ='Financial & LCC Analysis'!$C$52*(1+'Financial & LCC Analysis'!$C$26)^(B65-1) | D65: =1/(1+'Financial & LCC Analysis'!$C$25)^B65 | E65: =C65*D65 | F65: =F64+E65
B66: 3 | C66: ='Financial & LCC Analysis'!$C$52*(1+'Financial & LCC Analysis'!$C$26)^(B66-1) | D66: =1/(1+'Financial & LCC Analysis'!$C$25)^B66 | E66: =C66*D66 | F66: =F65+E66
B67: 4 | C67: ='Financial & LCC Analysis'!$C$52*(1+'Financial & LCC Analysis'!$C$26)^(B67-1) | D67: =1/(1+'Financial & LCC Analysis'!$C$25)^B67 | E67: =C67*D67 | F67: =F66+E67
B68: 5 | C68: ='Financial & LCC Analysis'!$C$52*(1+'Financial & LCC Analysis'!$C$26)^(B68-1) | D68: =1/(1+'Financial & LCC Analysis'!$C$25)^B68 | E68: =C68*D68 | F68: =F67+E68
B69: 6 | C69: ='Financial & LCC Analysis'!$C$52*(1+'Financial & LCC Analysis'!$C$26)^(B69-1) | D69: =1/(1+'Financial & LCC Analysis'!$C$25)^B69 | E69: =C69*D69 | F69: =F68+E69
B70: 7 | C70: ='Financial & LCC Analysis'!$C$52*(1+'Financial & LCC Analysis'!$C$26)^(B70-1) | D70: =1/(1+'Financial & LCC Analysis'!$C$25)^B70 | E70: =C70*D70 | F70: =F69+E70
B71: 8 | C71: ='Financial & LCC Analysis'!$C$52*(1+'Financial & LCC Analysis'!$C$26)^(B71-1) | D71: =1/(1+'Financial & LCC Analysis'!$C$25)^B71 | E71: =C71*D71 | F71: =F70+E71
B72: 9 | C72: ='Financial & LCC Analysis'!$C$52*(1+'Financial & LCC Analysis'!$C$26)^(B72-1) | D72: =1/(1+'Financial & LCC Analysis'!$C$25)^B72 | E72: =C72*D72 | F72: =F71+E72
B73: 10 | C73: ='Financial & LCC Analysis'!$C$52*(1+'Financial & LCC Analysis'!$C$26)^(B73-1) | D73: =1/(1+'Financial & LCC Analysis'!$C$25)^B73 | E73: =C73*D73 | F73: =F72+E73
B75: NPV = −CapEx + NPV(i, CF₁…CF_N) | C75: =C63+NPV('Financial & LCC Analysis'!$C$25,C64:C73) | D75: $
B76: NPV check = Σ PV | C76: =SUM(E63:E73) | D76: $
B77: IRR | C77: =IFERROR(IRR(C63:C73),"n/a") | D77: -
B78: Discounted break-even year (BEP) | C78: =IF(COUNTIF(F64:F73,"<0")=10,"> horizon",COUNTIF(F64:F73,"<0")+(-INDEX(F63:F73,COUNTIF(F64:F73,"<0")+1))/(INDEX(F63:F73,COUNTIF(F64:F73,"<0")+2)-INDEX(F63:F73,COUNTIF(F64:F73,"<0")+1))) | D78: years
B79: Simple payback SPBT = CapEx / savings | C79: =IF('Financial & LCC Analysis'!$C$52>0,'Financial & LCC Analysis'!$C$59/'Financial & LCC Analysis'!$C$52,"n/a") | D79: years
B80: Investment decision | C80: =IF('Financial & LCC Analysis'!$C$75>0,"✅ Positive NPV — invest","❌ Negative NPV")

Sheet Source Library
B1: Source Library — Raw Water Quality Matrices
B2: Edit any yellow cell; the Dashboard source selector pulls the matching column.
B5: Baseline quality by source
B6: Parameter | C6: Unit | D6: Municipal Potable | E6: Sea Water | F6: River Water | G6: Groundwater | H6: MBR Permeate / Wastewater Reuse | I6: Rainwater (roof harvest) | J6: Selected source
B7: pH | C7: - | D7: 7.2 | E7: 8.1 | F7: 7.6 | G7: 7.3 | H7: 7 | I7: 6 | J7: =INDEX(D7:I7,MATCH('Dashboard'!$C$6,'Source Library'!$D$6:$I$6,0))
B8: EC | C8: µS/cm | D8: 110 | E8: 53000 | F8: 400 | G8: 700 | H8: 900 | I8: 20 | J8: =INDEX(D8:I8,MATCH('Dashboard'!$C$6,'Source Library'!$D$6:$I$6,0))
B9: TDS | C9: mg/L | D9: 65 | E9: 35000 | F9: 260 | G9: 455 | H9: 585 | I9: 13 | J9: =INDEX(D9:I9,MATCH('Dashboard'!$C$6,'Source Library'!$D$6:$I$6,0))
B10: SiO₂ | C10: mg/L | D10: 3.5 | E10: 2 | F10: 12 | G10: 30 | H10: 20 | I10: 0.5 | J10: =INDEX(D10:I10,MATCH('Dashboard'!$C$6,'Source Library'!$D$6:$I$6,0))
B11: Na⁺ | C11: mg/L | D11: 10 | E11: 10770 | F11: 20 | G11: 40 | H11: 90 | I11: 1 | J11: =INDEX(D11:I11,MATCH('Dashboard'!$C$6,'Source Library'!$D$6:$I$6,0))
B12: Ca²⁺ | C12: mg/L | D12: 7 | E12: 412 | F12: 40 | G12: 90 | H12: 50 | I12: 1 | J12: =INDEX(D12:I12,MATCH('Dashboard'!$C$6,'Source Library'!$D$6:$I$6,0))
B13: Mg²⁺ | C13: mg/L | D13: 1.5 | E13: 1290 | F13: 10 | G13: 25 | H13: 15 | I13: 0.3 | J13: =INDEX(D13:I13,MATCH('Dashboard'!$C$6,'Source Library'!$D$6:$I$6,0))
B14: Cl⁻ | C14: mg/L | D14: 15 | E14: 19350 | F14: 25 | G14: 50 | H14: 110 | I14: 2 | J14: =INDEX(D14:I14,MATCH('Dashboard'!$C$6,'Source Library'!$D$6:$I$6,0))
B15: PO₄³⁻ | C15: mg/L | D15: 2 | E15: 0.1 | F15: 0.3 | G15: 0.1 | H15: 4 | I15: 0.05 | J15: =INDEX(D15:I15,MATCH('Dashboard'!$C$6,'Source Library'!$D$6:$I$6,0))
B16: SO₄²⁻ | C16: mg/L | D16: 6 | E16: 2710 | F16: 40 | G16: 60 | H16: 70 | I16: 2 | J16: =INDEX(D16:I16,MATCH('Dashboard'!$C$6,'Source Library'!$D$6:$I$6,0))
B17: Alk (CaCO₃) | C17: mg/L | D17: 15 | E17: 116 | F17: 110 | G17: 250 | H17: 120 | I17: 5 | J17: =INDEX(D17:I17,MATCH('Dashboard'!$C$6,'Source Library'!$D$6:$I$6,0))
B18: Free Cl₂ | C18: mg/L | D18: 0.7 | E18: 0 | F18: 0 | G18: 0 | H18: 0 | I18: 0 | J18: =INDEX(D18:I18,MATCH('Dashboard'!$C$6,'Source Library'!$D$6:$I$6,0))
... B30: Recycled non-potable (LEED) 1/0 | C30: - | D30: 0 | E30: 0 | F30: 0 | G30: 0 | H30: 1 | I30: 1 | J30: =INDEX(D30:I30,MATCH('Dashboard'!$C$6,'Source Library'!$D$6:$I$6,0))

Sheet Merkel Solver
B1: Merkel Solver — required tower characteristic KaV/L vs cold-water temperature
B2: KaV/L = Range/4 · Σ 1/(h_sat(T_i) − h_air,i), T_i = T_cold + {0.1,0.4,0.6,0.9}·Range (Chebyshev)
B4: Inlet air enthalpy h_sat(T_wb) | C4: =(0.24*('Dashboard'!$C$9)+0.62198*(0.61094*EXP(17.625*(('Dashboard'!$C$9)-32)/1.8/((('Dashboard'!$C$9)-32)/1.8+243.04)))/('Cooling Tower & Corrugated Fill'!$C$14-(0.61094*EXP(17.625*(('Dashboard'!$C$9)-32)/1.8/((('Dashboard'!$C$9)-32)/1.8+243.04))))*(1061+0.444*('Dashboard'!$C$9))) | D4: BTU/lb
B6: Approach (°F) | C6: T_cold (°F) | D6: Δh @0.1R | E6: Δh @0.4R | F6: Δh @0.6R | G6: Δh @0.9R | H6: Required KaV/L
B7: 0.1 | C7: ='Dashboard'!$C$9+B7 | D7: =(0.24*((C7+0.1*'Cooling Tower & Corrugated Fill'!$C$12))+0.62198*(0.61094*EXP(17.625*(((C7+0.1*'Cooling Tower & Corrugated Fill'!$C$12))-32)/1.8/((((C7+0.1*'Cooling Tower & Corrugated Fill'!$C$12))-32)/1.8+243.04)))/('Cooling Tower & Corrugated Fill'!$C$14-(0.61094*EXP(17.625*(((C7+0.1*'Cooling Tower & Corrugated Fill'!$C$12))-32)/1.8/((((C7+0.1*'Cooling Tower & Corrugated Fill'!$C$12))-32)/1.8+243.04))))*(1061+0.444*((C7+0.1*'Cooling Tower & Corrugated Fill'!$C$12))))-('Merkel Solver'!$C$4+'Cooling Tower & Corrugated Fill'!$C$13*0.1*'Cooling Tower & Corrugated Fill'!$C$12) | E7: =(0.24*((C7+0.4*'Cooling Tower & Corrugated Fill'!$C$12))+0.62198*(0.61094*EXP(17.625*(((C7+0.4*'Cooling Tower & Corrugated Fill'!$C$12))-32)/1.8/((((C7+0.4*'Cooling Tower & Corrugated Fill'!$C$12))-32)/1.8+243.04)))/('Cooling Tower & Corrugated Fill'!$C$14-(0.61094*EXP(17.625*(((C7+0.4*'Cooling Tower & Corrugated Fill'!$C$12))-32)/1.8/((((C7+0.4*'Cooling Tower & Corrugated Fill'!$C$12))-32)/1.8+243.04))))*(1061+0.444*((C7+0.4*'Cooling Tower & Corrugated Fill'!$C$12))))-('Merkel Solver'!$C$4+'Cooling Tower & Corrugated Fill'!$C$13*0.4*'Cooling Tower & Corrugated Fill'!$C$12) | F7: =(0.24*((C7+0.6*'Cooling Tower & Corrugated Fill'!$C$12))+0.62198*(0.61094*EXP(17.625*(((C7+0.6*'Cooling Tower & Corrugated Fill'!$C$12))-32)/1.8/((((C7+0.6*'Cooling Tower & Corrugated Fill'!$C$12))-32)/1.8+243.04)))/('Cooling Tower & Corrugated Fill'!$C$14-(0.61094*EXP(17.625*(((C7+0.6*'Cooling Tower & Corrugated Fill'!$C$12))-32)/1.8/((((C7+0.6*'Cooling Tower & Corrugated Fill'!$C$12))-32)/1.8+243.04))))*(1061+0.444*((C7+0.6*'Cooling Tower & Corrugated Fill'!$C$12))))-('Merkel Solver'!$C$4+'Cooling Tower & Corrugated Fill'!$C$13*0.6*'Cooling Tower & Corrugated Fill'!$C$12) | G7: =(0.24*((C7+0.9*'Cooling Tower & Corrugated Fill'!$C$12))+0.62198*(0.61094*EXP(17.625*(((C7+0.9*'Cooling Tower & Corrugated Fill'!$C$12))-32)/1.8/((((C7+0.9*'Cooling Tower & Corrugated Fill'!$C$12))-32)/1.8+243.04)))/('Cooling Tower & Corrugated Fill'!$C$14-(0.61094*EXP(17.625*(((C7+0.9*'Cooling Tower & Corrugated Fill'!$C$12))-32)/1.8/((((C7+0.9*'Cooling Tower & Corrugated Fill'!$C$12))-32)/1.8+243.04))))*(1061+0.444*((C7+0.9*'Cooling Tower & Corrugated Fill'!$C$12))))-('Merkel Solver'!$C$4+'Cooling Tower & Corrugated Fill'!$C$13*0.9*'Cooling Tower & Corrugated Fill'!$C$12) | H7: =IF(MIN(D7:G7)<=0,99999,'Cooling Tower & Corrugated Fill'!$C$12/4*(1/D7+1/E7+1/F7+1/G7))
B8: 0.2 | C8: ='Dashboard'!$C$9+B8 | D8: =(0.24*((C8+0.1*'Cooling Tower & Corrugated Fill'!$C$12))+0.62198*(0.61094*EXP(17.625*(((C8+0.1*'Cooling Tower & Corrugated Fill'!$C$12))-32)/1.8/((((C8+0.1*'Cooling Tower & Corrugated Fill'!$C$12))-32)/1.8+243.04)))/('Cooling Tower & Corrugated Fill'!$C$14-(0.61094*EXP(17.625*(((C8+0.1*'Cooling Tower & Corrugated Fill'!$C$12))-32)/1.8/((((C8+0.1*'Cooling Tower & Corrugated Fill'!$C$12))-32)/1.8+243.04))))*(1061+0.444*((C8+0.1*'Cooling Tower & Corrugated Fill'!$C$12))))-('Merkel Solver'!$C$4+'Cooling Tower & Corrugated Fill'!$C$13*0.1*'Cooling Tower & Corrugated Fill'!$C$12) | E8: =(0.24*((C8+0.4*'Cooling Tower & Corrugated Fill'!$C$12))+0.62198*(0.61094*EXP(17.625*(((C8+0.4*'Cooling Tower & Corrugated Fill'!$C$12))-32)/1.8/((((C8+0.4*'Cooling Tower & Corrugated Fill'!$C$12))-32)/1.8+243.04)))/('Cooling Tower & Corrugated Fill'!$C$14-(0.61094*EXP(17.625*(((C8+0.4*'Cooling Tower & Corrugated Fill'!$C$12))-32)/1.8/((((C8+0.4*'Cooling Tower & Corrugated Fill'!$C$12))-32)/1.8+243.04))))*(1061+0.444*((C8+0.4*'Cooling Tower & Corrugated Fill'!$C$12))))-('Merkel Solver'!$C$4+'Cooling Tower & Corrugated Fill'!$C$13*0.4*'Cooling Tower & Corrugated Fill'!$C$12) | F8: =(0.24*((C8+0.6*'Cooling Tower & Corrugated Fill'!$C$12))+0.62198*(0.61094*EXP(17.625*(((C8+0.6*'Cooling Tower & Corrugated Fill'!$C$12))-32)/1.8/((((C8+0.6*'Cooling Tower & Corrugated Fill'!$C$12))-32)/1.8+243.04)))/('Cooling Tower & Corrugated Fill'!$C$14-(0.61094*EXP(17.625*(((C8+0.6*'Cooling Tower & Corrugated Fill'!$C$12))-32)/1.8/((((C8+0.6*'Cooling Tower & Corrugated Fill'!$C$12))-32)/1.8+243.04))))*(1061+0.444*((C8+0.6*'Cooling Tower & Corrugated Fill'!$C$12))))-('Merkel Solver'!$C$4+'Cooling Tower & Corrugated Fill'!$C$13*0.6*'Cooling Tower & Corrugated Fill'!$C$12) | G8: =(0.24*((C8+0.9*'Cooling Tower & Corrugated Fill'!$C$12))+0.62198*(0.61094*EXP(17.625*(((C8+0.9*'Cooling Tower & Corrugated Fill'!$C$12))-32)/1.8/((((C8+0.9*'Cooling Tower & Corrugated Fill'!$C$12))-32)/1.8+243.04)))/('Cooling Tower & Corrugated Fill'!$C$14-(0.61094*EXP(17.625*(((C8+0.9*'Cooling Tower & Corrugated Fill'!$C$12))-32)/1.8/((((C8+0.9*'Cooling Tower & Corrugated Fill'!$C$12))-32)/1.8+243.04))))*(1061+0.444*((C8+0.9*'Cooling Tower & Corrugated Fill'!$C$12))))-('Merkel Solver'!$C$4+'Cooling Tower & Corrugated Fill'!$C$13*0.9*'Cooling Tower & Corrugated Fill'!$C$12) | H8: =IF(MIN(D8:G8)<=0,99999,'Cooling Tower & Corrugated Fill'!$C$12/4*(1/D8+1/E8+1/F8+1/G8))
B9: 0.3 | C9: ='Dashboard'!$C$9+B9 | D9: =(0.24*((C9+0.1*'Cooling Tower & Corrugated Fill'!$C$12))+0.62198*(0.61094*EXP(17.625*(((C9+0.1*'Cooling Tower & Corrugated Fill'!$C$12))-32)/1.8/((((C9+0.1*'Cooling Tower & Corrugated Fill'!$C$12))-32)/1.8+243.04)))/('Cooling Tower & Corrugated Fill'!$C$14-(0.61094*EXP(17.625*(((C9+0.1*'Cooling Tower & Corrugated Fill'!$C$12))-32)/1.8/((((C9+0.1*'Cooling Tower & Corrugated Fill'!$C$12))-32)/1.8+243.04))))*(1061+0.444*((C9+0.1*'Cooling Tower & Corrugated Fill'!$C$12))))-('Merkel Solver'!$C$4+'Cooling Tower & Corrugated Fill'!$C$13*0.1*'Cooling Tower & Corrugated Fill'!$C$12) | E9: =(0.24*((C9+0.4*'Cooling Tower & Corrugated Fill'!$C$12))+0.62198*(0.61094*EXP(17.625*(((C9+0.4*'Cooling Tower & Corrugated Fill'!$C$12))-32)/1.8/((((C9+0.4*'Cooling Tower & Corrugated Fill'!$C$12))-32)/1.8+243.04)))/('Cooling Tower & Corrugated Fill'!$C$14-(0.61094*EXP(17.625*(((C9+0.4*'Cooling Tower & Corrugated Fill'!$C$12))-32)/1.8/((((C9+0.4*'Cooling Tower & Corrugated Fill'!$C$12))-32)/1.8+243.04))))*(1061+0.444*((C9+0.4*'Cooling Tower & Corrugated Fill'!$C$12))))-('Merkel Solver'!$C$4+'Cooling Tower & Corrugated Fill'!$C$13*0.4*'Cooling Tower & Corrugated Fill'!$C$12) | F9: =(0.24*((C9+0.6*'Cooling Tower & Corrugated Fill'!$C$12))+0.62198*(0.61094*EXP(17.625*(((C9+0.6*'Cooling Tower & Corrugated Fill'!$C$12))-32)/1.8/((((C9+0.6*'Cooling Tower & Corrugated Fill'!$C$12))-32)/1.8+243.04)))/('Cooling Tower & Corrugated Fill'!$C$14-(0.61094*EXP(17.625*(((C9+0.6*'Cooling Tower & Corrugated Fill'!$C$12))-32)/1.8/((((C9+0.6*'Cooling Tower & Corrugated Fill'!$C$12))-32)/1.8+243.04))))*(1061+0.444*((C9+0.6*'Cooling Tower & Corrugated Fill'!$C$12))))-('Merkel Solver'!$C$4+'Cooling Tower & Corrugated Fill'!$C$13*0.6*'Cooling Tower & Corrugated Fill'!$C$12) | G9: =(0.24*((C9+0.9*'Cooling Tower & Corrugated Fill'!$C$12))+0.62198*(0.61094*EXP(17.625*(((C9+0.9*'Cooling Tower & Corrugated Fill'!$C$12))-32)/1.8/((((C9+0.9*'Cooling Tower & Corrugated Fill'!$C$12))-32)/1.8+243.04)))/('Cooling Tower & Corrugated Fill'!$C$14-(0.61094*EXP(17.625*(((C9+0.9*'Cooling Tower & Corrugated Fill'!$C$12))-32)/1.8/((((C9+0.9*'Cooling Tower & Corrugated Fill'!$C$12))-32)/1.8+243.04))))*(1061+0.444*((C9+0.9*'Cooling Tower & Corrugated Fill'!$C$12))))-('Merkel Solver'!$C$4+'Cooling Tower & Corrugated Fill'!$C$13*0.9*'Cooling Tower & Corrugated Fill'!$C$12) | H9: =IF(MIN(D9:G9)<=0,99999,'Cooling Tower & Corrugated Fill'!$C$12/4*(1/D9+1/E9+1/F9+1/G9))
B10: 0.4 | C10: ='Dashboard'!$C$9+B10 | D10: =(0.24*((C10+0.1*'Cooling Tower & Corrugated Fill'!$C$12))+0.62198*(0.61094*EXP(17.625*(((C10+0.1*'Cooling Tower & Corrugated Fill'!$C$12))-32)/1.8/((((C10+0.1*'Cooling Tower & Corrugated Fill'!$C$12))-32)/1.8+243.04)))/('Cooling Tower & Corrugated Fill'!$C$14-(0.61094*EXP(17.625*(((C10+0.1*'Cooling Tower & Corrugated Fill'!$C$12))-32)/1.8/((((C10+0.1*'Cooling Tower & Corrugated Fill'!$C$12))-32)/1.8+243.04))))*(1061+0.444*((C10+0.1*'Cooling Tower & Corrugated Fill'!$C$12))))-('Merkel Solver'!$C$4+'Cooling Tower & Corrugated Fill'!$C$13*0.1*'Cooling Tower & Corrugated Fill'!$C$12) | E10: =(0.24*((C10+0.4*'Cooling Tower & Corrugated Fill'!$C$12))+0.62198*(0.61094*EXP(17.625*(((C10+0.4*'Cooling Tower & Corrugated Fill'!$C$12))-32)/1.8/((((C10+0.4*'Cooling Tower & Corrugated Fill'!$C$12))-32)/1.8+243.04)))/('Cooling Tower & Corrugated Fill'!$C$14-(0.61094*EXP(17.625*(((C10+0.4*'Cooling Tower & Corrugated Fill'!$C$12))-32)/1.8/((((C10+0.4*'Cooling Tower & Corrugated Fill'!$C$12))-32)/1.8+243.04))))*(1061+0.444*((C10+0.4*'Cooling Tower & Corrugated Fill'!$C$12))))-('Merkel Solver'!$C$4+'Cooling Tower & Corrugated Fill'!$C$13*0.4*'Cooling Tower & Corrugated Fill'!$C$12) | F10: =(0.24*((C10+0.6*'Cooling Tower & Corrugated Fill'!$C$12))+0.62198*(0.61094*EXP(17.625*(((C10+0.6*'Cooling Tower & Corrugated Fill'!$C$12))-32)/1.8/((((C10+0.6*'Cooling Tower & Corrugated Fill'!$C$12))-32)/1.8+243.04)))/('Cooling Tower & Corrugated Fill'!$C$14-(0.61094*EXP(17.625*(((C10+0.6*'Cooling Tower & Corrugated Fill'!$C$12))-32)/1.8/((((C10+0.6*'Cooling Tower & Corrugated Fill'!$C$12))-32)/1.8+243.04))))*(1061+0.444*((C10+0.6*'Cooling Tower & Corrugated Fill'!$C$12))))-('Merkel Solver'!$C$4+'Cooling Tower & Corrugated Fill'!$C$13*0.6*'Cooling Tower & Corrugated Fill'!$C$12) | G10: =(0.24*((C10+0.9*'Cooling Tower & Corrugated Fill'!$C$12))+0.62198*(0.61094*EXP(17.625*(((C10+0.9*'Cooling Tower & Corrugated Fill'!$C$12))-32)/1.8/((((C10+0.9*'Cooling Tower & Corrugated Fill'!$C$12))-32)/1.8+243.04)))/('Cooling Tower & Corrugated Fill'!$C$14-(0.61094*EXP(17.625*(((C10+0.9*'Cooling Tower & Corrugated Fill'!$C$12))-32)/1.8/((((C10+0.9*'Cooling Tower & Corrugated Fill'!$C$12))-32)/1.8+243.04))))*(1061+0.444*((C10+0.9*'Cooling Tower & Corrugated Fill'!$C$12))))-('Merkel Solver'!$C$4+'Cooling Tower & Corrugated Fill'!$C$13*0.9*'Cooling Tower & Corrugated Fill'!$C$12) | H10: =IF(MIN(D10:G10)<=0,99999,'Cooling Tower & Corrugated Fill'!$C$12/4*(1/D10+1/E10+1/F10+1/G10))
B11: 0.5 | C11: ='Dashboard'!$C$9+B11 | D11: =(0.24*((C11+0.1*'Cooling Tower & Corrugated Fill'!$C$12))+0.62198*(0.61094*EXP(17.625*(((C11+0.1*'Cooling Tower & Corrugated Fill'!$C$12))-32)/1.8/((((C11+0.1*'Cooling Tower & Corrugated Fill'!$C$12))-32)/1.8+243.04)))/('Cooling Tower & Corrugated Fill'!$C$14-(0.61094*EXP(17.625*(((C11+0.1*'Cooling Tower & Corrugated Fill'!$C$12))-32)/1.8/((((C11+0.1*'Cooling Tower & Corrugated Fill'!$C$12))-32)/1.8+243.04))))*(1061+0.444*((C11+0.1*'Cooling Tower & Corrugated Fill'!$C$12))))-('Merkel Solver'!$C$4+'Cooling Tower & Corrugated Fill'!$C$13*0.1*'Cooling Tower & Corrugated Fill'!$C$12) | E11: =(0.24*((C11+0.4*'Cooling Tower & Corrugated Fill'!$C$12))+0.62198*(0.61094*EXP(17.625*(((C11+0.4*'Cooling Tower & Corrugated Fill'!$C$12))-32)/1.8/((((C11+0.4*'Cooling Tower & Corrugated Fill'!$C$12))-32)/1.8+243.04)))/('Cooling Tower & Corrugated Fill'!$C$14-(0.61094*EXP(17.625*(((C11+0.4*'Cooling Tower & Corrugated Fill'!$C$12))-32)/1.8/((((C11+0.4*'Cooling Tower & Corrugated Fill'!$C$12))-32)/1.8+243.04))))*(1061+0.444*((C11+0.4*'Cooling Tower & Corrugated Fill'!$C$12))))-('Merkel Solver'!$C$4+'Cooling Tower & Corrugated Fill'!$C$13*0.4*'Cooling Tower & Corrugated Fill'!$C$12) | F11: =(0.24*((C11+0.6*'Cooling Tower & Corrugated Fill'!$C$12))+0.62198*(0.61094*EXP(17.625*(((C11+0.6*'Cooling Tower & Corrugated Fill'!$C$12))-32)/1.8/((((C11+0.6*'Cooling Tower & Corrugated Fill'!$C$12))-32)/1.8+243.04)))/('Cooling Tower & Corrugated Fill'!$C$14-(0.61094*EXP(17.625*(((C11+0.6*'Cooling Tower & Corrugated Fill'!$C$12))-32)/1.8/((((C11+0.6*'Cooling Tower & Corrugated Fill'!$C$12))-32)/1.8+243.04))))*(1061+0.444*((C11+0.6*'Cooling Tower & Corrugated Fill'!$C$12))))-('Merkel Solver'!$C$4+'Cooling Tower & Corrugated Fill'!$C$13*0.6*'Cooling Tower & Corrugated Fill'!$C$12) | G11: =(0.24*((C11+0.9*'Cooling Tower & Corrugated Fill'!$C$12))+0.62198*(0.61094*EXP(17.625*(((C11+0.9*'Cooling Tower & Corrugated Fill'!$C$12))-32)/1.8/((((C11+0.9*'Cooling Tower & Corrugated Fill'!$C$12))-32)/1.8+243.04)))/('Cooling Tower & Corrugated Fill'!$C$14-(0.61094*EXP(17.625*(((C11+0.9*'Cooling Tower & Corrugated Fill'!$C$12))-32)/1.8/((((C11+0.9*'Cooling Tower & Corrugated Fill'!$C$12))-32)/1.8+243.04))))*(1061+0.444*((C11+0.9*'Cooling Tower & Corrugated Fill'!$C$12))))-('Merkel Solver'!$C$4+'Cooling Tower & Corrugated Fill'!$C$13*0.9*'Cooling Tower & Corrugated Fill'!$C$12) | H11: =IF(MIN(D11:G11)<=0,99999,'Cooling Tower & Corrugated Fill'!$C$12/4*(1/D11+1/E11+1/F11+1/G11))
B12: 0.6 | C12: ='Dashboard'!$C$9+B12 | D12: =(0.24*((C12+0.1*'Cooling Tower & Corrugated Fill'!$C$12))+0.62198*(0.61094*EXP(17.625*(((C12+0.1*'Cooling Tower & Corrugated Fill'!$C$12))-32)/1.8/((((C12+0.1*'Cooling Tower & Corrugated Fill'!$C$12))-32)/1.8+243.04)))/('Cooling Tower & Corrugated Fill'!$C$14-(0.61094*EXP(17.625*(((C12+0.1*'Cooling Tower & Corrugated Fill'!$C$12))-32)/1.8/((((C12+0.1*'Cooling Tower & Corrugated Fill'!$C$12))-32)/1.8+243.04))))*(1061+0.444*((C12+0.1*'Cooling Tower & Corrugated Fill'!$C$12))))-('Merkel Solver'!$C$4+'Cooling Tower & Corrugated Fill'!$C$13*0.1*'Cooling Tower & Corrugated Fill'!$C$12) | E12: =(0.24*((C12+0.4*'Cooling Tower & Corrugated Fill'!$C$12))+0.62198*(0.61094*EXP(17.625*(((C12+0.4*'Cooling Tower & Corrugated Fill'!$C$12))-32)/1.8/((((C12+0.4*'Cooling Tower & Corrugated Fill'!$C$12))-32)/1.8+243.04)))/('Cooling Tower & Corrugated Fill'!$C$14-(0.61094*EXP(17.625*(((C12+0.4*'Cooling Tower & Corrugated Fill'!$C$12))-32)/1.8/((((C12+0.4*'Cooling Tower & Corrugated Fill'!$C$12))-32)/1.8+243.04))))*(1061+0.444*((C12+0.4*'Cooling Tower & Corrugated Fill'!$C$12))))-('Merkel Solver'!$C$4+'Cooling Tower & Corrugated Fill'!$C$13*0.4*'Cooling Tower & Corrugated Fill'!$C$12) | F12: =(0.24*((C12+0.6*'Cooling Tower & Corrugated Fill'!$C$12))+0.62198*(0.61094*EXP(17.625*(((C12+0.6*'Cooling Tower & Corrugated Fill'!$C$12))-32)/1.8/((((C12+0.6*'Cooling Tower & Corrugated Fill'!$C$12))-32)/1.8+243.04)))/('Cooling Tower & Corrugated Fill'!$C$14-(0.61094*EXP(17.625*(((C12+0.6*'Cooling Tower & Corrugated Fill'!$C$12))-32)/1.8/((((C12+0.6*'Cooling Tower & Corrugated Fill'!$C$12))-32)/1.8+243.04))))*(1061+0.444*((C12+0.6*'Cooling Tower & Corrugated Fill'!$C$12))))-('Merkel Solver'!$C$4+'Cooling Tower & Corrugated Fill'!$C$13*0.6*'Cooling Tower & Corrugated Fill'!$C$12) | G12: =(0.24*((C12+0.9*'Cooling Tower & Corrugated Fill'!$C$12))+0.62198*(0.61094*EXP(17.625*(((C12+0.9*'Cooling Tower & Corrugated Fill'!$C$12))-32)/1.8/((((C12+0.9*'Cooling Tower & Corrugated Fill'!$C$12))-32)/1.8+243.04)))/('Cooling Tower & Corrugated Fill'!$C$14-(0.61094*EXP(17.625*(((C12+0.9*'Cooling Tower & Corrugated Fill'!$C$12))-32)/1.8/((((C12+0.9*'Cooling Tower & Corrugated Fill'!$C$12))-32)/1.8+243.04))))*(1061+0.444*((C12+0.9*'Cooling Tower & Corrugated Fill'!$C$12))))-('Merkel Solver'!$C$4+'Cooling Tower & Corrugated Fill'!$C$13*0.9*'Cooling Tower & Corrugated Fill'!$C$12) | H12: =IF(MIN(D12:G12)<=0,99999,'Cooling Tower & Corrugated Fill'!$C$12/4*(1/D12+1/E12+1/F12+1/G12))
B13: 0.7 | C13: ='Dashboard'!$C$9+B13 | D13: =(0.24*((C13+0.1*'Cooling Tower & Corrugated Fill'!$C$12))+0.62198*(0.61094*EXP(17.625*(((C13+0.1*'Cooling Tower & Corrugated Fill'!$C$12))-32)/1.8/((((C13+0.1*'Cooling Tower & Corrugated Fill'!$C$12))-32)/1.8+243.04)))/('Cooling Tower & Corrugated Fill'!$C$14-(0.61094*EXP(17.625*(((C13+0.1*'Cooling Tower & Corrugated Fill'!$C$12))-32)/1.8/((((C13+0.1*'Cooling Tower & Corrugated Fill'!$C$12))-32)/1.8+243.04))))*(1061+0.444*((C13+0.1*'Cooling Tower & Corrugated Fill'!$C$12))))-('Merkel Solver'!$C$4+'Cooling Tower & Corrugated Fill'!$C$13*0.1*'Cooling Tower & Corrugated Fill'!$C$12) | E13: =(0.24*((C13+0.4*'Cooling Tower & Corrugated Fill'!$C$12))+0.62198*(0.61094*EXP(17.625*(((C13+0.4*'Cooling Tower & Corrugated Fill'!$C$12))-32)/1.8/((((C13+0.4*'Cooling Tower & Corrugated Fill'!$C$12))-32)/1.8+243.04)))/('Cooling Tower & Corrugated Fill'!$C$14-(0.61094*EXP(17.625*(((C13+0.4*'Cooling Tower & Corrugated Fill'!$C$12))-32)/1.8/((((C13+0.4*'Cooling Tower & Corrugated Fill'!$C$12))-32)/1.8+243.04))))*(1061+0.444*((C13+0.4*'Cooling Tower & Corrugated Fill'!$C$12))))-('Merkel Solver'!$C$4+'Cooling Tower & Corrugated Fill'!$C$13*0.4*'Cooling Tower & Corrugated Fill'!$C$12) | F13: =(0.24*((C13+0.6*'Cooling Tower & Corrugated Fill'!$C$12))+0.62198*(0.61094*EXP(17.625*(((C13+0.6*'Cooling Tower & Corrugated Fill'!$C$12))-32)/1.8/((((C13+0.6*'Cooling Tower & Corrugated Fill'!$C$12))-32)/1.8+243.04)))/('Cooling Tower & Corrugated Fill'!$C$14-(0.61094*EXP(17.625*(((C13+0.6*'Cooling Tower & Corrugated Fill'!$C$12))-32)/1.8/((((C13+0.6*'Cooling Tower & Corrugated Fill'!$C$12))-32)/1.8+243.04))))*(1061+0.444*((C13+0.6*'Cooling Tower & Corrugated Fill'!$C$12))))-('Merkel Solver'!$C$4+'Cooling Tower & Corrugated Fill'!$C$13*0.6*'Cooling Tower & Corrugated Fill'!$C$12) | G13: =(0.24*((C13+0.9*'Cooling Tower & Corrugated Fill'!$C$12))+0.62198*(0.61094*EXP(17.625*(((C13+0.9*'Cooling Tower & Corrugated Fill'!$C$12))-32)/1.8/((((C13+0.9*'Cooling Tower & Corrugated Fill'!$C$12))-32)/1.8+243.04)))/('Cooling Tower & Corrugated Fill'!$C$14-(0.61094*EXP(17.625*(((C13+0.9*'Cooling Tower & Corrugated Fill'!$C$12))-32)/1.8/((((C13+0.9*'Cooling Tower & Corrugated Fill'!$C$12))-32)/1.8+243.04))))*(1061+0.444*((C13+0.9*'Cooling Tower & Corrugated Fill'!$C$12))))-('Merkel Solver'!$C$4+'Cooling Tower & Corrugated Fill'!$C$13*0.9*'Cooling Tower & Corrugated Fill'!$C$12) | H13: =IF(MIN(D13:G13)<=0,99999,'Cooling Tower & Corrugated Fill'!$C$12/4*(1/D13+1/E13+1/F13+1/G13))
B14: 0.8 | C14: ='Dashboard'!$C$9+B14 | D14: =(0.24*((C14+0.1*'Cooling Tower & Corrugated Fill'!$C$12))+0.62198*(0.61094*EXP(17.625*(((C14+0.1*'Cooling Tower & Corrugated Fill'!$C$12))-32)/1.8/((((C14+0.1*'Cooling Tower & Corrugated Fill'!$C$12))-32)/1.8+243.04)))/('Cooling Tower & Corrugated Fill'!$C$14-(0.61094*EXP(17.625*(((C14+0.1*'Cooling Tower & Corrugated Fill'!$C$12))-32)/1.8/((((C14+0.1*'Cooling Tower & Corrugated Fill'!$C$12))-32)/1.8+243.04))))*(1061+0.444*((C14+0.1*'Cooling Tower & Corrugated Fill'!$C$12))))-('Merkel Solver'!$C$4+'Cooling Tower & Corrugated Fill'!$C$13*0.1*'Cooling Tower & Corrugated Fill'!$C$12) | E14: =(0.24*((C14+0.4*'Cooling Tower & Corrugated Fill'!$C$12))+0.62198*(0.61094*EXP(17.625*(((C14+0.4*'Cooling Tower & Corrugated Fill'!$C$12))-32)/1.8/((((C14+0.4*'Cooling Tower & Corrugated Fill'!$C$12))-32)/1.8+243.04)))/('Cooling Tower & Corrugated Fill'!$C$14-(0.61094*EXP(17.625*(((C14+0.4*'Cooling Tower & Corrugated Fill'!$C$12))-32)/1.8/((((C14+0.4*'Cooling Tower & Corrugated Fill'!$C$12))-32)/1.8+243.04))))*(1061+0.444*((C14+0.4*'Cooling Tower & Corrugated Fill'!$C$12))))-('Merkel Solver'!$C$4+'Cooling Tower & Corrugated Fill'!$C$13*0.4*'Cooling Tower & Corrugated Fill'!$C$12) | F14: =(0.24*((C14+0.6*'Cooling Tower & Corrugated Fill'!$C$12))+0.62198*(0.61094*EXP(17.625*(((C14+0.6*'Cooling Tower & Corrugated Fill'!$C$12))-32)/1.8/((((C14+0.6*'Cooling Tower & Corrugated Fill'!$C$12))-32)/1.8+243.04)))/('Cooling Tower & Corrugated Fill'!$C$14-(0.61094*EXP(17.625*(((C14+0.6*'Cooling Tower & Corrugated Fill'!$C$12))-32)/1.8/((((C14+0.6*'Cooling Tower & Corrugated Fill'!$C$12))-32)/1.8+243.04))))*(1061+0.444*((C14+0.6*'Cooling Tower & Corrugated Fill'!$C$12))))-('Merkel Solver'!$C$4+'Cooling Tower & Corrugated Fill'!$C$13*0.6*'Cooling Tower & Corrugated Fill'!$C$12) | G14: =(0.24*((C14+0.9*'Cooling Tower & Corrugated Fill'!$C$12))+0.62198*(0.61094*EXP(17.625*(((C14+0.9*'Cooling Tower & Corrugated Fill'!$C$12))-32)/1.8/((((C14+0.9*'Cooling Tower & Corrugated Fill'!$C$12))-32)/1.8+243.04)))/('Cooling Tower & Corrugated Fill'!$C$14-(0.61094*EXP(17.625*(((C14+0.9*'Cooling Tower & Corrugated Fill'!$C$12))-32)/1.8/((((C14+0.9*'Cooling Tower & Corrugated Fill'!$C$12))-32)/1.8+243.04))))*(1061+0.444*((C14+0.9*'Cooling Tower & Corrugated Fill'!$C$12))))-('Merkel Solver'!$C$4+'Cooling Tower & Corrugated Fill'!$C$13*0.9*'Cooling Tower & Corrugated Fill'!$C$12) | H14: =IF(MIN(D14:G14)<=0,99999,'Cooling Tower & Corrugated Fill'!$C$12/4*(1/D14+1/E14+1/F14+1/G14))
B15: 0.9 | C15: ='Dashboard'!$C$9+B15 | D15: =(0.24*((C15+0.1*'Cooling Tower & Corrugated Fill'!$C$12))+0.62198*(0.61094*EXP(17.625*(((C15+0.1*'Cooling Tower & Corrugated Fill'!$C$12))-32)/1.8/((((C15+0.1*'Cooling Tower & Corrugated Fill'!$C$12))-32)/1.8+243.04)))/('Cooling Tower & Corrugated Fill'!$C$14-(0.61094*EXP(17.625*(((C15+0.1*'Cooling Tower & Corrugated Fill'!$C$12))-32)/1.8/((((C15+0.1*'Cooling Tower & Corrugated Fill'!$C$12))-32)/1.8+243.04))))*(1061+0.444*((C15+0.1*'Cooling Tower & Corrugated Fill'!$C$12))))-('Merkel Solver'!$C$4+'Cooling Tower & Corrugated Fill'!$C$13*0.1*'Cooling Tower & Corrugated Fill'!$C$12) | E15: =(0.24*((C15+0.4*'Cooling Tower & Corrugated Fill'!$C$12))+0.62198*(0.61094*EXP(17.625*(((C15+0.4*'Cooling Tower & Corrugated Fill'!$C$12))-32)/1.8/((((C15+0.4*'Cooling Tower & Corrugated Fill'!$C$12))-32)/1.8+243.04)))/('Cooling Tower & Corrugated Fill'!$C$14-(0.61094*EXP(17.625*(((C15+0.4*'Cooling Tower & Corrugated Fill'!$C$12))-32)/1.8/((((C15+0.4*'Cooling Tower & Corrugated Fill'!$C$12))-32)/1.8+243.04))))*(1061+0.444*((C15+0.4*'Cooling Tower & Corrugated Fill'!$C$12))))-('Merkel Solver'!$C$4+'Cooling Tower & Corrugated Fill'!$C$13*0.4*'Cooling Tower & Corrugated Fill'!$C$12) | F15: =(0.24*((C15+0.6*'Cooling Tower & Corrugated Fill'!$C$12))+0.62198*(0.61094*EXP(17.625*(((C15+0.6*'Cooling Tower & Corrugated Fill'!$C$12))-32)/1.8/((((C15+0.6*'Cooling Tower & Corrugated Fill'!$C$12))-32)/1.8+243.04)))/('Cooling Tower & Corrugated Fill'!$C$14-(0.61094*EXP(17.625*(((C15+0.6*'Cooling Tower & Corrugated Fill'!$C$12))-32)/1.8/((((C15+0.6*'Cooling Tower & Corrugated Fill'!$C$12))-32)/1.8+243.04))))*(1061+0.444*((C15+0.6*'Cooling Tower & Corrugated Fill'!$C$12))))-('Merkel Solver'!$C$4+'Cooling Tower & Corrugated Fill'!$C$13*0.6*'Cooling Tower & Corrugated Fill'!$C$12) | G15: =(0.24*((C15+0.9*'Cooling Tower & Corrugated Fill'!$C$12))+0.62198*(0.61094*EXP(17.625*(((C15+0.9*'Cooling Tower & Corrugated Fill'!$C$12))-32)/1.8/((((C15+0.9*'Cooling Tower & Corrugated Fill'!$C$12))-32)/1.8+243.04)))/('Cooling Tower & Corrugated Fill'!$C$14-(0.61094*EXP(17.625*(((C15+0.9*'Cooling Tower & Corrugated Fill'!$C$12))-32)/1.8/((((C15+0.9*'Cooling Tower & Corrugated Fill'!$C$12))-32)/1.8+243.04))))*(1061+0.444*((C15+0.9*'Cooling Tower & Corrugated Fill'!$C$12))))-('Merkel Solver'!$C$4+'Cooling Tower & Corrugated Fill'!$C$13*0.9*'Cooling Tower & Corrugated Fill'!$C$12) | H15: =IF(MIN(D15:G15)<=0,99999,'Cooling Tower & Corrugated Fill'!$C$12/4*(1/D15+1/E15+1/F15+1/G15))
B16: 1 | C16: ='Dashboard'!$C$9+B16 | D16: =(0.24*((C16+0.1*'Cooling Tower & Corrugated Fill'!$C$12))+0.62198*(0.61094*EXP(17.625*(((C16+0.1*'Cooling Tower & Corrugated Fill'!$C$12))-32)/1.8/((((C16+0.1*'Cooling Tower & Corrugated Fill'!$C$12))-32)/1.8+243.04)))/('Cooling Tower & Corrugated Fill'!$C$14-(0.61094*EXP(17.625*(((C16+0.1*'Cooling Tower & Corrugated Fill'!$C$12))-32)/1.8/((((C16+0.1*'Cooling Tower & Corrugated Fill'!$C$12))-32)/1.8+243.04))))*(1061+0.444*((C16+0.1*'Cooling Tower & Corrugated Fill'!$C$12))))-('Merkel Solver'!$C$4+'Cooling Tower & Corrugated Fill'!$C$13*0.1*'Cooling Tower & Corrugated Fill'!$C$12) | E16: =(0.24*((C16+0.4*'Cooling Tower & Corrugated Fill'!$C$12))+0.62198*(0.61094*EXP(17.625*(((C16+0.4*'Cooling Tower & Corrugated Fill'!$C$12))-32)/1.8/((((C16+0.4*'Cooling Tower & Corrugated Fill'!$C$12))-32)/1.8+243.04)))/('Cooling Tower & Corrugated Fill'!$C$14-(0.61094*EXP(17.625*(((C16+0.4*'Cooling Tower & Corrugated Fill'!$C$12))-32)/1.8/((((C16+0.4*'Cooling Tower & Corrugated Fill'!$C$12))-32)/1.8+243.04))))*(1061+0.444*((C16+0.4*'Cooling Tower & Corrugated Fill'!$C$12))))-('Merkel Solver'!$C$4+'Cooling Tower & Corrugated Fill'!$C$13*0.4*'Cooling Tower & Corrugated Fill'!$C$12) | F16: =(0.24*((C16+0.6*'Cooling Tower & Corrugated Fill'!$C$12))+0.62198*(0.61094*EXP(17.625*(((C16+0.6*'Cooling Tower & Corrugated Fill'!$C$12))-32)/1.8/((((C16+0.6*'Cooling Tower & Corrugated Fill'!$C$12))-32)/1.8+243.04)))/('Cooling Tower & Corrugated Fill'!$C$14-(0.61094*EXP(17.625*(((C16+0.6*'Cooling Tower & Corrugated Fill'!$C$12))-32)/1.8/((((C16+0.6*'Cooling Tower & Corrugated Fill'!$C$12))-32)/1.8+243.04))))*(1061+0.444*((C16+0.6*'Cooling Tower & Corrugated Fill'!$C$12))))-('Merkel Solver'!$C$4+'Cooling Tower & Corrugated Fill'!$C$13*0.6*'Cooling Tower & Corrugated Fill'!$C$12) | G16: =(0.24*((C16+0.9*'Cooling Tower & Corrugated Fill'!$C$12))+0.62198*(0.61094*EXP(17.625*(((C16+0.9*'Cooling Tower & Corrugated Fill'!$C$12))-32)/1.8/((((C16+0.9*'Cooling Tower & Corrugated Fill'!$C$12))-32)/1.8+243.04)))/('Cooling Tower & Corrugated Fill'!$C$14-(0.61094*EXP(17.625*(((C16+0.9*'Cooling Tower & Corrugated Fill'!$C$12))-32)/1.8/((((C16+0.9*'Cooling Tower & Corrugated Fill'!$C$12))-32)/1.8+243.04))))*(1061+0.444*((C16+0.9*'Cooling Tower & Corrugated Fill'!$C$12))))-('Merkel Solver'!$C$4+'Cooling Tower & Corrugated Fill'!$C$13*0.9*'Cooling Tower & Corrugated Fill'!$C$12) | H16: =IF(MIN(D16:G16)<=0,99999,'Cooling Tower & Corrugated Fill'!$C$12/4*(1/D16+1/E16+1/F16+1/G16))
B17: 1.1 | C17: ='Dashboard'!$C$9+B17 | D17: =(0.24*((C17+0.1*'Cooling Tower & Corrugated Fill'!$C$12))+0.62198*(0.61094*EXP(17.625*(((C17+0.1*'Cooling Tower & Corrugated Fill'!$C$12))-32)/1.8/((((C17+0.1*'Cooling Tower & Corrugated Fill'!$C$12))-32)/1.8+243.04)))/('Cooling Tower & Corrugated Fill'!$C$14-(0.61094*EXP(17.625*(((C17+0.1*'Cooling Tower & Corrugated Fill'!$C$12))-32)/1.8/((((C17+0.1*'Cooling Tower & Corrugated Fill'!$C$12))-32)/1.8+243.04))))*(1061+0.444*((C17+0.1*'Cooling Tower & Corrugated Fill'!$C$12))))-('Merkel Solver'!$C$4+'Cooling Tower & Corrugated Fill'!$C$13*0.1*'Cooling Tower & Corrugated Fill'!$C$12) | E17: =(0.24*((C17+0.4*'Cooling Tower & Corrugated Fill'!$C$12))+0.62198*(0.61094*EXP(17.625*(((C17+0.4*'Cooling Tower & Corrugated Fill'!$C$12))-32)/1.8/((((C17+0.4*'Cooling Tower & Corrugated Fill'!$C$12))-32)/1.8+243.04)))/('Cooling Tower & Corrugated Fill'!$C$14-(0.61094*EXP(17.625*(((C17+0.4*'Cooling Tower & Corrugated Fill'!$C$12))-32)/1.8/((((C17+0.4*'Cooling Tower & Corrugated Fill'!$C$12))-32)/1.8+243.04))))*(1061+0.444*((C17+0.4*'Cooling Tower & Corrugated Fill'!$C$12))))-('Merkel Solver'!$C$4+'Cooling Tower & Corrugated Fill'!$C$13*0.4*'Cooling Tower & Corrugated Fill'!$C$12) | F17: =(0.24*((C17+0.6*'Cooling Tower & Corrugated Fill'!$C$12))+0.62198*(0.61094*EXP(17.625*(((C17+0.6*'Cooling Tower & Corrugated Fill'!$C$12))-32)/1.8/((((C17+0.6*'Cooling Tower & Corrugated Fill'!$C$12))-32)/1.8+243.04)))/('Cooling Tower & Corrugated Fill'!$C$14-(0.61094*EXP(17.625*(((C17+0.6*'Cooling Tower & Corrugated Fill'!$C$12))-32)/1.8/((((C17+0.6*'Cooling Tower & Corrugated Fill'!$C$12))-32)/1.8+243.04))))*(1061+0.444*((C17+0.6*'Cooling Tower & Corrugated Fill'!$C$12))))-('Merkel Solver'!$C$4+'Cooling Tower & Corrugated Fill'!$C$13*0.6*'Cooling Tower & Corrugated Fill'!$C$12) | G17: =(0.24*((C17+0.9*'Cooling Tower & Corrugated Fill'!$C$12))+0.62198*(0.61094*EXP(17.625*(((C17+0.9*'Cooling Tower & Corrugated Fill'!$C$12))-32)/1.8/((((C17+0.9*'Cooling Tower & Corrugated Fill'!$C$12))-32)/1.8+243.04)))/('Cooling Tower & Corrugated Fill'!$C$14-(0.61094*EXP(17.625*(((C17+0.9*'Cooling Tower & Corrugated Fill'!$C$12))-32)/1.8/((((C17+0.9*'Cooling Tower & Corrugated Fill'!$C$12))-32)/1.8+243.04))))*(1061+0.444*((C17+0.9*'Cooling Tower & Corrugated Fill'!$C$12))))-('Merkel Solver'!$C$4+'Cooling Tower & Corrugated Fill'!$C$13*0.9*'Cooling Tower & Corrugated Fill'!$C$12) | H17: =IF(MIN(D17:G17)<=0,99999,'Cooling Tower & Corrugated Fill'!$C$12/4*(1/D17+1/E17+1/F17+1/G17))
B18: 1.2 | C18: ='Dashboard'!$C$9+B18 | D18: =(0.24*((C18+0.1*'Cooling Tower & Corrugated Fill'!$C$12))+0.62198*(0.61094*EXP(17.625*(((C18+0.1*'Cooling Tower & Corrugated Fill'!$C$12))-32)/1.8/((((C18+0.1*'Cooling Tower & Corrugated Fill'!$C$12))-32)/1.8+243.04)))/('Cooling Tower & Corrugated Fill'!$C$14-(0.61094*EXP(17.625*(((C18+0.1*'Cooling Tower & Corrugated Fill'!$C$12))-32)/1.8/((((C18+0.1*'Cooling Tower & Corrugated Fill'!$C$12))-32)/1.8+243.04))))*(1061+0.444*((C18+0.1*'Cooling Tower & Corrugated Fill'!$C$12))))-('Merkel Solver'!$C$4+'Cooling Tower & Corrugated Fill'!$C$13*0.1*'Cooling Tower & Corrugated Fill'!$C$12) | E18: =(0.24*((C18+0.4*'Cooling Tower & Corrugated Fill'!$C$12))+0.62198*(0.61094*EXP(17.625*(((C18+0.4*'Cooling Tower & Corrugated Fill'!$C$12))-32)/1.8/((((C18+0.4*'Cooling Tower & Corrugated Fill'!$C$12))-32)/1.8+243.04)))/('Cooling Tower & Corrugated Fill'!$C$14-(0.61094*EXP(17.625*(((C18+0.4*'Cooling Tower & Corrugated Fill'!$C$12))-32)/1.8/((((C18+0.4*'Cooling Tower & Corrugated Fill'!$C$12))-32)/1.8+243.04))))*(1061+0.444*((C18+0.4*'Cooling Tower & Corrugated Fill'!$C$12))))-('Merkel Solver'!$C$4+'Cooling Tower & Corrugated Fill'!$C$13*0.4*'Cooling Tower & Corrugated Fill'!$C$12) | F18: =(0.24*((C18+0.6*'Cooling Tower & Corrugated Fill'!$C$12))+0.62198*(0.61094*EXP(17.625*(((C18+0.6*'Cooling Tower & Corrugated Fill'!$C$12))-32)/1.8/((((C18+0.6*'Cooling Tower & Corrugated Fill'!$C$12))-32)/1.8+243.04)))/('Cooling Tower & Corrugated Fill'!$C$14-(0.61094*EXP(17.625*(((C18+0.6*'Cooling Tower & Corrugated Fill'!$C$12))-32)/1.8/((((C18+0.6*'Cooling Tower & Corrugated Fill'!$C$12))-32)/1.8+243.04))))*(1061+0.444*((C18+0.6*'Cooling Tower & Corrugated Fill'!$C$12))))-('Merkel Solver'!$C$4+'Cooling Tower & Corrugated Fill'!$C$13*0.6*'Cooling Tower & Corrugated Fill'!$C$12) | G18: =(0.24*((C18+0.9*'Cooling Tower & Corrugated Fill'!$C$12))+0.62198*(0.61094*EXP(17.625*(((C18+0.9*'Cooling Tower & Corrugated Fill'!$C$12))-32)/1.8/((((C18+0.9*'Cooling Tower & Corrugated Fill'!$C$12))-32)/1.8+243.04)))/('Cooling Tower & Corrugated Fill'!$C$14-(0.61094*EXP(17.625*(((C18+0.9*'Cooling Tower & Corrugated Fill'!$C$12))-32)/1.8/((((C18+0.9*'Cooling Tower & Corrugated Fill'!$C$12))-32)/1.8+243.04))))*(1061+0.444*((C18+0.9*'Cooling Tower & Corrugated Fill'!$C$12))))-('Merkel Solver'!$C$4+'Cooling Tower & Corrugated Fill'!$C$13*0.9*'Cooling Tower & Corrugated Fill'!$C$12) | H18: =IF(MIN(D18:G18)<=0,99999,'Cooling Tower & Corrugated Fill'!$C$12/4*(1/D18+1/E18+1/F18+1/G18))
... B406: 40 | C406: ='Dashboard'!$C$9+B406 | D406: =(0.24*((C406+0.1*'Cooling Tower & Corrugated Fill'!$C$12))+0.62198*(0.61094*EXP(17.625*(((C406+0.1*'Cooling Tower & Corrugated Fill'!$C$12))-32)/1.8/((((C406+0.1*'Cooling Tower & Corrugated Fill'!$C$12))-32)/1.8+243.04)))/('Cooling Tower & Corrugated Fill'!$C$14-(0.61094*EXP(17.625*(((C406+0.1*'Cooling Tower & Corrugated Fill'!$C$12))-32)/1.8/((((C406+0.1*'Cooling Tower & Corrugated Fill'!$C$12))-32)/1.8+243.04))))*(1061+0.444*((C406+0.1*'Cooling Tower & Corrugated Fill'!$C$12))))-('Merkel Solver'!$C$4+'Cooling Tower & Corrugated Fill'!$C$13*0.1*'Cooling Tower & Corrugated Fill'!$C$12) | E406: =(0.24*((C406+0.4*'Cooling Tower & Corrugated Fill'!$C$12))+0.62198*(0.61094*EXP(17.625*(((C406+0.4*'Cooling Tower & Corrugated Fill'!$C$12))-32)/1.8/((((C406+0.4*'Cooling Tower & Corrugated Fill'!$C$12))-32)/1.8+243.04)))/('Cooling Tower & Corrugated Fill'!$C$14-(0.61094*EXP(17.625*(((C406+0.4*'Cooling Tower & Corrugated Fill'!$C$12))-32)/1.8/((((C406+0.4*'Cooling Tower & Corrugated Fill'!$C$12))-32)/1.8+243.04))))*(1061+0.444*((C406+0.4*'Cooling Tower & Corrugated Fill'!$C$12))))-('Merkel Solver'!$C$4+'Cooling Tower & Corrugated Fill'!$C$13*0.4*'Cooling Tower & Corrugated Fill'!$C$12) | F406: =(0.24*((C406+0.6*'Cooling Tower & Corrugated Fill'!$C$12))+0.62198*(0.61094*EXP(17.625*(((C406+0.6*'Cooling Tower & Corrugated Fill'!$C$12))-32)/1.8/((((C406+0.6*'Cooling Tower & Corrugated Fill'!$C$12))-32)/1.8+243.04)))/('Cooling Tower & Corrugated Fill'!$C$14-(0.61094*EXP(17.625*(((C406+0.6*'Cooling Tower & Corrugated Fill'!$C$12))-32)/1.8/((((C406+0.6*'Cooling Tower & Corrugated Fill'!$C$12))-32)/1.8+243.04))))*(1061+0.444*((C406+0.6*'Cooling Tower & Corrugated Fill'!$C$12))))-('Merkel Solver'!$C$4+'Cooling Tower & Corrugated Fill'!$C$13*0.6*'Cooling Tower & Corrugated Fill'!$C$12) | G406: =(0.24*((C406+0.9*'Cooling Tower & Corrugated Fill'!$C$12))+0.62198*(0.61094*EXP(17.625*(((C406+0.9*'Cooling Tower & Corrugated Fill'!$C$12))-32)/1.8/((((C406+0.9*'Cooling Tower & Corrugated Fill'!$C$12))-32)/1.8+243.04)))/('Cooling Tower & Corrugated Fill'!$C$14-(0.61094*EXP(17.625*(((C406+0.9*'Cooling Tower & Corrugated Fill'!$C$12))-32)/1.8/((((C406+0.9*'Cooling Tower & Corrugated Fill'!$C$12))-32)/1.8+243.04))))*(1061+0.444*((C406+0.9*'Cooling Tower & Corrugated Fill'!$C$12))))-('Merkel Solver'!$C$4+'Cooling Tower & Corrugated Fill'!$C$13*0.9*'Cooling Tower & Corrugated Fill'!$C$12) | H406: =IF(MIN(D406:G406)<=0,99999,'Cooling Tower & Corrugated Fill'!$C$12/4*(1/D406+1/E406+1/F406+1/G406))
